Workbook

Sheet Executive Dashboard
A1: PIPELINE EXECUTIVE DASHBOARD
A3: ="Period: May-26 to Dec-27 | Currency: SAR | Last refresh: " & TEXT('Pipeline Report'!H2,"dd-mmm-yyyy") -> Period: May-26 to Dec-27 | Currency: SAR | Last refresh: 05-May-2026
A5: PIPELINE — WEIGHTED | D5: MATERIALIZING (75%+ PROB) | G5: PROJECTED GP — WEIGHTED | J5: FREE CAPACITY BASELINE
A6: ='Pipeline Report'!AH67 -> 43332714 | D6: =SUMIFS('Pipeline Report'!AI6:AI65,'Pipeline Report'!E6:E65,">=0.75") -> 20217983 | G6: ='Pipeline Report'!AH137 -> 10833178 | J6: ='Pipeline Report'!G171 -> 88870
A8: ="Unweighted: " & TEXT('Pipeline Report'!AH66,"#,##0,,") & "M SAR" -> Unweighted: 64M SAR | D8: ="Across " & SUMPRODUCT(('Pipeline Report'!E6:E65>=0.75)*('Pipeline Report'!B6:B65<>"")) & " near-term deals" -> Across 18 near-term deals | G8: ="Unweighted GP: " & TEXT('Pipeline Report'!AH136,"#,##0,,") & "M | Margin: " & TEXT('Pipeline Report'!AH138,"0.0%") -> Unweighted GP: 16M | Margin: 25.0% | J8: ="Committed by Dec-26: " & TEXT('Pipeline Report'!S183,"#,##0") & " pallets (" & TEXT('Pipeline Report'!S185,"0.0%") & " utilization)" -> Committed by Dec-26: 24,220 pallets (27.3% utilization)
A10: 💰 FORECAST vs BUDGET — FY26
A11: FY26 REVENUE GAP | D11: FY26 GP GAP | G11: UNSOLD CAPACITY VALUE
A12: ='Forecast +75% - 100%'!P11 -> -12255269 | D12: ='Forecast +75% - 100%'!P19 -> -6454619.6 | G12: ='Forecast +75% - 100%'!P23 -> 3148980
A14: ="Forecast: " & TEXT('Forecast +75% - 100%'!P9,"#,##0.0,,") & "M | Budget: " & TEXT('Forecast +75% - 100%'!P10,"#,##0.0,,") & "M SAR" -> Forecast: 92.8M | Budget: 106.0M SAR | D14: ="Forecast GP: " & TEXT('Forecast +75% - 100%'!P17,"#,##0.0,,") & "M | Budget GP: " & TEXT('Forecast +75% - 100%'!P18,"#,##0.0,,") & "M SAR" -> Forecast GP: 7.1M | Budget GP: 13.6M SAR | G14: ="If " & TEXT('Forecast +75% - 100%'!O21,"#,##0") & " pallets stay unsold @ " & TEXT('Forecast +75% - 100%'!O22,"#,##0") & " SAR/pallet/mo" -> If 64,650 pallets stay unsold @ 48 SAR/pallet/mo
A16: 📊 PIPELINE BY STAGE
A17: Stage | B17: Probability | C17: # Deals | D17: Pipeline (Unwtd) | E17: Pipeline (Wtd) | F17: % of Total Wtd
A18: Contract Negotiation | B18: 0.9 | C18: =COUNTIF('Pipeline Report'!D6:D65,"Contract Negotiation") -> 3 | D18: =SUMIF('Pipeline Report'!D6:D65,"Contract Negotiation",'Pipeline Report'!AH6:AH65) -> 7100000 | E18: =SUMIF('Pipeline Report'!D6:D65,"Contract Negotiation",'Pipeline Report'!AI6:AI65) -> 6390000 | F18: =IFERROR(E18/$E$25,0) -> 0.14746365
A19: Shortlisted | B19: 0.75 | C19: =COUNTIF('Pipeline Report'!D6:D65,"Shortlisted") -> 5 | D19: =SUMIF('Pipeline Report'!D6:D65,"Shortlisted",'Pipeline Report'!AH6:AH65) -> 5578200 | E19: =SUMIF('Pipeline Report'!D6:D65,"Shortlisted",'Pipeline Report'!AI6:AI65) -> 4183650 | F19: =IFERROR(E19/$E$25,0) -> 0.09654715
A20: Proposal Sent | B20: 0.6 | C20: =COUNTIF('Pipeline Report'!D6:D65,"Proposal Sent") -> 25 | D20: =SUMIF('Pipeline Report'!D6:D65,"Proposal Sent",'Pipeline Report'!AH6:AH65) -> 36427328 | E20: =SUMIF('Pipeline Report'!D6:D65,"Proposal Sent",'Pipeline Report'!AI6:AI65) -> 21856397 | F20: =IFERROR(E20/$E$25,0) -> 0.50438561
A21: Qualified | B21: 0.4 | C21: =COUNTIF('Pipeline Report'!D6:D65,"Qualified") -> 1 | D21: =SUMIF('Pipeline Report'!D6:D65,"Qualified",'Pipeline Report'!AH6:AH65) -> 1345833.3 | E21: =SUMIF('Pipeline Report'!D6:D65,"Qualified",'Pipeline Report'!AI6:AI65) -> 538333.33 | F21: =IFERROR(E21/$E$25,0) -> 0.012423255
A22: Prospecting | B22: 0.2 | C22: =COUNTIF('Pipeline Report'!D6:D65,"Prospecting") -> 1 | D22: =SUMIF('Pipeline Report'!D6:D65,"Prospecting",'Pipeline Report'!AH6:AH65) -> 3600000 | E22: =SUMIF('Pipeline Report'!D6:D65,"Prospecting",'Pipeline Report'!AI6:AI65) -> 720000 | F22: =IFERROR(E22/$E$25,0) -> 0.016615622
A23: Closed Won | B23: 1 | C23: =COUNTIF('Pipeline Report'!D6:D65,"Closed Won") -> 10 | D23: =SUMIF('Pipeline Report'!D6:D65,"Closed Won",'Pipeline Report'!AH6:AH65) -> 9644333.3 | E23: =SUMIF('Pipeline Report'!D6:D65,"Closed Won",'Pipeline Report'!AI6:AI65) -> 9644333.3 | F23: =IFERROR(E23/$E$25,0) -> 0.22256472
A24: Closed Lost | B24: 0 | C24: =COUNTIF('Pipeline Report'!D6:D65,"Closed Lost") -> 0 | D24: =SUMIF('Pipeline Report'!D6:D65,"Closed Lost",'Pipeline Report'!AH6:AH65) -> 0 | E24: =SUMIF('Pipeline Report'!D6:D65,"Closed Lost",'Pipeline Report'!AI6:AI65) -> 0 | F24: =IFERROR(E24/$E$25,0) -> 0
A25: TOTAL | C25: =SUM(C18:C24) -> 45 | D25: =SUM(D18:D24) -> 63695695 | E25: =SUM(E18:E24) -> 43332714 | F25: =SUM(F18:F24) -> 1
A28: 🎯 TOP DEALS BY WEIGHTED VALUE — what's most likely to materialize
A29: # | B29: Customer | C29: Stage | D29: Probability | E29: Warehouse | F29: Go-Live | G29: ACV (SAR) | H29: Weighted (SAR)
A30: 1 | B30: =IFERROR(INDEX('Pipeline Report'!B6:B65,MATCH(LARGE('Pipeline Report'!AI6:AI65,1),'Pipeline Report'!AI6:AI65,0)),"") -> Kuehne & Nagel | C30: =IFERROR(INDEX('Pipeline Report'!D6:D65,MATCH(LARGE('Pipeline Report'!AI6:AI65,1),'Pipeline Report'!AI6:AI65,0)),"") -> Proposal Sent | D30: =IFERROR(INDEX('Pipeline Report'!E6:E65,MATCH(LARGE('Pipeline Report'!AI6:AI65,1),'Pipeline Report'!AI6:AI65,0)),0) -> 0.6 | E30: =IFERROR(INDEX('Pipeline Report'!F6:F65,MATCH(LARGE('Pipeline Report'!AI6:AI65,1),'Pipeline Report'!AI6:AI65,0)),"") -> RUH Tayba | F30: =IFERROR(INDEX('Pipeline Report'!G6:G65,MATCH(LARGE('Pipeline Report'!AI6:AI65,1),'Pipeline Report'!AI6:AI65,0)),"") -> 46327 | G30: =IFERROR(INDEX('Pipeline Report'!H6:H65,MATCH(LARGE('Pipeline Report'!AI6:AI65,1),'Pipeline Report'!AI6:AI65,0)),0) -> 6102000 | H30: =IFERROR(LARGE('Pipeline Report'!AI6:AI65,1),0) -> 4271400
A31: 2 | B31: =IFERROR(INDEX('Pipeline Report'!B6:B65,MATCH(LARGE('Pipeline Report'!AI6:AI65,2),'Pipeline Report'!AI6:AI65,0)),"") -> Tejoury | C31: =IFERROR(INDEX('Pipeline Report'!D6:D65,MATCH(LARGE('Pipeline Report'!AI6:AI65,2),'Pipeline Report'!AI6:AI65,0)),"") -> Proposal Sent | D31: =IFERROR(INDEX('Pipeline Report'!E6:E65,MATCH(LARGE('Pipeline Report'!AI6:AI65,2),'Pipeline Report'!AI6:AI65,0)),0) -> 0.6 | E31: =IFERROR(INDEX('Pipeline Report'!F6:F65,MATCH(LARGE('Pipeline Report'!AI6:AI65,2),'Pipeline Report'!AI6:AI65,0)),"") -> Jeddah Modon 3A | F31: =IFERROR(INDEX('Pipeline Report'!G6:G65,MATCH(LARGE('Pipeline Report'!AI6:AI65,2),'Pipeline Report'!AI6:AI65,0)),"") -> 46204 | G31: =IFERROR(INDEX('Pipeline Report'!H6:H65,MATCH(LARGE('Pipeline Report'!AI6:AI65,2),'Pipeline Report'!AI6:AI65,0)),0) -> 4400000 | H31: =IFERROR(LARGE('Pipeline Report'!AI6:AI65,2),0) -> 3960000
A32: 3 | B32: =IFERROR(INDEX('Pipeline Report'!B6:B65,MATCH(LARGE('Pipeline Report'!AI6:AI65,3),'Pipeline Report'!AI6:AI65,0)),"") -> NALCO Ecolab | C32: =IFERROR(INDEX('Pipeline Report'!D6:D65,MATCH(LARGE('Pipeline Report'!AI6:AI65,3),'Pipeline Report'!AI6:AI65,0)),"") -> Contract Negotiation | D32: =IFERROR(INDEX('Pipeline Report'!E6:E65,MATCH(LARGE('Pipeline Report'!AI6:AI65,3),'Pipeline Report'!AI6:AI65,0)),0) -> 0.9 | E32: =IFERROR(INDEX('Pipeline Report'!F6:F65,MATCH(LARGE('Pipeline Report'!AI6:AI65,3),'Pipeline Report'!AI6:AI65,0)),"") -> Dammam 2nd Ind -Tad WH | F32: =IFERROR(INDEX('Pipeline Report'!G6:G65,MATCH(LARGE('Pipeline Report'!AI6:AI65,3),'Pipeline Report'!AI6:AI65,0)),"") -> 46174 | G32: =IFERROR(INDEX('Pipeline Report'!H6:H65,MATCH(LARGE('Pipeline Report'!AI6:AI65,3),'Pipeline Report'!AI6:AI65,0)),0) -> 2400000 | H32: =IFERROR(LARGE('Pipeline Report'!AI6:AI65,3),0) -> 3420000
A33: 4 | B33: =IFERROR(INDEX('Pipeline Report'!B6:B65,MATCH(LARGE('Pipeline Report'!AI6:AI65,4),'Pipeline Report'!AI6:AI65,0)),"") -> PSA-BDP | C33: =IFERROR(INDEX('Pipeline Report'!D6:D65,MATCH(LARGE('Pipeline Report'!AI6:AI65,4),'Pipeline Report'!AI6:AI65,0)),"") -> Closed Won | D33: =IFERROR(INDEX('Pipeline Report'!E6:E65,MATCH(LARGE('Pipeline Report'!AI6:AI65,4),'Pipeline Report'!AI6:AI65,0)),0) -> 1 | E33: =IFERROR(INDEX('Pipeline Report'!F6:F65,MATCH(LARGE('Pipeline Report'!AI6:AI65,4),'Pipeline Report'!AI6:AI65,0)),"") -> Subcontractor | F33: =IFERROR(INDEX('Pipeline Report'!G6:G65,MATCH(LARGE('Pipeline Report'!AI6:AI65,4),'Pipeline Report'!AI6:AI65,0)),"") -> 46067 | G33: =IFERROR(INDEX('Pipeline Report'!H6:H65,MATCH(LARGE('Pipeline Report'!AI6:AI65,4),'Pipeline Report'!AI6:AI65,0)),0) -> 1800000 | H33: =IFERROR(LARGE('Pipeline Report'!AI6:AI65,4),0) -> 3000000
A34: 5 | B34: =IFERROR(INDEX('Pipeline Report'!B6:B65,MATCH(LARGE('Pipeline Report'!AI6:AI65,5),'Pipeline Report'!AI6:AI65,0)),"") -> Saudi National Bank | C34: =IFERROR(INDEX('Pipeline Report'!D6:D65,MATCH(LARGE('Pipeline Report'!AI6:AI65,5),'Pipeline Report'!AI6:AI65,0)),"") -> Proposal Sent | D34: =IFERROR(INDEX('Pipeline Report'!E6:E65,MATCH(LARGE('Pipeline Report'!AI6:AI65,5),'Pipeline Report'!AI6:AI65,0)),0) -> 0.6 | E34: =IFERROR(INDEX('Pipeline Report'!F6:F65,MATCH(LARGE('Pipeline Report'!AI6:AI65,5),'Pipeline Report'!AI6:AI65,0)),"") -> Contract Logistics | F34: =IFERROR(INDEX('Pipeline Report'!G6:G65,MATCH(LARGE('Pipeline Report'!AI6:AI65,5),'Pipeline Report'!AI6:AI65,0)),"") -> 46157 | G34: =IFERROR(INDEX('Pipeline Report'!H6:H65,MATCH(LARGE('Pipeline Report'!AI6:AI65,5),'Pipeline Report'!AI6:AI65,0)),0) -> 1975386 | H34: =IFERROR(LARGE('Pipeline Report'!AI6:AI65,5),0) -> 1975386
A35: 6 | B35: =IFERROR(INDEX('Pipeline Report'!B6:B65,MATCH(LARGE('Pipeline Report'!AI6:AI65,6),'Pipeline Report'!AI6:AI65,0)),"") -> Kuehne & Nagel | C35: =IFERROR(INDEX('Pipeline Report'!D6:D65,MATCH(LARGE('Pipeline Report'!AI6:AI65,6),'Pipeline Report'!AI6:AI65,0)),"") -> Proposal Sent | D35: =IFERROR(INDEX('Pipeline Report'!E6:E65,MATCH(LARGE('Pipeline Report'!AI6:AI65,6),'Pipeline Report'!AI6:AI65,0)),0) -> 0.6 | E35: =IFERROR(INDEX('Pipeline Report'!F6:F65,MATCH(LARGE('Pipeline Report'!AI6:AI65,6),'Pipeline Report'!AI6:AI65,0)),"") -> RUH Tayba | F35: =IFERROR(INDEX('Pipeline Report'!G6:G65,MATCH(LARGE('Pipeline Report'!AI6:AI65,6),'Pipeline Report'!AI6:AI65,0)),"") -> 46204 | G35: =IFERROR(INDEX('Pipeline Report'!H6:H65,MATCH(LARGE('Pipeline Report'!AI6:AI65,6),'Pipeline Report'!AI6:AI65,0)),0) -> 2025000 | H35: =IFERROR(LARGE('Pipeline Report'!AI6:AI65,6),0) -> 1822500
A36: 7 | B36: =IFERROR(INDEX('Pipeline Report'!B6:B65,MATCH(LARGE('Pipeline Report'!AI6:AI65,7),'Pipeline Report'!AI6:AI65,0)),"") -> Al Nahdi | C36: =IFERROR(INDEX('Pipeline Report'!D6:D65,MATCH(LARGE('Pipeline Report'!AI6:AI65,7),'Pipeline Report'!AI6:AI65,0)),"") -> Contract Negotiation | D36: =IFERROR(INDEX('Pipeline Report'!E6:E65,MATCH(LARGE('Pipeline Report'!AI6:AI65,7),'Pipeline Report'!AI6:AI65,0)),0) -> 0.9 | E36: =IFERROR(INDEX('Pipeline Report'!F6:F65,MATCH(LARGE('Pipeline Report'!AI6:AI65,7),'Pipeline Report'!AI6:AI65,0)),"") -> Jeddah Modon 3A | F36: =IFERROR(INDEX('Pipeline Report'!G6:G65,MATCH(LARGE('Pipeline Report'!AI6:AI65,7),'Pipeline Report'!AI6:AI65,0)),"") -> 46143 | G36: =IFERROR(INDEX('Pipeline Report'!H6:H65,MATCH(LARGE('Pipeline Report'!AI6:AI65,7),'Pipeline Report'!AI6:AI65,0)),0) -> 1080000 | H36: =IFERROR(LARGE('Pipeline Report'!AI6:AI65,7),0) -> 1620000
A37: 8 | B37: =IFERROR(INDEX('Pipeline Report'!B6:B65,MATCH(LARGE('Pipeline Report'!AI6:AI65,8),'Pipeline Report'!AI6:AI65,0)),"") -> Maaden | C37: =IFERROR(INDEX('Pipeline Report'!D6:D65,MATCH(LARGE('Pipeline Report'!AI6:AI65,8),'Pipeline Report'!AI6:AI65,0)),"") -> Closed Won | D37: =IFERROR(INDEX('Pipeline Report'!E6:E65,MATCH(LARGE('Pipeline Report'!AI6:AI65,8),'Pipeline Report'!AI6:AI65,0)),0) -> 1 | E37: =IFERROR(INDEX('Pipeline Report'!F6:F65,MATCH(LARGE('Pipeline Report'!AI6:AI65,8),'Pipeline Report'!AI6:AI65,0)),"") -> Jubail 1 | F37: =IFERROR(INDEX('Pipeline Report'!G6:G65,MATCH(LARGE('Pipeline Report'!AI6:AI65,8),'Pipeline Report'!AI6:AI65,0)),"") -> 46054 | G37: =IFERROR(INDEX('Pipeline Report'!H6:H65,MATCH(LARGE('Pipeline Report'!AI6:AI65,8),'Pipeline Report'!AI6:AI65,0)),0) -> 960000 | H37: =IFERROR(LARGE('Pipeline Report'!AI6:AI65,8),0) -> 1600000
A39: 🏭 WAREHOUSE CAPACITY — utilization at end of 2026
A40: Warehouse | B40: Baseline Free Space | C40: Committed (Dec-26) | D40: Remaining (Dec-26) | E40: Utilization %
A41: Dammam Port | B41: ='Pipeline Report'!G161 -> 4973 | C41: ='Pipeline Report'!S173 -> 300 | D41: ='Pipeline Report'!S161 -> 4673 | E41: =IFERROR(C41/B41,0) -> 0.060325759
A42: Dammam 2nd Ind | B42: ='Pipeline Report'!G162 -> 10047 | C42: ='Pipeline Report'!S174 -> 7090 | D42: ='Pipeline Report'!S162 -> 2957 | E42: =IFERROR(C42/B42,0) -> 0.70568329
A43: Jubail 1 | B43: ='Pipeline Report'!G163 -> 23706 | C43: ='Pipeline Report'!S175 -> 4330 | D43: ='Pipeline Report'!S163 -> 19376 | E43: =IFERROR(C43/B43,0) -> 0.18265418
A44: Jubail 2 | B44: ='Pipeline Report'!G164 -> 19247 | C44: ='Pipeline Report'!S176 -> 0 | D44: ='Pipeline Report'!S164 -> 19247 | E44: =IFERROR(C44/B44,0) -> 0
A45: Jubail Total | B45: ='Pipeline Report'!G165 -> 42953 | C45: ='Pipeline Report'!S177 -> 4330 | D45: ='Pipeline Report'!S165 -> 38623 | E45: =IFERROR(C45/B45,0) -> 0.10080786
A46: Jeddah Modon 3A | B46: ='Pipeline Report'!G166 -> 19713 | C46: ='Pipeline Report'!S178 -> 4500 | D46: ='Pipeline Report'!S166 -> 15213 | E46: =IFERROR(C46/B46,0) -> 0.22827576
A47: Jeddah Modon 3B | B47: ='Pipeline Report'!G167 -> 686 | C47: ='Pipeline Report'!S179 -> 5500 | D47: ='Pipeline Report'!S167 -> -4814 | E47: =IFERROR(C47/B47,0) -> 8.0174927
A48: RUH Tayba | B48: ='Pipeline Report'!G168 -> 2998 | C48: ='Pipeline Report'!S180 -> 0 | D48: ='Pipeline Report'!S168 -> 2998 | E48: =IFERROR(C48/B48,0) -> 0
A49: Subcontractor | B49: ='Pipeline Report'!G169 -> 7500 | C49: ='Pipeline Report'!S181 -> 2500 | D49: ='Pipeline Report'!S169 -> 5000 | E49: =IFERROR(C49/B49,0) -> 0.33333333
A50: Contract Logistics | B50: ='Pipeline Report'!G170 -> 0 | C50: ='Pipeline Report'!S182 -> 0 | D50: ='Pipeline Report'!S170 -> 0 | E50: =IFERROR(C50/B50,0) -> 0
A51: NETWORK TOTAL | B51: ='Pipeline Report'!G171 -> 88870 | C51: ='Pipeline Report'!S183 -> 24220 | D51: ='Pipeline Report'!S171 -> 64650 | E51: ='Pipeline Report'!S185 -> 0.27253291
A53: ⚠️ TOP RISKS & ACTIONS NEEDED — what requires leadership decision
A54: # | B54: Risk / Action | F54: Impact | H54: Owner | I54: Status
A55: L1 | B55: Move 5 deals from Proposal Sent (60%) → Contract Negotiation (90%) | F55: ="+" & TEXT(SUMIF('Pipeline Report'!D6:D65,"Proposal Sent",'Pipeline Report'!AH6:AH65)*5*0.3/COUNTIF('Pipeline Report'!D6:D65,"Proposal Sent"),"#,##0,,") & "M weighted SAR" -> +2M weighted SAR | H55: Sales (Hano) | I55: Open
A56: L2 | B56: Fix top 4 ACV flags: Tejoury, KN-Hample, Baxter, SNB | F56: +/− 3.7M SAR forecast accuracy | H56: Sales / Ops | I56: Open
A57: L3 | B57: Calibrate Cost % per deal (replace 75% global default) | F57: +/− 2-3M SAR GP visibility | H57: Finance | I57: Open
A58: L4 | B58: Resolve RUH Tayba over-commitment by Dec-26 | F58: ≈ 1M SAR at stake | H58: COO | I58: Decision needed
A59: L5 | B59: Formalize Subcontractor capacity (4,500 pallets without baseline) | F59: ≈ 675K SAR at stake | H59: COO | I59: Decision needed
A60: R1 | B60: Tejoury: ACV corrected (4.4M); Source CY in CRM still stale (660K) | F60: Cosmetic — flag only | H60: Hano | I60: Resolved data
A61: R2 | B61: 11 total data discrepancy flags — see Pipeline Report Notes column | F61: Review weekly | H61: Sales | I61: Review weekly
A63: ="For full deal-level detail, see Pipeline Report tab. Data refreshes when Pipeline Data or Warehouse Snapshot tabs are updated." -> For full deal-level detail, see Pipeline Report tab. Data refreshes when Pipeline Data or Warehouse Snapshot tabs are updated.

Sheet Pipeline Report
A1: PIPELINE ROLLING PROFITABILITY REPORT
A2: Period: | B2: May-26 to Dec-27 (20 months) | D2: Currency: | E2: SAR | G2: Last Updated: | H2: 05-May-2026 | J2: Source: | K2: Hala YTD WH Pipeline (Hano Oberholzer, 05-May-2026)
A4: 1. PIPELINE OPPORTUNITIES (Revenue)
A5: # | B5: Customer / Opportunity | C5: Opportunity Owner | D5: Stage | E5: Probability | F5: Warehouse Location | G5: Ops Go-Live Date | H5: Annual Contract Value | I5: Expected Revenue (Current Yr) | J5: Volume - Pallets | K5: Volume - SQM | L5: May-26 | M5: Jun-26 | N5: Jul-26 | O5: Aug-26 | P5: Sep-26 | Q5: Oct-26 | R5: Nov-26 | S5: Dec-26 | T5: 2026 Total | U5: Jan-27 | V5: Feb-27 | W5: Mar-27 | X5: Apr-27 | Y5: May-27 | Z5: Jun-27 | AA5: Jul-27 | AB5: Aug-27 | AC5: Sep-27 | AD5: Oct-27 | AE5: Nov-27 | AF5: Dec-27 | AG5: 2027 Total | AH5: Grand Total | AI5: Weighted Total | AJ5: Notes
A6: 1 | B6: =IF('Pipeline Data Input'!D3="","",'Pipeline Data Input'!D3) -> SLB | C6: =IF('Pipeline Data Input'!E3="","",'Pipeline Data Input'!E3) -> Yazan Darwish | D6: =IF('Pipeline Data Input'!J3="","",'Pipeline Data Input'!J3) -> Prospecting | E6: =IFERROR(VLOOKUP(D6,$B$211:$C$217,2,FALSE()),0) -> 0.2 | F6: =IF('Pipeline Data Input'!B3="","",IFERROR(VLOOKUP('Pipeline Data Input'!B3,'Pipeline Data Input'!$A$66:$B$80,2,FALSE()),'Pipeline Data Input'!B3)) -> Dammam 2nd Ind -Tad WH | G6: =IF('Pipeline Data Input'!K3="","",'Pipeline Data Input'!K3) -> 46204 | H6: =IF('Pipeline Data Input'!I3="",0,'Pipeline Data Input'!I3) -> 2400000 | I6: =T6 -> 1200000 | J6: =IF('Pipeline Data Input'!F3="",0,'Pipeline Data Input'!F3) -> 4000 | K6: =IF('Pipeline Data Input'!G3="",0,'Pipeline Data Input'!G3) -> 0 | L6: =IF(OR(G6="",H6=""),0,IF(DATE(2026,5,1)>=DATE(YEAR(G6),MONTH(G6),1),H6/12,0)) -> 0 | M6: =IF(OR(G6="",H6=""),0,IF(DATE(2026,6,1)>=DATE(YEAR(G6),MONTH(G6),1),H6/12,0)) -> 0 | N6: =IF(OR(G6="",H6=""),0,IF(DATE(2026,7,1)>=DATE(YEAR(G6),MONTH(G6),1),H6/12,0)) -> 200000 | O6: =IF(OR(G6="",H6=""),0,IF(DATE(2026,8,1)>=DATE(YEAR(G6),MONTH(G6),1),H6/12,0)) -> 200000 | P6: =IF(OR(G6="",H6=""),0,IF(DATE(2026,9,1)>=DATE(YEAR(G6),MONTH(G6),1),H6/12,0)) -> 200000 | Q6: =IF(OR(G6="",H6=""),0,IF(DATE(2026,10,1)>=DATE(YEAR(G6),MONTH(G6),1),H6/12,0)) -> 200000 | R6: =IF(OR(G6="",H6=""),0,IF(DATE(2026,11,1)>=DATE(YEAR(G6),MONTH(G6),1),H6/12,0)) -> 200000 | S6: =IF(OR(G6="",H6=""),0,IF(DATE(2026,12,1)>=DATE(YEAR(G6),MONTH(G6),1),H6/12,0)) -> 200000 | T6: =SUM(L6:S6) -> 1200000 | U6: =IF(OR(G6="",H6=""),0,IF(DATE(2027,1,1)>=DATE(YEAR(G6),MONTH(G6),1),H6/12,0)) -> 200000 | V6: =IF(OR(G6="",H6=""),0,IF(DATE(2027,2,1)>=DATE(YEAR(G6),MONTH(G6),1),H6/12,0)) -> 200000 | W6: =IF(OR(G6="",H6=""),0,IF(DATE(2027,3,1)>=DATE(YEAR(G6),MONTH(G6),1),H6/12,0)) -> 200000 | X6: =IF(OR(G6="",H6=""),0,IF(DATE(2027,4,1)>=DATE(YEAR(G6),MONTH(G6),1),H6/12,0)) -> 200000 | Y6: =IF(OR(G6="",H6=""),0,IF(DATE(2027,5,1)>=DATE(YEAR(G6),MONTH(G6),1),H6/12,0)) -> 200000 | Z6: =IF(OR(G6="",H6=""),0,IF(DATE(2027,6,1)>=DATE(YEAR(G6),MONTH(G6),1),H6/12,0)) -> 200000 | AA6: =IF(OR(G6="",H6=""),0,IF(DATE(2027,7,1)>=DATE(YEAR(G6),MONTH(G6),1),H6/12,0)) -> 200000 | AB6: =IF(OR(G6="",H6=""),0,IF(DATE(2027,8,1)>=DATE(YEAR(G6),MONTH(G6),1),H6/12,0)) -> 200000 | AC6: =IF(OR(G6="",H6=""),0,IF(DATE(2027,9,1)>=DATE(YEAR(G6),MONTH(G6),1),H6/12,0)) -> 200000 | AD6: =IF(OR(G6="",H6=""),0,IF(DATE(2027,10,1)>=DATE(YEAR(G6),MONTH(G6),1),H6/12,0)) -> 200000 | AE6: =IF(OR(G6="",H6=""),0,IF(DATE(2027,11,1)>=DATE(YEAR(G6),MONTH(G6),1),H6/12,0)) -> 200000 | AF6: =IF(OR(G6="",H6=""),0,IF(DATE(2027,12,1)>=DATE(YEAR(G6),MONTH(G6),1),H6/12,0)) -> 200000 | AG6: =SUM(U6:AF6) -> 2400000 | AH6: =T6+AG6 -> 3600000 | AI6: =IF(OR(E6="",AH6=""),"",E6*AH6) -> 720000 | AJ6: =IF('Pipeline Data Input'!M3="","",'Pipeline Data Input'!M3) -> Opp: ChampionX/DMM/WH/4000PP | Region: East
A7: 2 | B7: =IF('Pipeline Data Input'!D4="","",'Pipeline Data Input'!D4) -> NALCO Ecolab | C7: =IF('Pipeline Data Input'!E4="","",'Pipeline Data Input'!E4) -> Yazan Darwish | D7: =IF('Pipeline Data Input'!J4="","",'Pipeline Data Input'!J4) -> Contract Negotiation | E7: =IFERROR(VLOOKUP(D7,$B$211:$C$217,2,FALSE()),0) -> 0.9 | F7: =IF('Pipeline Data Input'!B4="","",IFERROR(VLOOKUP('Pipeline Data Input'!B4,'Pipeline Data Input'!$A$66:$B$80,2,FALSE()),'Pipeline Data Input'!B4)) -> Dammam 2nd Ind -Tad WH | G7: =IF('Pipeline Data Input'!K4="","",'Pipeline Data Input'!K4) -> 46174 | H7: =IF('Pipeline Data Input'!I4="",0,'Pipeline Data Input'!I4) -> 2400000 | I7: =T7 -> 1400000 | J7: =IF('Pipeline Data Input'!F4="",0,'Pipeline Data Input'!F4) -> 4000 | K7: =IF('Pipeline Data Input'!G4="",0,'Pipeline Data Input'!G4) -> 0 | L7: =IF(OR(G7="",H7=""),0,IF(DATE(2026,5,1)>=DATE(YEAR(G7),MONTH(G7),1),H7/12,0)) -> 0 | M7: =IF(OR(G7="",H7=""),0,IF(DATE(2026,6,1)>=DATE(YEAR(G7),MONTH(G7),1),H7/12,0)) -> 200000 | N7: =IF(OR(G7="",H7=""),0,IF(DATE(2026,7,1)>=DATE(YEAR(G7),MONTH(G7),1),H7/12,0)) -> 200000 | O7: =IF(OR(G7="",H7=""),0,IF(DATE(2026,8,1)>=DATE(YEAR(G7),MONTH(G7),1),H7/12,0)) -> 200000 | P7: =IF(OR(G7="",H7=""),0,IF(DATE(2026,9,1)>=DATE(YEAR(G7),MONTH(G7),1),H7/12,0)) -> 200000 | Q7: =IF(OR(G7="",H7=""),0,IF(DATE(2026,10,1)>=DATE(YEAR(G7),MONTH(G7),1),H7/12,0)) -> 200000 | R7: =IF(OR(G7="",H7=""),0,IF(DATE(2026,11,1)>=DATE(YEAR(G7),MONTH(G7),1),H7/12,0)) -> 200000 | S7: =IF(OR(G7="",H7=""),0,IF(DATE(2026,12,1)>=DATE(YEAR(G7),MONTH(G7),1),H7/12,0)) -> 200000 | T7: =SUM(L7:S7) -> 1400000 | U7: =IF(OR(G7="",H7=""),0,IF(DATE(2027,1,1)>=DATE(YEAR(G7),MONTH(G7),1),H7/12,0)) -> 200000 | V7: =IF(OR(G7="",H7=""),0,IF(DATE(2027,2,1)>=DATE(YEAR(G7),MONTH(G7),1),H7/12,0)) -> 200000 | W7: =IF(OR(G7="",H7=""),0,IF(DATE(2027,3,1)>=DATE(YEAR(G7),MONTH(G7),1),H7/12,0)) -> 200000 | X7: =IF(OR(G7="",H7=""),0,IF(DATE(2027,4,1)>=DATE(YEAR(G7),MONTH(G7),1),H7/12,0)) -> 200000 | Y7: =IF(OR(G7="",H7=""),0,IF(DATE(2027,5,1)>=DATE(YEAR(G7),MONTH(G7),1),H7/12,0)) -> 200000 | Z7: =IF(OR(G7="",H7=""),0,IF(DATE(2027,6,1)>=DATE(YEAR(G7),MONTH(G7),1),H7/12,0)) -> 200000 | AA7: =IF(OR(G7="",H7=""),0,IF(DATE(2027,7,1)>=DATE(YEAR(G7),MONTH(G7),1),H7/12,0)) -> 200000 | AB7: =IF(OR(G7="",H7=""),0,IF(DATE(2027,8,1)>=DATE(YEAR(G7),MONTH(G7),1),H7/12,0)) -> 200000 | AC7: =IF(OR(G7="",H7=""),0,IF(DATE(2027,9,1)>=DATE(YEAR(G7),MONTH(G7),1),H7/12,0)) -> 200000 | AD7: =IF(OR(G7="",H7=""),0,IF(DATE(2027,10,1)>=DATE(YEAR(G7),MONTH(G7),1),H7/12,0)) -> 200000 | AE7: =IF(OR(G7="",H7=""),0,IF(DATE(2027,11,1)>=DATE(YEAR(G7),MONTH(G7),1),H7/12,0)) -> 200000 | AF7: =IF(OR(G7="",H7=""),0,IF(DATE(2027,12,1)>=DATE(YEAR(G7),MONTH(G7),1),H7/12,0)) -> 200000 | AG7: =SUM(U7:AF7) -> 2400000 | AH7: =T7+AG7 -> 3800000 | AI7: =IF(OR(E7="",AH7=""),"",E7*AH7) -> 3420000 | AJ7: =IF('Pipeline Data Input'!M4="","",'Pipeline Data Input'!M4) -> Opp: NALCO/WH/DMM/4000PP | Region: East
A8: 3 | B8: =IF('Pipeline Data Input'!D5="","",'Pipeline Data Input'!D5) -> Synthomer ME | C8: =IF('Pipeline Data Input'!E5="","",'Pipeline Data Input'!E5) -> Yazan Darwish | D8: =IF('Pipeline Data Input'!J5="","",'Pipeline Data Input'!J5) -> Contract Negotiation | E8: =IFERROR(VLOOKUP(D8,$B$211:$C$217,2,FALSE()),0) -> 0.9 | F8: =IF('Pipeline Data Input'!B5="","",IFERROR(VLOOKUP('Pipeline Data Input'!B5,'Pipeline Data Input'!$A$66:$B$80,2,FALSE()),'Pipeline Data Input'!B5)) -> Dammam 2nd Ind -Tad WH | G8: =IF('Pipeline Data Input'!K5="","",'Pipeline Data Input'!K5) -> 46157 | H8: =IF('Pipeline Data Input'!I5="",0,'Pipeline Data Input'!I5) -> 900000 | I8: =T8 -> 600000 | J8: =IF('Pipeline Data Input'!F5="",0,'Pipeline Data Input'!F5) -> 1500 | K8: =IF('Pipeline Data Input'!G5="",0,'Pipeline Data Input'!G5) -> 0 | L8: =IF(OR(G8="",H8=""),0,IF(DATE(2026,5,1)>=DATE(YEAR(G8),MONTH(G8),1),H8/12,0)) -> 75000 | M8: =IF(OR(G8="",H8=""),0,IF(DATE(2026,6,1)>=DATE(YEAR(G8),MONTH(G8),1),H8/12,0)) -> 75000 | N8: =IF(OR(G8="",H8=""),0,IF(DATE(2026,7,1)>=DATE(YEAR(G8),MONTH(G8),1),H8/12,0)) -> 75000 | O8: =IF(OR(G8="",H8=""),0,IF(DATE(2026,8,1)>=DATE(YEAR(G8),MONTH(G8),1),H8/12,0)) -> 75000 | P8: =IF(OR(G8="",H8=""),0,IF(DATE(2026,9,1)>=DATE(YEAR(G8),MONTH(G8),1),H8/12,0)) -> 75000 | Q8: =IF(OR(G8="",H8=""),0,IF(DATE(2026,10,1)>=DATE(YEAR(G8),MONTH(G8),1),H8/12,0)) -> 75000 | R8: =IF(OR(G8="",H8=""),0,IF(DATE(2026,11,1)>=DATE(YEAR(G8),MONTH(G8),1),H8/12,0)) -> 75000 | S8: =IF(OR(G8="",H8=""),0,IF(DATE(2026,12,1)>=DATE(YEAR(G8),MONTH(G8),1),H8/12,0)) -> 75000 | T8: =SUM(L8:S8) -> 600000 | U8: =IF(OR(G8="",H8=""),0,IF(DATE(2027,1,1)>=DATE(YEAR(G8),MONTH(G8),1),H8/12,0)) -> 75000 | V8: =IF(OR(G8="",H8=""),0,IF(DATE(2027,2,1)>=DATE(YEAR(G8),MONTH(G8),1),H8/12,0)) -> 75000 | W8: =IF(OR(G8="",H8=""),0,IF(DATE(2027,3,1)>=DATE(YEAR(G8),MONTH(G8),1),H8/12,0)) -> 75000 | X8: =IF(OR(G8="",H8=""),0,IF(DATE(2027,4,1)>=DATE(YEAR(G8),MONTH(G8),1),H8/12,0)) -> 75000 | Y8: =IF(OR(G8="",H8=""),0,IF(DATE(2027,5,1)>=DATE(YEAR(G8),MONTH(G8),1),H8/12,0)) -> 75000 | Z8: =IF(OR(G8="",H8=""),0,IF(DATE(2027,6,1)>=DATE(YEAR(G8),MONTH(G8),1),H8/12,0)) -> 75000 | AA8: =IF(OR(G8="",H8=""),0,IF(DATE(2027,7,1)>=DATE(YEAR(G8),MONTH(G8),1),H8/12,0)) -> 75000 | AB8: =IF(OR(G8="",H8=""),0,IF(DATE(2027,8,1)>=DATE(YEAR(G8),MONTH(G8),1),H8/12,0)) -> 75000 | AC8: =IF(OR(G8="",H8=""),0,IF(DATE(2027,9,1)>=DATE(YEAR(G8),MONTH(G8),1),H8/12,0)) -> 75000 | AD8: =IF(OR(G8="",H8=""),0,IF(DATE(2027,10,1)>=DATE(YEAR(G8),MONTH(G8),1),H8/12,0)) -> 75000 | AE8: =IF(OR(G8="",H8=""),0,IF(DATE(2027,11,1)>=DATE(YEAR(G8),MONTH(G8),1),H8/12,0)) -> 75000 | AF8: =IF(OR(G8="",H8=""),0,IF(DATE(2027,12,1)>=DATE(YEAR(G8),MONTH(G8),1),H8/12,0)) -> 75000 | AG8: =SUM(U8:AF8) -> 900000 | AH8: =T8+AG8 -> 1500000 | AI8: =IF(OR(E8="",AH8=""),"",E8*AH8) -> 1350000 | AJ8: =IF('Pipeline Data Input'!M5="","",'Pipeline Data Input'!M5) -> Opp: Synthomer/WH/DMM/1500PP | Region: East
A9: 4 | B9: =IF('Pipeline Data Input'!D6="","",'Pipeline Data Input'!D6) -> Transworld Saudi Logistics | C9: =IF('Pipeline Data Input'!E6="","",'Pipeline Data Input'!E6) -> Yazan Darwish | D9: =IF('Pipeline Data Input'!J6="","",'Pipeline Data Input'!J6) -> Proposal Sent | E9: =IFERROR(VLOOKUP(D9,$B$211:$C$217,2,FALSE()),0) -> 0.6 | F9: =IF('Pipeline Data Input'!B6="","",IFERROR(VLOOKUP('Pipeline Data Input'!B6,'Pipeline Data Input'!$A$66:$B$80,2,FALSE()),'Pipeline Data Input'!B6)) -> Dammam 2nd Ind -Tad WH | G9: =IF('Pipeline Data Input'!K6="","",'Pipeline Data Input'!K6) -> 46143 | H9: =IF('Pipeline Data Input'!I6="",0,'Pipeline Data Input'!I6) -> 420000 | I9: =T9 -> 280000 | J9: =IF('Pipeline Data Input'!F6="",0,'Pipeline Data Input'!F6) -> 500 | K9: =IF('Pipeline Data Input'!G6="",0,'Pipeline Data Input'!G6) -> 0 | L9: =IF(OR(G9="",H9=""),0,IF(DATE(2026,5,1)>=DATE(YEAR(G9),MONTH(G9),1),H9/12,0)) -> 35000 | M9: =IF(OR(G9="",H9=""),0,IF(DATE(2026,6,1)>=DATE(YEAR(G9),MONTH(G9),1),H9/12,0)) -> 35000 | N9: =IF(OR(G9="",H9=""),0,IF(DATE(2026,7,1)>=DATE(YEAR(G9),MONTH(G9),1),H9/12,0)) -> 35000 | O9: =IF(OR(G9="",H9=""),0,IF(DATE(2026,8,1)>=DATE(YEAR(G9),MONTH(G9),1),H9/12,0)) -> 35000 | P9: =IF(OR(G9="",H9=""),0,IF(DATE(2026,9,1)>=DATE(YEAR(G9),MONTH(G9),1),H9/12,0)) -> 35000 | Q9: =IF(OR(G9="",H9=""),0,IF(DATE(2026,10,1)>=DATE(YEAR(G9),MONTH(G9),1),H9/12,0)) -> 35000 | R9: =IF(OR(G9="",H9=""),0,IF(DATE(2026,11,1)>=DATE(YEAR(G9),MONTH(G9),1),H9/12,0)) -> 35000 | S9: =IF(OR(G9="",H9=""),0,IF(DATE(2026,12,1)>=DATE(YEAR(G9),MONTH(G9),1),H9/12,0)) -> 35000 | T9: =SUM(L9:S9) -> 280000 | U9: =IF(OR(G9="",H9=""),0,IF(DATE(2027,1,1)>=DATE(YEAR(G9),MONTH(G9),1),H9/12,0)) -> 35000 | V9: =IF(OR(G9="",H9=""),0,IF(DATE(2027,2,1)>=DATE(YEAR(G9),MONTH(G9),1),H9/12,0)) -> 35000 | W9: =IF(OR(G9="",H9=""),0,IF(DATE(2027,3,1)>=DATE(YEAR(G9),MONTH(G9),1),H9/12,0)) -> 35000 | X9: =IF(OR(G9="",H9=""),0,IF(DATE(2027,4,1)>=DATE(YEAR(G9),MONTH(G9),1),H9/12,0)) -> 35000 | Y9: =IF(OR(G9="",H9=""),0,IF(DATE(2027,5,1)>=DATE(YEAR(G9),MONTH(G9),1),H9/12,0)) -> 35000 | Z9: =IF(OR(G9="",H9=""),0,IF(DATE(2027,6,1)>=DATE(YEAR(G9),MONTH(G9),1),H9/12,0)) -> 35000 | AA9: =IF(OR(G9="",H9=""),0,IF(DATE(2027,7,1)>=DATE(YEAR(G9),MONTH(G9),1),H9/12,0)) -> 35000 | AB9: =IF(OR(G9="",H9=""),0,IF(DATE(2027,8,1)>=DATE(YEAR(G9),MONTH(G9),1),H9/12,0)) -> 35000 | AC9: =IF(OR(G9="",H9=""),0,IF(DATE(2027,9,1)>=DATE(YEAR(G9),MONTH(G9),1),H9/12,0)) -> 35000 | AD9: =IF(OR(G9="",H9=""),0,IF(DATE(2027,10,1)>=DATE(YEAR(G9),MONTH(G9),1),H9/12,0)) -> 35000 | AE9: =IF(OR(G9="",H9=""),0,IF(DATE(2027,11,1)>=DATE(YEAR(G9),MONTH(G9),1),H9/12,0)) -> 35000 | AF9: =IF(OR(G9="",H9=""),0,IF(DATE(2027,12,1)>=DATE(YEAR(G9),MONTH(G9),1),H9/12,0)) -> 35000 | AG9: =SUM(U9:AF9) -> 420000 | AH9: =T9+AG9 -> 700000 | AI9: =IF(OR(E9="",AH9=""),"",E9*AH9) -> 420000 | AJ9: =IF('Pipeline Data Input'!M6="","",'Pipeline Data Input'!M6) -> Opp: Transworld/DMM/WH/500PP | Region: East
A10: 5 | B10: =IF('Pipeline Data Input'!D7="","",'Pipeline Data Input'!D7) -> Schmidt | C10: =IF('Pipeline Data Input'!E7="","",'Pipeline Data Input'!E7) -> Yazan Darwish | D10: =IF('Pipeline Data Input'!J7="","",'Pipeline Data Input'!J7) -> Proposal Sent | E10: =IFERROR(VLOOKUP(D10,$B$211:$C$217,2,FALSE()),0) -> 0.6 | F10: =IF('Pipeline Data Input'!B7="","",IFERROR(VLOOKUP('Pipeline Data Input'!B7,'Pipeline Data Input'!$A$66:$B$80,2,FALSE()),'Pipeline Data Input'!B7)) -> Dammam 2nd Ind -Tad WH | G10: =IF('Pipeline Data Input'!K7="","",'Pipeline Data Input'!K7) -> 46143 | H10: =IF('Pipeline Data Input'!I7="",0,'Pipeline Data Input'!I7) -> 264000 | I10: =T10 -> 176000 | J10: =IF('Pipeline Data Input'!F7="",0,'Pipeline Data Input'!F7) -> 400 | K10: =IF('Pipeline Data Input'!G7="",0,'Pipeline Data Input'!G7) -> 0 | L10: =IF(OR(G10="",H10=""),0,IF(DATE(2026,5,1)>=DATE(YEAR(G10),MONTH(G10),1),H10/12,0)) -> 22000 | M10: =IF(OR(G10="",H10=""),0,IF(DATE(2026,6,1)>=DATE(YEAR(G10),MONTH(G10),1),H10/12,0)) -> 22000 | N10: =IF(OR(G10="",H10=""),0,IF(DATE(2026,7,1)>=DATE(YEAR(G10),MONTH(G10),1),H10/12,0)) -> 22000 | O10: =IF(OR(G10="",H10=""),0,IF(DATE(2026,8,1)>=DATE(YEAR(G10),MONTH(G10),1),H10/12,0)) -> 22000 | P10: =IF(OR(G10="",H10=""),0,IF(DATE(2026,9,1)>=DATE(YEAR(G10),MONTH(G10),1),H10/12,0)) -> 22000 | Q10: =IF(OR(G10="",H10=""),0,IF(DATE(2026,10,1)>=DATE(YEAR(G10),MONTH(G10),1),H10/12,0)) -> 22000 | R10: =IF(OR(G10="",H10=""),0,IF(DATE(2026,11,1)>=DATE(YEAR(G10),MONTH(G10),1),H10/12,0)) -> 22000 | S10: =IF(OR(G10="",H10=""),0,IF(DATE(2026,12,1)>=DATE(YEAR(G10),MONTH(G10),1),H10/12,0)) -> 22000 | T10: =SUM(L10:S10) -> 176000 | U10: =IF(OR(G10="",H10=""),0,IF(DATE(2027,1,1)>=DATE(YEAR(G10),MONTH(G10),1),H10/12,0)) -> 22000 | V10: =IF(OR(G10="",H10=""),0,IF(DATE(2027,2,1)>=DATE(YEAR(G10),MONTH(G10),1),H10/12,0)) -> 22000 | W10: =IF(OR(G10="",H10=""),0,IF(DATE(2027,3,1)>=DATE(YEAR(G10),MONTH(G10),1),H10/12,0)) -> 22000 | X10: =IF(OR(G10="",H10=""),0,IF(DATE(2027,4,1)>=DATE(YEAR(G10),MONTH(G10),1),H10/12,0)) -> 22000 | Y10: =IF(OR(G10="",H10=""),0,IF(DATE(2027,5,1)>=DATE(YEAR(G10),MONTH(G10),1),H10/12,0)) -> 22000 | Z10: =IF(OR(G10="",H10=""),0,IF(DATE(2027,6,1)>=DATE(YEAR(G10),MONTH(G10),1),H10/12,0)) -> 22000 | AA10: =IF(OR(G10="",H10=""),0,IF(DATE(2027,7,1)>=DATE(YEAR(G10),MONTH(G10),1),H10/12,0)) -> 22000 | AB10: =IF(OR(G10="",H10=""),0,IF(DATE(2027,8,1)>=DATE(YEAR(G10),MONTH(G10),1),H10/12,0)) -> 22000 | AC10: =IF(OR(G10="",H10=""),0,IF(DATE(2027,9,1)>=DATE(YEAR(G10),MONTH(G10),1),H10/12,0)) -> 22000 | AD10: =IF(OR(G10="",H10=""),0,IF(DATE(2027,10,1)>=DATE(YEAR(G10),MONTH(G10),1),H10/12,0)) -> 22000 | AE10: =IF(OR(G10="",H10=""),0,IF(DATE(2027,11,1)>=DATE(YEAR(G10),MONTH(G10),1),H10/12,0)) -> 22000 | AF10: =IF(OR(G10="",H10=""),0,IF(DATE(2027,12,1)>=DATE(YEAR(G10),MONTH(G10),1),H10/12,0)) -> 22000 | AG10: =SUM(U10:AF10) -> 264000 | AH10: =T10+AG10 -> 440000 | AI10: =IF(OR(E10="",AH10=""),"",E10*AH10) -> 264000 | AJ10: =IF('Pipeline Data Input'!M7="","",'Pipeline Data Input'!M7) -> Opp: Schmidt/WH/DMM2/400PP | Region: East
A11: 6 | B11: =IF('Pipeline Data Input'!D8="","",'Pipeline Data Input'!D8) -> Zaghami | C11: =IF('Pipeline Data Input'!E8="","",'Pipeline Data Input'!E8) -> Yazan Darwish | D11: =IF('Pipeline Data Input'!J8="","",'Pipeline Data Input'!J8) -> Proposal Sent | E11: =IFERROR(VLOOKUP(D11,$B$211:$C$217,2,FALSE()),0) -> 0.6 | F11: =IF('Pipeline Data Input'!B8="","",IFERROR(VLOOKUP('Pipeline Data Input'!B8,'Pipeline Data Input'!$A$66:$B$80,2,FALSE()),'Pipeline Data Input'!B8)) -> Dammam 2nd Ind -Tad WH | G11: =IF('Pipeline Data Input'!K8="","",'Pipeline Data Input'!K8) -> 46235 | H11: =IF('Pipeline Data Input'!I8="",0,'Pipeline Data Input'!I8) -> 210000 | I11: =T11 -> 87500 | J11: =IF('Pipeline Data Input'!F8="",0,'Pipeline Data Input'!F8) -> 250 | K11: =IF('Pipeline Data Input'!G8="",0,'Pipeline Data Input'!G8) -> 0 | L11: =IF(OR(G11="",H11=""),0,IF(DATE(2026,5,1)>=DATE(YEAR(G11),MONTH(G11),1),H11/12,0)) -> 0 | M11: =IF(OR(G11="",H11=""),0,IF(DATE(2026,6,1)>=DATE(YEAR(G11),MONTH(G11),1),H11/12,0)) -> 0 | N11: =IF(OR(G11="",H11=""),0,IF(DATE(2026,7,1)>=DATE(YEAR(G11),MONTH(G11),1),H11/12,0)) -> 0 | O11: =IF(OR(G11="",H11=""),0,IF(DATE(2026,8,1)>=DATE(YEAR(G11),MONTH(G11),1),H11/12,0)) -> 17500 | P11: =IF(OR(G11="",H11=""),0,IF(DATE(2026,9,1)>=DATE(YEAR(G11),MONTH(G11),1),H11/12,0)) -> 17500 | Q11: =IF(OR(G11="",H11=""),0,IF(DATE(2026,10,1)>=DATE(YEAR(G11),MONTH(G11),1),H11/12,0)) -> 17500 | R11: =IF(OR(G11="",H11=""),0,IF(DATE(2026,11,1)>=DATE(YEAR(G11),MONTH(G11),1),H11/12,0)) -> 17500 | S11: =IF(OR(G11="",H11=""),0,IF(DATE(2026,12,1)>=DATE(YEAR(G11),MONTH(G11),1),H11/12,0)) -> 17500 | T11: =SUM(L11:S11) -> 87500 | U11: =IF(OR(G11="",H11=""),0,IF(DATE(2027,1,1)>=DATE(YEAR(G11),MONTH(G11),1),H11/12,0)) -> 17500 | V11: =IF(OR(G11="",H11=""),0,IF(DATE(2027,2,1)>=DATE(YEAR(G11),MONTH(G11),1),H11/12,0)) -> 17500 | W11: =IF(OR(G11="",H11=""),0,IF(DATE(2027,3,1)>=DATE(YEAR(G11),MONTH(G11),1),H11/12,0)) -> 17500 | X11: =IF(OR(G11="",H11=""),0,IF(DATE(2027,4,1)>=DATE(YEAR(G11),MONTH(G11),1),H11/12,0)) -> 17500 | Y11: =IF(OR(G11="",H11=""),0,IF(DATE(2027,5,1)>=DATE(YEAR(G11),MONTH(G11),1),H11/12,0)) -> 17500 | Z11: =IF(OR(G11="",H11=""),0,IF(DATE(2027,6,1)>=DATE(YEAR(G11),MONTH(G11),1),H11/12,0)) -> 17500 | AA11: =IF(OR(G11="",H11=""),0,IF(DATE(2027,7,1)>=DATE(YEAR(G11),MONTH(G11),1),H11/12,0)) -> 17500 | AB11: =IF(OR(G11="",H11=""),0,IF(DATE(2027,8,1)>=DATE(YEAR(G11),MONTH(G11),1),H11/12,0)) -> 17500 | AC11: =IF(OR(G11="",H11=""),0,IF(DATE(2027,9,1)>=DATE(YEAR(G11),MONTH(G11),1),H11/12,0)) -> 17500 | AD11: =IF(OR(G11="",H11=""),0,IF(DATE(2027,10,1)>=DATE(YEAR(G11),MONTH(G11),1),H11/12,0)) -> 17500 | AE11: =IF(OR(G11="",H11=""),0,IF(DATE(2027,11,1)>=DATE(YEAR(G11),MONTH(G11),1),H11/12,0)) -> 17500 | AF11: =IF(OR(G11="",H11=""),0,IF(DATE(2027,12,1)>=DATE(YEAR(G11),MONTH(G11),1),H11/12,0)) -> 17500 | AG11: =SUM(U11:AF11) -> 210000 | AH11: =T11+AG11 -> 297500 | AI11: =IF(OR(E11="",AH11=""),"",E11*AH11) -> 178500 | AJ11: =IF('Pipeline Data Input'!M8="","",'Pipeline Data Input'!M8) -> Opp: Zaghami/WH/DMM/250PP | Region: East
A12: 7 | B12: =IF('Pipeline Data Input'!D9="","",'Pipeline Data Input'!D9) -> Transworld Saudi Logistics | C12: =IF('Pipeline Data Input'!E9="","",'Pipeline Data Input'!E9) -> Yazan Darwish | D12: =IF('Pipeline Data Input'!J9="","",'Pipeline Data Input'!J9) -> Proposal Sent | E12: =IFERROR(VLOOKUP(D12,$B$211:$C$217,2,FALSE()),0) -> 0.6 | F12: =IF('Pipeline Data Input'!B9="","",IFERROR(VLOOKUP('Pipeline Data Input'!B9,'Pipeline Data Input'!$A$66:$B$80,2,FALSE()),'Pipeline Data Input'!B9)) -> Dammam 2nd Ind -Tad WH | G12: =IF('Pipeline Data Input'!K9="","",'Pipeline Data Input'!K9) -> 46174 | H12: =IF('Pipeline Data Input'!I9="",0,'Pipeline Data Input'!I9) -> 162500 | I12: =T12 -> 94791.667 | J12: =IF('Pipeline Data Input'!F9="",0,'Pipeline Data Input'!F9) -> 250 | K12: =IF('Pipeline Data Input'!G9="",0,'Pipeline Data Input'!G9) -> 0 | L12: =IF(OR(G12="",H12=""),0,IF(DATE(2026,5,1)>=DATE(YEAR(G12),MONTH(G12),1),H12/12,0)) -> 0 | M12: =IF(OR(G12="",H12=""),0,IF(DATE(2026,6,1)>=DATE(YEAR(G12),MONTH(G12),1),H12/12,0)) -> 13541.667 | N12: =IF(OR(G12="",H12=""),0,IF(DATE(2026,7,1)>=DATE(YEAR(G12),MONTH(G12),1),H12/12,0)) -> 13541.667 | O12: =IF(OR(G12="",H12=""),0,IF(DATE(2026,8,1)>=DATE(YEAR(G12),MONTH(G12),1),H12/12,0)) -> 13541.667 | P12: =IF(OR(G12="",H12=""),0,IF(DATE(2026,9,1)>=DATE(YEAR(G12),MONTH(G12),1),H12/12,0)) -> 13541.667 | Q12: =IF(OR(G12="",H12=""),0,IF(DATE(2026,10,1)>=DATE(YEAR(G12),MONTH(G12),1),H12/12,0)) -> 13541.667 | R12: =IF(OR(G12="",H12=""),0,IF(DATE(2026,11,1)>=DATE(YEAR(G12),MONTH(G12),1),H12/12,0)) -> 13541.667 | S12: =IF(OR(G12="",H12=""),0,IF(DATE(2026,12,1)>=DATE(YEAR(G12),MONTH(G12),1),H12/12,0)) -> 13541.667 | T12: =SUM(L12:S12) -> 94791.667 | U12: =IF(OR(G12="",H12=""),0,IF(DATE(2027,1,1)>=DATE(YEAR(G12),MONTH(G12),1),H12/12,0)) -> 13541.667 | V12: =IF(OR(G12="",H12=""),0,IF(DATE(2027,2,1)>=DATE(YEAR(G12),MONTH(G12),1),H12/12,0)) -> 13541.667 | W12: =IF(OR(G12="",H12=""),0,IF(DATE(2027,3,1)>=DATE(YEAR(G12),MONTH(G12),1),H12/12,0)) -> 13541.667 | X12: =IF(OR(G12="",H12=""),0,IF(DATE(2027,4,1)>=DATE(YEAR(G12),MONTH(G12),1),H12/12,0)) -> 13541.667 | Y12: =IF(OR(G12="",H12=""),0,IF(DATE(2027,5,1)>=DATE(YEAR(G12),MONTH(G12),1),H12/12,0)) -> 13541.667 | Z12: =IF(OR(G12="",H12=""),0,IF(DATE(2027,6,1)>=DATE(YEAR(G12),MONTH(G12),1),H12/12,0)) -> 13541.667 | AA12: =IF(OR(G12="",H12=""),0,IF(DATE(2027,7,1)>=DATE(YEAR(G12),MONTH(G12),1),H12/12,0)) -> 13541.667 | AB12: =IF(OR(G12="",H12=""),0,IF(DATE(2027,8,1)>=DATE(YEAR(G12),MONTH(G12),1),H12/12,0)) -> 13541.667 | AC12: =IF(OR(G12="",H12=""),0,IF(DATE(2027,9,1)>=DATE(YEAR(G12),MONTH(G12),1),H12/12,0)) -> 13541.667 | AD12: =IF(OR(G12="",H12=""),0,IF(DATE(2027,10,1)>=DATE(YEAR(G12),MONTH(G12),1),H12/12,0)) -> 13541.667 | AE12: =IF(OR(G12="",H12=""),0,IF(DATE(2027,11,1)>=DATE(YEAR(G12),MONTH(G12),1),H12/12,0)) -> 13541.667 | AF12: =IF(OR(G12="",H12=""),0,IF(DATE(2027,12,1)>=DATE(YEAR(G12),MONTH(G12),1),H12/12,0)) -> 13541.667 | AG12: =SUM(U12:AF12) -> 162500 | AH12: =T12+AG12 -> 257291.67 | AI12: =IF(OR(E12="",AH12=""),"",E12*AH12) -> 154375 | AJ12: =IF('Pipeline Data Input'!M9="","",'Pipeline Data Input'!M9) -> ⚠ Source Exp CY (113,750) ≠ ACV/12 implied (94,792) | Opp: Transworld/DMM/WH/250PP | Region: East
A13: 8 | B13: =IF('Pipeline Data Input'!D10="","",'Pipeline Data Input'!D10) -> i-Energy | C13: =IF('Pipeline Data Input'!E10="","",'Pipeline Data Input'!E10) -> Yazan Darwish | D13: =IF('Pipeline Data Input'!J10="","",'Pipeline Data Input'!J10) -> Proposal Sent | E13: =IFERROR(VLOOKUP(D13,$B$211:$C$217,2,FALSE()),0) -> 0.6 | F13: =IF('Pipeline Data Input'!B10="","",IFERROR(VLOOKUP('Pipeline Data Input'!B10,'Pipeline Data Input'!$A$66:$B$80,2,FALSE()),'Pipeline Data Input'!B10)) -> Dammam 2nd Ind -Tad WH | G13: =IF('Pipeline Data Input'!K10="","",'Pipeline Data Input'!K10) -> 46143 | H13: =IF('Pipeline Data Input'!I10="",0,'Pipeline Data Input'!I10) -> 150000 | I13: =T13 -> 100000 | J13: =IF('Pipeline Data Input'!F10="",0,'Pipeline Data Input'!F10) -> 250 | K13: =IF('Pipeline Data Input'!G10="",0,'Pipeline Data Input'!G10) -> 0 | L13: =IF(OR(G13="",H13=""),0,IF(DATE(2026,5,1)>=DATE(YEAR(G13),MONTH(G13),1),H13/12,0)) -> 12500 | M13: =IF(OR(G13="",H13=""),0,IF(DATE(2026,6,1)>=DATE(YEAR(G13),MONTH(G13),1),H13/12,0)) -> 12500 | N13: =IF(OR(G13="",H13=""),0,IF(DATE(2026,7,1)>=DATE(YEAR(G13),MONTH(G13),1),H13/12,0)) -> 12500 | O13: =IF(OR(G13="",H13=""),0,IF(DATE(2026,8,1)>=DATE(YEAR(G13),MONTH(G13),1),H13/12,0)) -> 12500 | P13: =IF(OR(G13="",H13=""),0,IF(DATE(2026,9,1)>=DATE(YEAR(G13),MONTH(G13),1),H13/12,0)) -> 12500 | Q13: =IF(OR(G13="",H13=""),0,IF(DATE(2026,10,1)>=DATE(YEAR(G13),MONTH(G13),1),H13/12,0)) -> 12500 | R13: =IF(OR(G13="",H13=""),0,IF(DATE(2026,11,1)>=DATE(YEAR(G13),MONTH(G13),1),H13/12,0)) -> 12500 | S13: =IF(OR(G13="",H13=""),0,IF(DATE(2026,12,1)>=DATE(YEAR(G13),MONTH(G13),1),H13/12,0)) -> 12500 | T13: =SUM(L13:S13) -> 100000 | U13: =IF(OR(G13="",H13=""),0,IF(DATE(2027,1,1)>=DATE(YEAR(G13),MONTH(G13),1),H13/12,0)) -> 12500 | V13: =IF(OR(G13="",H13=""),0,IF(DATE(2027,2,1)>=DATE(YEAR(G13),MONTH(G13),1),H13/12,0)) -> 12500 | W13: =IF(OR(G13="",H13=""),0,IF(DATE(2027,3,1)>=DATE(YEAR(G13),MONTH(G13),1),H13/12,0)) -> 12500 | X13: =IF(OR(G13="",H13=""),0,IF(DATE(2027,4,1)>=DATE(YEAR(G13),MONTH(G13),1),H13/12,0)) -> 12500 | Y13: =IF(OR(G13="",H13=""),0,IF(DATE(2027,5,1)>=DATE(YEAR(G13),MONTH(G13),1),H13/12,0)) -> 12500 | Z13: =IF(OR(G13="",H13=""),0,IF(DATE(2027,6,1)>=DATE(YEAR(G13),MONTH(G13),1),H13/12,0)) -> 12500 | AA13: =IF(OR(G13="",H13=""),0,IF(DATE(2027,7,1)>=DATE(YEAR(G13),MONTH(G13),1),H13/12,0)) -> 12500 | AB13: =IF(OR(G13="",H13=""),0,IF(DATE(2027,8,1)>=DATE(YEAR(G13),MONTH(G13),1),H13/12,0)) -> 12500 | AC13: =IF(OR(G13="",H13=""),0,IF(DATE(2027,9,1)>=DATE(YEAR(G13),MONTH(G13),1),H13/12,0)) -> 12500 | AD13: =IF(OR(G13="",H13=""),0,IF(DATE(2027,10,1)>=DATE(YEAR(G13),MONTH(G13),1),H13/12,0)) -> 12500 | AE13: =IF(OR(G13="",H13=""),0,IF(DATE(2027,11,1)>=DATE(YEAR(G13),MONTH(G13),1),H13/12,0)) -> 12500 | AF13: =IF(OR(G13="",H13=""),0,IF(DATE(2027,12,1)>=DATE(YEAR(G13),MONTH(G13),1),H13/12,0)) -> 12500 | AG13: =SUM(U13:AF13) -> 150000 | AH13: =T13+AG13 -> 250000 | AI13: =IF(OR(E13="",AH13=""),"",E13*AH13) -> 150000 | AJ13: =IF('Pipeline Data Input'!M10="","",'Pipeline Data Input'!M10) -> Opp: iEnergy/WH/DMM2/250PP | Region: East
A14: 9 | B14: =IF('Pipeline Data Input'!D11="","",'Pipeline Data Input'!D11) -> FMS Group | C14: =IF('Pipeline Data Input'!E11="","",'Pipeline Data Input'!E11) -> Yazan Darwish | D14: =IF('Pipeline Data Input'!J11="","",'Pipeline Data Input'!J11) -> Proposal Sent | E14: =IFERROR(VLOOKUP(D14,$B$211:$C$217,2,FALSE()),0) -> 0.6 | F14: =IF('Pipeline Data Input'!B11="","",IFERROR(VLOOKUP('Pipeline Data Input'!B11,'Pipeline Data Input'!$A$66:$B$80,2,FALSE()),'Pipeline Data Input'!B11)) -> Dammam 2nd Ind -Tad WH | G14: =IF('Pipeline Data Input'!K11="","",'Pipeline Data Input'!K11) -> 46174 | H14: =IF('Pipeline Data Input'!I11="",0,'Pipeline Data Input'!I11) -> 50000 | I14: =T14 -> 29166.667 | J14: =IF('Pipeline Data Input'!F11="",0,'Pipeline Data Input'!F11) -> 100 | K14: =IF('Pipeline Data Input'!G11="",0,'Pipeline Data Input'!G11) -> 0 | L14: =IF(OR(G14="",H14=""),0,IF(DATE(2026,5,1)>=DATE(YEAR(G14),MONTH(G14),1),H14/12,0)) -> 0 | M14: =IF(OR(G14="",H14=""),0,IF(DATE(2026,6,1)>=DATE(YEAR(G14),MONTH(G14),1),H14/12,0)) -> 4166.6667 | N14: =IF(OR(G14="",H14=""),0,IF(DATE(2026,7,1)>=DATE(YEAR(G14),MONTH(G14),1),H14/12,0)) -> 4166.6667 | O14: =IF(OR(G14="",H14=""),0,IF(DATE(2026,8,1)>=DATE(YEAR(G14),MONTH(G14),1),H14/12,0)) -> 4166.6667 | P14: =IF(OR(G14="",H14=""),0,IF(DATE(2026,9,1)>=DATE(YEAR(G14),MONTH(G14),1),H14/12,0)) -> 4166.6667 | Q14: =IF(OR(G14="",H14=""),0,IF(DATE(2026,10,1)>=DATE(YEAR(G14),MONTH(G14),1),H14/12,0)) -> 4166.6667 | R14: =IF(OR(G14="",H14=""),0,IF(DATE(2026,11,1)>=DATE(YEAR(G14),MONTH(G14),1),H14/12,0)) -> 4166.6667 | S14: =IF(OR(G14="",H14=""),0,IF(DATE(2026,12,1)>=DATE(YEAR(G14),MONTH(G14),1),H14/12,0)) -> 4166.6667 | T14: =SUM(L14:S14) -> 29166.667 | U14: =IF(OR(G14="",H14=""),0,IF(DATE(2027,1,1)>=DATE(YEAR(G14),MONTH(G14),1),H14/12,0)) -> 4166.6667 | V14: =IF(OR(G14="",H14=""),0,IF(DATE(2027,2,1)>=DATE(YEAR(G14),MONTH(G14),1),H14/12,0)) -> 4166.6667 | W14: =IF(OR(G14="",H14=""),0,IF(DATE(2027,3,1)>=DATE(YEAR(G14),MONTH(G14),1),H14/12,0)) -> 4166.6667 | X14: =IF(OR(G14="",H14=""),0,IF(DATE(2027,4,1)>=DATE(YEAR(G14),MONTH(G14),1),H14/12,0)) -> 4166.6667 | Y14: =IF(OR(G14="",H14=""),0,IF(DATE(2027,5,1)>=DATE(YEAR(G14),MONTH(G14),1),H14/12,0)) -> 4166.6667 | Z14: =IF(OR(G14="",H14=""),0,IF(DATE(2027,6,1)>=DATE(YEAR(G14),MONTH(G14),1),H14/12,0)) -> 4166.6667 | AA14: =IF(OR(G14="",H14=""),0,IF(DATE(2027,7,1)>=DATE(YEAR(G14),MONTH(G14),1),H14/12,0)) -> 4166.6667 | AB14: =IF(OR(G14="",H14=""),0,IF(DATE(2027,8,1)>=DATE(YEAR(G14),MONTH(G14),1),H14/12,0)) -> 4166.6667 | AC14: =IF(OR(G14="",H14=""),0,IF(DATE(2027,9,1)>=DATE(YEAR(G14),MONTH(G14),1),H14/12,0)) -> 4166.6667 | AD14: =IF(OR(G14="",H14=""),0,IF(DATE(2027,10,1)>=DATE(YEAR(G14),MONTH(G14),1),H14/12,0)) -> 4166.6667 | AE14: =IF(OR(G14="",H14=""),0,IF(DATE(2027,11,1)>=DATE(YEAR(G14),MONTH(G14),1),H14/12,0)) -> 4166.6667 | AF14: =IF(OR(G14="",H14=""),0,IF(DATE(2027,12,1)>=DATE(YEAR(G14),MONTH(G14),1),H14/12,0)) -> 4166.6667 | AG14: =SUM(U14:AF14) -> 50000 | AH14: =T14+AG14 -> 79166.667 | AI14: =IF(OR(E14="",AH14=""),"",E14*AH14) -> 47500 | AJ14: =IF('Pipeline Data Input'!M11="","",'Pipeline Data Input'!M11) -> ⚠ Source Exp CY (35,000) ≠ ACV/12 implied (29,167) | Opp: FMS/DMM/WH/100PP | Region: East
A15: 10 | B15: =IF('Pipeline Data Input'!D12="","",'Pipeline Data Input'!D12) -> El Ajou Group | C15: =IF('Pipeline Data Input'!E12="","",'Pipeline Data Input'!E12) -> Yazan Darwish | D15: =IF('Pipeline Data Input'!J12="","",'Pipeline Data Input'!J12) -> Proposal Sent | E15: =IFERROR(VLOOKUP(D15,$B$211:$C$217,2,FALSE()),0) -> 0.6 | F15: =IF('Pipeline Data Input'!B12="","",IFERROR(VLOOKUP('Pipeline Data Input'!B12,'Pipeline Data Input'!$A$66:$B$80,2,FALSE()),'Pipeline Data Input'!B12)) -> Dammam 2nd Ind -Tad WH | G15: =IF('Pipeline Data Input'!K12="","",'Pipeline Data Input'!K12) -> 46204 | H15: =IF('Pipeline Data Input'!I12="",0,'Pipeline Data Input'!I12) -> 78000 | I15: =T15 -> 39000 | J15: =IF('Pipeline Data Input'!F12="",0,'Pipeline Data Input'!F12) -> 100 | K15: =IF('Pipeline Data Input'!G12="",0,'Pipeline Data Input'!G12) -> 0 | L15: =IF(OR(G15="",H15=""),0,IF(DATE(2026,5,1)>=DATE(YEAR(G15),MONTH(G15),1),H15/12,0)) -> 0 | M15: =IF(OR(G15="",H15=""),0,IF(DATE(2026,6,1)>=DATE(YEAR(G15),MONTH(G15),1),H15/12,0)) -> 0 | N15: =IF(OR(G15="",H15=""),0,IF(DATE(2026,7,1)>=DATE(YEAR(G15),MONTH(G15),1),H15/12,0)) -> 6500 | O15: =IF(OR(G15="",H15=""),0,IF(DATE(2026,8,1)>=DATE(YEAR(G15),MONTH(G15),1),H15/12,0)) -> 6500 | P15: =IF(OR(G15="",H15=""),0,IF(DATE(2026,9,1)>=DATE(YEAR(G15),MONTH(G15),1),H15/12,0)) -> 6500 | Q15: =IF(OR(G15="",H15=""),0,IF(DATE(2026,10,1)>=DATE(YEAR(G15),MONTH(G15),1),H15/12,0)) -> 6500 | R15: =IF(OR(G15="",H15=""),0,IF(DATE(2026,11,1)>=DATE(YEAR(G15),MONTH(G15),1),H15/12,0)) -> 6500 | S15: =IF(OR(G15="",H15=""),0,IF(DATE(2026,12,1)>=DATE(YEAR(G15),MONTH(G15),1),H15/12,0)) -> 6500 | T15: =SUM(L15:S15) -> 39000 | U15: =IF(OR(G15="",H15=""),0,IF(DATE(2027,1,1)>=DATE(YEAR(G15),MONTH(G15),1),H15/12,0)) -> 6500 | V15: =IF(OR(G15="",H15=""),0,IF(DATE(2027,2,1)>=DATE(YEAR(G15),MONTH(G15),1),H15/12,0)) -> 6500 | W15: =IF(OR(G15="",H15=""),0,IF(DATE(2027,3,1)>=DATE(YEAR(G15),MONTH(G15),1),H15/12,0)) -> 6500 | X15: =IF(OR(G15="",H15=""),0,IF(DATE(2027,4,1)>=DATE(YEAR(G15),MONTH(G15),1),H15/12,0)) -> 6500 | Y15: =IF(OR(G15="",H15=""),0,IF(DATE(2027,5,1)>=DATE(YEAR(G15),MONTH(G15),1),H15/12,0)) -> 6500 | Z15: =IF(OR(G15="",H15=""),0,IF(DATE(2027,6,1)>=DATE(YEAR(G15),MONTH(G15),1),H15/12,0)) -> 6500 | AA15: =IF(OR(G15="",H15=""),0,IF(DATE(2027,7,1)>=DATE(YEAR(G15),MONTH(G15),1),H15/12,0)) -> 6500 | AB15: =IF(OR(G15="",H15=""),0,IF(DATE(2027,8,1)>=DATE(YEAR(G15),MONTH(G15),1),H15/12,0)) -> 6500 | AC15: =IF(OR(G15="",H15=""),0,IF(DATE(2027,9,1)>=DATE(YEAR(G15),MONTH(G15),1),H15/12,0)) -> 6500 | AD15: =IF(OR(G15="",H15=""),0,IF(DATE(2027,10,1)>=DATE(YEAR(G15),MONTH(G15),1),H15/12,0)) -> 6500 | AE15: =IF(OR(G15="",H15=""),0,IF(DATE(2027,11,1)>=DATE(YEAR(G15),MONTH(G15),1),H15/12,0)) -> 6500 | AF15: =IF(OR(G15="",H15=""),0,IF(DATE(2027,12,1)>=DATE(YEAR(G15),MONTH(G15),1),H15/12,0)) -> 6500 | AG15: =SUM(U15:AF15) -> 78000 | AH15: =T15+AG15 -> 117000 | AI15: =IF(OR(E15="",AH15=""),"",E15*AH15) -> 70200 | AJ15: =IF('Pipeline Data Input'!M12="","",'Pipeline Data Input'!M12) -> Opp: El Ajou Group/WH/DAMM2nd/100PP | Region: East
A16: 11 | B16: =IF('Pipeline Data Input'!D13="","",'Pipeline Data Input'!D13) -> JAS | C16: =IF('Pipeline Data Input'!E13="","",'Pipeline Data Input'!E13) -> Yazan Darwish | D16: =IF('Pipeline Data Input'!J13="","",'Pipeline Data Input'!J13) -> Shortlisted | E16: =IFERROR(VLOOKUP(D16,$B$211:$C$217,2,FALSE()),0) -> 0.75 | F16: =IF('Pipeline Data Input'!B13="","",IFERROR(VLOOKUP('Pipeline Data Input'!B13,'Pipeline Data Input'!$A$66:$B$80,2,FALSE()),'Pipeline Data Input'!B13)) -> Jubail 1 | G16: =IF('Pipeline Data Input'!K13="","",'Pipeline Data Input'!K13) -> 46174 | H16: =IF('Pipeline Data Input'!I13="",0,'Pipeline Data Input'!I13) -> 924000 | I16: =T16 -> 539000 | J16: =IF('Pipeline Data Input'!F13="",0,'Pipeline Data Input'!F13) -> 1400 | K16: =IF('Pipeline Data Input'!G13="",0,'Pipeline Data Input'!G13) -> 0 | L16: =IF(OR(G16="",H16=""),0,IF(DATE(2026,5,1)>=DATE(YEAR(G16),MONTH(G16),1),H16/12,0)) -> 0 | M16: =IF(OR(G16="",H16=""),0,IF(DATE(2026,6,1)>=DATE(YEAR(G16),MONTH(G16),1),H16/12,0)) -> 77000 | N16: =IF(OR(G16="",H16=""),0,IF(DATE(2026,7,1)>=DATE(YEAR(G16),MONTH(G16),1),H16/12,0)) -> 77000 | O16: =IF(OR(G16="",H16=""),0,IF(DATE(2026,8,1)>=DATE(YEAR(G16),MONTH(G16),1),H16/12,0)) -> 77000 | P16: =IF(OR(G16="",H16=""),0,IF(DATE(2026,9,1)>=DATE(YEAR(G16),MONTH(G16),1),H16/12,0)) -> 77000 | Q16: =IF(OR(G16="",H16=""),0,IF(DATE(2026,10,1)>=DATE(YEAR(G16),MONTH(G16),1),H16/12,0)) -> 77000 | R16: =IF(OR(G16="",H16=""),0,IF(DATE(2026,11,1)>=DATE(YEAR(G16),MONTH(G16),1),H16/12,0)) -> 77000 | S16: =IF(OR(G16="",H16=""),0,IF(DATE(2026,12,1)>=DATE(YEAR(G16),MONTH(G16),1),H16/12,0)) -> 77000 | T16: =SUM(L16:S16) -> 539000 | U16: =IF(OR(G16="",H16=""),0,IF(DATE(2027,1,1)>=DATE(YEAR(G16),MONTH(G16),1),H16/12,0)) -> 77000 | V16: =IF(OR(G16="",H16=""),0,IF(DATE(2027,2,1)>=DATE(YEAR(G16),MONTH(G16),1),H16/12,0)) -> 77000 | W16: =IF(OR(G16="",H16=""),0,IF(DATE(2027,3,1)>=DATE(YEAR(G16),MONTH(G16),1),H16/12,0)) -> 77000 | X16: =IF(OR(G16="",H16=""),0,IF(DATE(2027,4,1)>=DATE(YEAR(G16),MONTH(G16),1),H16/12,0)) -> 77000 | Y16: =IF(OR(G16="",H16=""),0,IF(DATE(2027,5,1)>=DATE(YEAR(G16),MONTH(G16),1),H16/12,0)) -> 77000 | Z16: =IF(OR(G16="",H16=""),0,IF(DATE(2027,6,1)>=DATE(YEAR(G16),MONTH(G16),1),H16/12,0)) -> 77000 | AA16: =IF(OR(G16="",H16=""),0,IF(DATE(2027,7,1)>=DATE(YEAR(G16),MONTH(G16),1),H16/12,0)) -> 77000 | AB16: =IF(OR(G16="",H16=""),0,IF(DATE(2027,8,1)>=DATE(YEAR(G16),MONTH(G16),1),H16/12,0)) -> 77000 | AC16: =IF(OR(G16="",H16=""),0,IF(DATE(2027,9,1)>=DATE(YEAR(G16),MONTH(G16),1),H16/12,0)) -> 77000 | AD16: =IF(OR(G16="",H16=""),0,IF(DATE(2027,10,1)>=DATE(YEAR(G16),MONTH(G16),1),H16/12,0)) -> 77000 | AE16: =IF(OR(G16="",H16=""),0,IF(DATE(2027,11,1)>=DATE(YEAR(G16),MONTH(G16),1),H16/12,0)) -> 77000 | AF16: =IF(OR(G16="",H16=""),0,IF(DATE(2027,12,1)>=DATE(YEAR(G16),MONTH(G16),1),H16/12,0)) -> 77000 | AG16: =SUM(U16:AF16) -> 924000 | AH16: =T16+AG16 -> 1463000 | AI16: =IF(OR(E16="",AH16=""),"",E16*AH16) -> 1097250 | AJ16: =IF('Pipeline Data Input'!M13="","",'Pipeline Data Input'!M13) -> Opp: JAS/WH/JUB/1400PP | Region: East
A17: 12 | B17: =IF('Pipeline Data Input'!D14="","",'Pipeline Data Input'!D14) -> LX Pantos Logistics | C17: =IF('Pipeline Data Input'!E14="","",'Pipeline Data Input'!E14) -> Yazan Darwish | D17: =IF('Pipeline Data Input'!J14="","",'Pipeline Data Input'!J14) -> Shortlisted | E17: =IFERROR(VLOOKUP(D17,$B$211:$C$217,2,FALSE()),0) -> 0.75 | F17: =IF('Pipeline Data Input'!B14="","",IFERROR(VLOOKUP('Pipeline Data Input'!B14,'Pipeline Data Input'!$A$66:$B$80,2,FALSE()),'Pipeline Data Input'!B14)) -> Jubail 1 | G17: =IF('Pipeline Data Input'!K14="","",'Pipeline Data Input'!K14) -> 46143 | H17: =IF('Pipeline Data Input'!I14="",0,'Pipeline Data Input'!I14) -> 726000 | I17: =T17 -> 484000 | J17: =IF('Pipeline Data Input'!F14="",0,'Pipeline Data Input'!F14) -> 1000 | K17: =IF('Pipeline Data Input'!G14="",0,'Pipeline Data Input'!G14) -> 0 | L17: =IF(OR(G17="",H17=""),0,IF(DATE(2026,5,1)>=DATE(YEAR(G17),MONTH(G17),1),H17/12,0)) -> 60500 | M17: =IF(OR(G17="",H17=""),0,IF(DATE(2026,6,1)>=DATE(YEAR(G17),MONTH(G17),1),H17/12,0)) -> 60500 | N17: =IF(OR(G17="",H17=""),0,IF(DATE(2026,7,1)>=DATE(YEAR(G17),MONTH(G17),1),H17/12,0)) -> 60500 | O17: =IF(OR(G17="",H17=""),0,IF(DATE(2026,8,1)>=DATE(YEAR(G17),MONTH(G17),1),H17/12,0)) -> 60500 | P17: =IF(OR(G17="",H17=""),0,IF(DATE(2026,9,1)>=DATE(YEAR(G17),MONTH(G17),1),H17/12,0)) -> 60500 | Q17: =IF(OR(G17="",H17=""),0,IF(DATE(2026,10,1)>=DATE(YEAR(G17),MONTH(G17),1),H17/12,0)) -> 60500 | R17: =IF(OR(G17="",H17=""),0,IF(DATE(2026,11,1)>=DATE(YEAR(G17),MONTH(G17),1),H17/12,0)) -> 60500 | S17: =IF(OR(G17="",H17=""),0,IF(DATE(2026,12,1)>=DATE(YEAR(G17),MONTH(G17),1),H17/12,0)) -> 60500 | T17: =SUM(L17:S17) -> 484000 | U17: =IF(OR(G17="",H17=""),0,IF(DATE(2027,1,1)>=DATE(YEAR(G17),MONTH(G17),1),H17/12,0)) -> 60500 | V17: =IF(OR(G17="",H17=""),0,IF(DATE(2027,2,1)>=DATE(YEAR(G17),MONTH(G17),1),H17/12,0)) -> 60500 | W17: =IF(OR(G17="",H17=""),0,IF(DATE(2027,3,1)>=DATE(YEAR(G17),MONTH(G17),1),H17/12,0)) -> 60500 | X17: =IF(OR(G17="",H17=""),0,IF(DATE(2027,4,1)>=DATE(YEAR(G17),MONTH(G17),1),H17/12,0)) -> 60500 | Y17: =IF(OR(G17="",H17=""),0,IF(DATE(2027,5,1)>=DATE(YEAR(G17),MONTH(G17),1),H17/12,0)) -> 60500 | Z17: =IF(OR(G17="",H17=""),0,IF(DATE(2027,6,1)>=DATE(YEAR(G17),MONTH(G17),1),H17/12,0)) -> 60500 | AA17: =IF(OR(G17="",H17=""),0,IF(DATE(2027,7,1)>=DATE(YEAR(G17),MONTH(G17),1),H17/12,0)) -> 60500 | AB17: =IF(OR(G17="",H17=""),0,IF(DATE(2027,8,1)>=DATE(YEAR(G17),MONTH(G17),1),H17/12,0)) -> 60500 | AC17: =IF(OR(G17="",H17=""),0,IF(DATE(2027,9,1)>=DATE(YEAR(G17),MONTH(G17),1),H17/12,0)) -> 60500 | AD17: =IF(OR(G17="",H17=""),0,IF(DATE(2027,10,1)>=DATE(YEAR(G17),MONTH(G17),1),H17/12,0)) -> 60500 | AE17: =IF(OR(G17="",H17=""),0,IF(DATE(2027,11,1)>=DATE(YEAR(G17),MONTH(G17),1),H17/12,0)) -> 60500 | AF17: =IF(OR(G17="",H17=""),0,IF(DATE(2027,12,1)>=DATE(YEAR(G17),MONTH(G17),1),H17/12,0)) -> 60500 | AG17: =SUM(U17:AF17) -> 726000 | AH17: =T17+AG17 -> 1210000 | AI17: =IF(OR(E17="",AH17=""),"",E17*AH17) -> 907500 | AJ17: =IF('Pipeline Data Input'!M14="","",'Pipeline Data Input'!M14) -> Opp: LXPantos/WH/JUB1/1000PP | Region: East
... A65: 60 | B65: =IF('Pipeline Data Input'!D62="","",'Pipeline Data Input'!D62) | C65: =IF('Pipeline Data Input'!E62="","",'Pipeline Data Input'!E62) | D65: =IF('Pipeline Data Input'!J62="","",'Pipeline Data Input'!J62) | E65: =IFERROR(VLOOKUP(D65,$B$211:$C$217,2,FALSE()),0) -> 0 | F65: =IF('Pipeline Data Input'!B62="","",IFERROR(VLOOKUP('Pipeline Data Input'!B62,'Pipeline Data Input'!$A$66:$B$80,2,FALSE()),'Pipeline Data Input'!B62)) | G65: =IF('Pipeline Data Input'!K62="","",'Pipeline Data Input'!K62) | H65: =IF('Pipeline Data Input'!I62="",0,'Pipeline Data Input'!I62) -> 0 | I65: =T65 -> 0 | J65: =IF('Pipeline Data Input'!F62="",0,'Pipeline Data Input'!F62) -> 0 | K65: =IF('Pipeline Data Input'!G62="",0,'Pipeline Data Input'!G62) -> 0 | L65: =IF(OR(G65="",H65=""),0,IF(DATE(2026,5,1)>=DATE(YEAR(G65),MONTH(G65),1),H65/12,0)) -> 0 | M65: =IF(OR(G65="",H65=""),0,IF(DATE(2026,6,1)>=DATE(YEAR(G65),MONTH(G65),1),H65/12,0)) -> 0 | N65: =IF(OR(G65="",H65=""),0,IF(DATE(2026,7,1)>=DATE(YEAR(G65),MONTH(G65),1),H65/12,0)) -> 0 | O65: =IF(OR(G65="",H65=""),0,IF(DATE(2026,8,1)>=DATE(YEAR(G65),MONTH(G65),1),H65/12,0)) -> 0 | P65: =IF(OR(G65="",H65=""),0,IF(DATE(2026,9,1)>=DATE(YEAR(G65),MONTH(G65),1),H65/12,0)) -> 0 | Q65: =IF(OR(G65="",H65=""),0,IF(DATE(2026,10,1)>=DATE(YEAR(G65),MONTH(G65),1),H65/12,0)) -> 0 | R65: =IF(OR(G65="",H65=""),0,IF(DATE(2026,11,1)>=DATE(YEAR(G65),MONTH(G65),1),H65/12,0)) -> 0 | S65: =IF(OR(G65="",H65=""),0,IF(DATE(2026,12,1)>=DATE(YEAR(G65),MONTH(G65),1),H65/12,0)) -> 0 | T65: =SUM(L65:S65) -> 0 | U65: =IF(OR(G65="",H65=""),0,IF(DATE(2027,1,1)>=DATE(YEAR(G65),MONTH(G65),1),H65/12,0)) -> 0 | V65: =IF(OR(G65="",H65=""),0,IF(DATE(2027,2,1)>=DATE(YEAR(G65),MONTH(G65),1),H65/12,0)) -> 0 | W65: =IF(OR(G65="",H65=""),0,IF(DATE(2027,3,1)>=DATE(YEAR(G65),MONTH(G65),1),H65/12,0)) -> 0 | X65: =IF(OR(G65="",H65=""),0,IF(DATE(2027,4,1)>=DATE(YEAR(G65),MONTH(G65),1),H65/12,0)) -> 0 | Y65: =IF(OR(G65="",H65=""),0,IF(DATE(2027,5,1)>=DATE(YEAR(G65),MONTH(G65),1),H65/12,0)) -> 0 | Z65: =IF(OR(G65="",H65=""),0,IF(DATE(2027,6,1)>=DATE(YEAR(G65),MONTH(G65),1),H65/12,0)) -> 0 | AA65: =IF(OR(G65="",H65=""),0,IF(DATE(2027,7,1)>=DATE(YEAR(G65),MONTH(G65),1),H65/12,0)) -> 0 | AB65: =IF(OR(G65="",H65=""),0,IF(DATE(2027,8,1)>=DATE(YEAR(G65),MONTH(G65),1),H65/12,0)) -> 0 | AC65: =IF(OR(G65="",H65=""),0,IF(DATE(2027,9,1)>=DATE(YEAR(G65),MONTH(G65),1),H65/12,0)) -> 0 | AD65: =IF(OR(G65="",H65=""),0,IF(DATE(2027,10,1)>=DATE(YEAR(G65),MONTH(G65),1),H65/12,0)) -> 0 | AE65: =IF(OR(G65="",H65=""),0,IF(DATE(2027,11,1)>=DATE(YEAR(G65),MONTH(G65),1),H65/12,0)) -> 0 | AF65: =IF(OR(G65="",H65=""),0,IF(DATE(2027,12,1)>=DATE(YEAR(G65),MONTH(G65),1),H65/12,0)) -> 0 | AG65: =SUM(U65:AF65) -> 0 | AH65: =T65+AG65 -> 0 | AI65: =IF(OR(E65="",AH65=""),"",E65*AH65) -> 0 | AJ65: =IF('Pipeline Data Input'!M62="","",'Pipeline Data Input'!M62)
B66: TOTAL PIPELINE (Unweighted) | H66: =SUM(H6:H65) -> 42367332 | I66: =SUM(I6:I65) -> 21328363 | J66: =SUM(J6:J65) -> 49820 | K66: =SUM(K6:K65) -> 26145 | L66: =SUM(L6:L65) -> 1016669.3 | M66: =SUM(M6:M65) -> 1696194.3 | N66: =SUM(N6:N65) -> 2678777.7 | O66: =SUM(O6:O65) -> 2831277.7 | ... S66: =SUM(S6:S65) -> 3530611 | T66: =SUM(L66:S66) -> 21328363 | U66: =SUM(U6:U65) -> 3530611 | V66: =SUM(V6:V65) -> 3530611 | W66: =SUM(W6:W65) -> 3530611 | X66: =SUM(X6:X65) -> 3530611 | Y66: =SUM(Y6:Y65) -> 3530611 | Z66: =SUM(Z6:Z65) -> 3530611 | AA66: =SUM(AA6:AA65) -> 3530611 | AB66: =SUM(AB6:AB65) -> 3530611 | ... AF66: =SUM(AF6:AF65) -> 3530611 | AG66: =SUM(U66:AF66) -> 42367332 | AH66: =T66+AG66 -> 63695695
B67: TOTAL PIPELINE (Probability-Weighted) | H67: =SUMPRODUCT(E6:E65,H6:H65) -> 28448479 | I67: =SUMPRODUCT(E6:E65,I6:I65) -> 14884234 | J67: =SUM(J6:J65) -> 49820 | K67: =SUM(K6:K65) -> 26145 | L67: =SUMPRODUCT(E6:E65,L6:L65) -> 861463.27 | M67: =SUMPRODUCT(E6:E65,M6:M65) -> 1339431.6 | N67: =SUMPRODUCT(E6:E65,N6:N65) -> 1859606.6 | O67: =SUMPRODUCT(E6:E65,O6:O65) -> 1951106.6 | P67: =SUMPRODUCT(E6:E65,P6:P65) -> 2065606.6 | Q67: =SUMPRODUCT(E6:E65,Q6:Q65) -> 2065606.6 | R67: =SUMPRODUCT(E6:E65,R6:R65) -> 2370706.6 | S67: =SUMPRODUCT(E6:E65,S6:S65) -> 2370706.6 | T67: =SUM(L67:S67) -> 14884234 | U67: =SUMPRODUCT(E6:E65,U6:U65) -> 2370706.6 | V67: =SUMPRODUCT(E6:E65,V6:V65) -> 2370706.6 | W67: =SUMPRODUCT(E6:E65,W6:W65) -> 2370706.6 | X67: =SUMPRODUCT(E6:E65,X6:X65) -> 2370706.6 | Y67: =SUMPRODUCT(E6:E65,Y6:Y65) -> 2370706.6 | Z67: =SUMPRODUCT(E6:E65,Z6:Z65) -> 2370706.6 | AA67: =SUMPRODUCT(E6:E65,AA6:AA65) -> 2370706.6 | AB67: =SUMPRODUCT(E6:E65,AB6:AB65) -> 2370706.6 | AC67: =SUMPRODUCT(E6:E65,AC6:AC65) -> 2370706.6 | AD67: =SUMPRODUCT(E6:E65,AD6:AD65) -> 2370706.6 | AE67: =SUMPRODUCT(E6:E65,AE6:AE65) -> 2370706.6 | AF67: =SUMPRODUCT(E6:E65,AF6:AF65) -> 2370706.6 | AG67: =SUM(U67:AF67) -> 28448479 | AH67: =T67+AG67 -> 43332714
A69: 2. COST PROJECTIONS (Cost % per deal × Revenue ACV; monthly cells follow Go-Live)
A70: # | B70: Customer / Cost Item | C70: Opportunity Owner | D70: Stage | E70: Probability | F70: Warehouse Location | G70: Ops Go-Live Date | H70: Cost % | I70: Annual Cost (Projected) | J70: Volume - Pallets | K70: Volume - SQM | L70: May-26 | M70: Jun-26 | N70: Jul-26 | O70: Aug-26 | P70: Sep-26 | Q70: Oct-26 | R70: Nov-26 | S70: Dec-26 | T70: 2026 Total | U70: Jan-27 | V70: Feb-27 | W70: Mar-27 | X70: Apr-27 | Y70: May-27 | Z70: Jun-27 | AA70: Jul-27 | AB70: Aug-27 | AC70: Sep-27 | AD70: Oct-27 | AE70: Nov-27 | AF70: Dec-27 | AG70: 2027 Total | AH70: Grand Total | AI70: Weighted Total | AJ70: Notes
A71: 1 | B71: =IF(B6="","",B6) -> SLB | C71: =IF(C6="","",C6) -> Yazan Darwish | D71: =IF(D6="","",D6) -> Prospecting | E71: =IF(E6="","",E6) -> 0.2 | F71: =IF(F6="","",F6) -> Dammam 2nd Ind -Tad WH | G71: =IF(G6="","",G6) -> 46204 | H71: 0.75 | I71: =IF(OR(H71="",H6=""),0,H71*H6) -> 1800000 | J71: =IF(J6="","",J6) -> 4000 | K71: =IF(K6="","",K6) -> 0 | L71: =IF(OR(G71="",I71=0),0,IF(DATE(2026,5,1)>=DATE(YEAR(G71),MONTH(G71),1),I71/12,0)) -> 0 | M71: =IF(OR(G71="",I71=0),0,IF(DATE(2026,6,1)>=DATE(YEAR(G71),MONTH(G71),1),I71/12,0)) -> 0 | N71: =IF(OR(G71="",I71=0),0,IF(DATE(2026,7,1)>=DATE(YEAR(G71),MONTH(G71),1),I71/12,0)) -> 150000 | O71: =IF(OR(G71="",I71=0),0,IF(DATE(2026,8,1)>=DATE(YEAR(G71),MONTH(G71),1),I71/12,0)) -> 150000 | P71: =IF(OR(G71="",I71=0),0,IF(DATE(2026,9,1)>=DATE(YEAR(G71),MONTH(G71),1),I71/12,0)) -> 150000 | Q71: =IF(OR(G71="",I71=0),0,IF(DATE(2026,10,1)>=DATE(YEAR(G71),MONTH(G71),1),I71/12,0)) -> 150000 | R71: =IF(OR(G71="",I71=0),0,IF(DATE(2026,11,1)>=DATE(YEAR(G71),MONTH(G71),1),I71/12,0)) -> 150000 | S71: =IF(OR(G71="",I71=0),0,IF(DATE(2026,12,1)>=DATE(YEAR(G71),MONTH(G71),1),I71/12,0)) -> 150000 | T71: =SUM(L71:S71) -> 900000 | U71: =IF(OR(G71="",I71=0),0,IF(DATE(2027,1,1)>=DATE(YEAR(G71),MONTH(G71),1),I71/12,0)) -> 150000 | V71: =IF(OR(G71="",I71=0),0,IF(DATE(2027,2,1)>=DATE(YEAR(G71),MONTH(G71),1),I71/12,0)) -> 150000 | W71: =IF(OR(G71="",I71=0),0,IF(DATE(2027,3,1)>=DATE(YEAR(G71),MONTH(G71),1),I71/12,0)) -> 150000 | X71: =IF(OR(G71="",I71=0),0,IF(DATE(2027,4,1)>=DATE(YEAR(G71),MONTH(G71),1),I71/12,0)) -> 150000 | Y71: =IF(OR(G71="",I71=0),0,IF(DATE(2027,5,1)>=DATE(YEAR(G71),MONTH(G71),1),I71/12,0)) -> 150000 | Z71: =IF(OR(G71="",I71=0),0,IF(DATE(2027,6,1)>=DATE(YEAR(G71),MONTH(G71),1),I71/12,0)) -> 150000 | AA71: =IF(OR(G71="",I71=0),0,IF(DATE(2027,7,1)>=DATE(YEAR(G71),MONTH(G71),1),I71/12,0)) -> 150000 | AB71: =IF(OR(G71="",I71=0),0,IF(DATE(2027,8,1)>=DATE(YEAR(G71),MONTH(G71),1),I71/12,0)) -> 150000 | AC71: =IF(OR(G71="",I71=0),0,IF(DATE(2027,9,1)>=DATE(YEAR(G71),MONTH(G71),1),I71/12,0)) -> 150000 | AD71: =IF(OR(G71="",I71=0),0,IF(DATE(2027,10,1)>=DATE(YEAR(G71),MONTH(G71),1),I71/12,0)) -> 150000 | AE71: =IF(OR(G71="",I71=0),0,IF(DATE(2027,11,1)>=DATE(YEAR(G71),MONTH(G71),1),I71/12,0)) -> 150000 | AF71: =IF(OR(G71="",I71=0),0,IF(DATE(2027,12,1)>=DATE(YEAR(G71),MONTH(G71),1),I71/12,0)) -> 150000 | AG71: =SUM(U71:AF71) -> 1800000 | AH71: =T71+AG71 -> 2700000 | AI71: =IF(OR(E71="",AH71=""),"",E71*AH71) -> 540000
A72: 2 | B72: =IF(B7="","",B7) -> NALCO Ecolab | C72: =IF(C7="","",C7) -> Yazan Darwish | D72: =IF(D7="","",D7) -> Contract Negotiation | E72: =IF(E7="","",E7) -> 0.9 | F72: =IF(F7="","",F7) -> Dammam 2nd Ind -Tad WH | G72: =IF(G7="","",G7) -> 46174 | H72: 0.75 | I72: =IF(OR(H72="",H7=""),0,H72*H7) -> 1800000 | J72: =IF(J7="","",J7) -> 4000 | K72: =IF(K7="","",K7) -> 0 | L72: =IF(OR(G72="",I72=0),0,IF(DATE(2026,5,1)>=DATE(YEAR(G72),MONTH(G72),1),I72/12,0)) -> 0 | M72: =IF(OR(G72="",I72=0),0,IF(DATE(2026,6,1)>=DATE(YEAR(G72),MONTH(G72),1),I72/12,0)) -> 150000 | N72: =IF(OR(G72="",I72=0),0,IF(DATE(2026,7,1)>=DATE(YEAR(G72),MONTH(G72),1),I72/12,0)) -> 150000 | O72: =IF(OR(G72="",I72=0),0,IF(DATE(2026,8,1)>=DATE(YEAR(G72),MONTH(G72),1),I72/12,0)) -> 150000 | P72: =IF(OR(G72="",I72=0),0,IF(DATE(2026,9,1)>=DATE(YEAR(G72),MONTH(G72),1),I72/12,0)) -> 150000 | Q72: =IF(OR(G72="",I72=0),0,IF(DATE(2026,10,1)>=DATE(YEAR(G72),MONTH(G72),1),I72/12,0)) -> 150000 | R72: =IF(OR(G72="",I72=0),0,IF(DATE(2026,11,1)>=DATE(YEAR(G72),MONTH(G72),1),I72/12,0)) -> 150000 | S72: =IF(OR(G72="",I72=0),0,IF(DATE(2026,12,1)>=DATE(YEAR(G72),MONTH(G72),1),I72/12,0)) -> 150000 | T72: =SUM(L72:S72) -> 1050000 | U72: =IF(OR(G72="",I72=0),0,IF(DATE(2027,1,1)>=DATE(YEAR(G72),MONTH(G72),1),I72/12,0)) -> 150000 | V72: =IF(OR(G72="",I72=0),0,IF(DATE(2027,2,1)>=DATE(YEAR(G72),MONTH(G72),1),I72/12,0)) -> 150000 | W72: =IF(OR(G72="",I72=0),0,IF(DATE(2027,3,1)>=DATE(YEAR(G72),MONTH(G72),1),I72/12,0)) -> 150000 | X72: =IF(OR(G72="",I72=0),0,IF(DATE(2027,4,1)>=DATE(YEAR(G72),MONTH(G72),1),I72/12,0)) -> 150000 | Y72: =IF(OR(G72="",I72=0),0,IF(DATE(2027,5,1)>=DATE(YEAR(G72),MONTH(G72),1),I72/12,0)) -> 150000 | Z72: =IF(OR(G72="",I72=0),0,IF(DATE(2027,6,1)>=DATE(YEAR(G72),MONTH(G72),1),I72/12,0)) -> 150000 | AA72: =IF(OR(G72="",I72=0),0,IF(DATE(2027,7,1)>=DATE(YEAR(G72),MONTH(G72),1),I72/12,0)) -> 150000 | AB72: =IF(OR(G72="",I72=0),0,IF(DATE(2027,8,1)>=DATE(YEAR(G72),MONTH(G72),1),I72/12,0)) -> 150000 | AC72: =IF(OR(G72="",I72=0),0,IF(DATE(2027,9,1)>=DATE(YEAR(G72),MONTH(G72),1),I72/12,0)) -> 150000 | AD72: =IF(OR(G72="",I72=0),0,IF(DATE(2027,10,1)>=DATE(YEAR(G72),MONTH(G72),1),I72/12,0)) -> 150000 | AE72: =IF(OR(G72="",I72=0),0,IF(DATE(2027,11,1)>=DATE(YEAR(G72),MONTH(G72),1),I72/12,0)) -> 150000 | AF72: =IF(OR(G72="",I72=0),0,IF(DATE(2027,12,1)>=DATE(YEAR(G72),MONTH(G72),1),I72/12,0)) -> 150000 | AG72: =SUM(U72:AF72) -> 1800000 | AH72: =T72+AG72 -> 2850000 | AI72: =IF(OR(E72="",AH72=""),"",E72*AH72) -> 2565000
A73: 3 | B73: =IF(B8="","",B8) -> Synthomer ME | C73: =IF(C8="","",C8) -> Yazan Darwish | D73: =IF(D8="","",D8) -> Contract Negotiation | E73: =IF(E8="","",E8) -> 0.9 | F73: =IF(F8="","",F8) -> Dammam 2nd Ind -Tad WH | G73: =IF(G8="","",G8) -> 46157 | H73: 0.75 | I73: =IF(OR(H73="",H8=""),0,H73*H8) -> 675000 | J73: =IF(J8="","",J8) -> 1500 | K73: =IF(K8="","",K8) -> 0 | L73: =IF(OR(G73="",I73=0),0,IF(DATE(2026,5,1)>=DATE(YEAR(G73),MONTH(G73),1),I73/12,0)) -> 56250 | M73: =IF(OR(G73="",I73=0),0,IF(DATE(2026,6,1)>=DATE(YEAR(G73),MONTH(G73),1),I73/12,0)) -> 56250 | N73: =IF(OR(G73="",I73=0),0,IF(DATE(2026,7,1)>=DATE(YEAR(G73),MONTH(G73),1),I73/12,0)) -> 56250 | O73: =IF(OR(G73="",I73=0),0,IF(DATE(2026,8,1)>=DATE(YEAR(G73),MONTH(G73),1),I73/12,0)) -> 56250 | P73: =IF(OR(G73="",I73=0),0,IF(DATE(2026,9,1)>=DATE(YEAR(G73),MONTH(G73),1),I73/12,0)) -> 56250 | Q73: =IF(OR(G73="",I73=0),0,IF(DATE(2026,10,1)>=DATE(YEAR(G73),MONTH(G73),1),I73/12,0)) -> 56250 | R73: =IF(OR(G73="",I73=0),0,IF(DATE(2026,11,1)>=DATE(YEAR(G73),MONTH(G73),1),I73/12,0)) -> 56250 | S73: =IF(OR(G73="",I73=0),0,IF(DATE(2026,12,1)>=DATE(YEAR(G73),MONTH(G73),1),I73/12,0)) -> 56250 | T73: =SUM(L73:S73) -> 450000 | U73: =IF(OR(G73="",I73=0),0,IF(DATE(2027,1,1)>=DATE(YEAR(G73),MONTH(G73),1),I73/12,0)) -> 56250 | V73: =IF(OR(G73="",I73=0),0,IF(DATE(2027,2,1)>=DATE(YEAR(G73),MONTH(G73),1),I73/12,0)) -> 56250 | W73: =IF(OR(G73="",I73=0),0,IF(DATE(2027,3,1)>=DATE(YEAR(G73),MONTH(G73),1),I73/12,0)) -> 56250 | X73: =IF(OR(G73="",I73=0),0,IF(DATE(2027,4,1)>=DATE(YEAR(G73),MONTH(G73),1),I73/12,0)) -> 56250 | Y73: =IF(OR(G73="",I73=0),0,IF(DATE(2027,5,1)>=DATE(YEAR(G73),MONTH(G73),1),I73/12,0)) -> 56250 | Z73: =IF(OR(G73="",I73=0),0,IF(DATE(2027,6,1)>=DATE(YEAR(G73),MONTH(G73),1),I73/12,0)) -> 56250 | AA73: =IF(OR(G73="",I73=0),0,IF(DATE(2027,7,1)>=DATE(YEAR(G73),MONTH(G73),1),I73/12,0)) -> 56250 | AB73: =IF(OR(G73="",I73=0),0,IF(DATE(2027,8,1)>=DATE(YEAR(G73),MONTH(G73),1),I73/12,0)) -> 56250 | AC73: =IF(OR(G73="",I73=0),0,IF(DATE(2027,9,1)>=DATE(YEAR(G73),MONTH(G73),1),I73/12,0)) -> 56250 | AD73: =IF(OR(G73="",I73=0),0,IF(DATE(2027,10,1)>=DATE(YEAR(G73),MONTH(G73),1),I73/12,0)) -> 56250 | AE73: =IF(OR(G73="",I73=0),0,IF(DATE(2027,11,1)>=DATE(YEAR(G73),MONTH(G73),1),I73/12,0)) -> 56250 | AF73: =IF(OR(G73="",I73=0),0,IF(DATE(2027,12,1)>=DATE(YEAR(G73),MONTH(G73),1),I73/12,0)) -> 56250 | AG73: =SUM(U73:AF73) -> 675000 | AH73: =T73+AG73 -> 1125000 | AI73: =IF(OR(E73="",AH73=""),"",E73*AH73) -> 1012500
A74: 4 | B74: =IF(B9="","",B9) -> Transworld Saudi Logistics | C74: =IF(C9="","",C9) -> Yazan Darwish | D74: =IF(D9="","",D9) -> Proposal Sent | E74: =IF(E9="","",E9) -> 0.6 | F74: =IF(F9="","",F9) -> Dammam 2nd Ind -Tad WH | G74: =IF(G9="","",G9) -> 46143 | H74: 0.75 | I74: =IF(OR(H74="",H9=""),0,H74*H9) -> 315000 | J74: =IF(J9="","",J9) -> 500 | K74: =IF(K9="","",K9) -> 0 | L74: =IF(OR(G74="",I74=0),0,IF(DATE(2026,5,1)>=DATE(YEAR(G74),MONTH(G74),1),I74/12,0)) -> 26250 | M74: =IF(OR(G74="",I74=0),0,IF(DATE(2026,6,1)>=DATE(YEAR(G74),MONTH(G74),1),I74/12,0)) -> 26250 | N74: =IF(OR(G74="",I74=0),0,IF(DATE(2026,7,1)>=DATE(YEAR(G74),MONTH(G74),1),I74/12,0)) -> 26250 | O74: =IF(OR(G74="",I74=0),0,IF(DATE(2026,8,1)>=DATE(YEAR(G74),MONTH(G74),1),I74/12,0)) -> 26250 | P74: =IF(OR(G74="",I74=0),0,IF(DATE(2026,9,1)>=DATE(YEAR(G74),MONTH(G74),1),I74/12,0)) -> 26250 | Q74: =IF(OR(G74="",I74=0),0,IF(DATE(2026,10,1)>=DATE(YEAR(G74),MONTH(G74),1),I74/12,0)) -> 26250 | R74: =IF(OR(G74="",I74=0),0,IF(DATE(2026,11,1)>=DATE(YEAR(G74),MONTH(G74),1),I74/12,0)) -> 26250 | S74: =IF(OR(G74="",I74=0),0,IF(DATE(2026,12,1)>=DATE(YEAR(G74),MONTH(G74),1),I74/12,0)) -> 26250 | T74: =SUM(L74:S74) -> 210000 | U74: =IF(OR(G74="",I74=0),0,IF(DATE(2027,1,1)>=DATE(YEAR(G74),MONTH(G74),1),I74/12,0)) -> 26250 | V74: =IF(OR(G74="",I74=0),0,IF(DATE(2027,2,1)>=DATE(YEAR(G74),MONTH(G74),1),I74/12,0)) -> 26250 | W74: =IF(OR(G74="",I74=0),0,IF(DATE(2027,3,1)>=DATE(YEAR(G74),MONTH(G74),1),I74/12,0)) -> 26250 | X74: =IF(OR(G74="",I74=0),0,IF(DATE(2027,4,1)>=DATE(YEAR(G74),MONTH(G74),1),I74/12,0)) -> 26250 | Y74: =IF(OR(G74="",I74=0),0,IF(DATE(2027,5,1)>=DATE(YEAR(G74),MONTH(G74),1),I74/12,0)) -> 26250 | Z74: =IF(OR(G74="",I74=0),0,IF(DATE(2027,6,1)>=DATE(YEAR(G74),MONTH(G74),1),I74/12,0)) -> 26250 | AA74: =IF(OR(G74="",I74=0),0,IF(DATE(2027,7,1)>=DATE(YEAR(G74),MONTH(G74),1),I74/12,0)) -> 26250 | AB74: =IF(OR(G74="",I74=0),0,IF(DATE(2027,8,1)>=DATE(YEAR(G74),MONTH(G74),1),I74/12,0)) -> 26250 | AC74: =IF(OR(G74="",I74=0),0,IF(DATE(2027,9,1)>=DATE(YEAR(G74),MONTH(G74),1),I74/12,0)) -> 26250 | AD74: =IF(OR(G74="",I74=0),0,IF(DATE(2027,10,1)>=DATE(YEAR(G74),MONTH(G74),1),I74/12,0)) -> 26250 | AE74: =IF(OR(G74="",I74=0),0,IF(DATE(2027,11,1)>=DATE(YEAR(G74),MONTH(G74),1),I74/12,0)) -> 26250 | AF74: =IF(OR(G74="",I74=0),0,IF(DATE(2027,12,1)>=DATE(YEAR(G74),MONTH(G74),1),I74/12,0)) -> 26250 | AG74: =SUM(U74:AF74) -> 315000 | AH74: =T74+AG74 -> 525000 | AI74: =IF(OR(E74="",AH74=""),"",E74*AH74) -> 315000
A75: 5 | B75: =IF(B10="","",B10) -> Schmidt | C75: =IF(C10="","",C10) -> Yazan Darwish | D75: =IF(D10="","",D10) -> Proposal Sent | E75: =IF(E10="","",E10) -> 0.6 | F75: =IF(F10="","",F10) -> Dammam 2nd Ind -Tad WH | G75: =IF(G10="","",G10) -> 46143 | H75: 0.75 | I75: =IF(OR(H75="",H10=""),0,H75*H10) -> 198000 | J75: =IF(J10="","",J10) -> 400 | K75: =IF(K10="","",K10) -> 0 | L75: =IF(OR(G75="",I75=0),0,IF(DATE(2026,5,1)>=DATE(YEAR(G75),MONTH(G75),1),I75/12,0)) -> 16500 | M75: =IF(OR(G75="",I75=0),0,IF(DATE(2026,6,1)>=DATE(YEAR(G75),MONTH(G75),1),I75/12,0)) -> 16500 | N75: =IF(OR(G75="",I75=0),0,IF(DATE(2026,7,1)>=DATE(YEAR(G75),MONTH(G75),1),I75/12,0)) -> 16500 | O75: =IF(OR(G75="",I75=0),0,IF(DATE(2026,8,1)>=DATE(YEAR(G75),MONTH(G75),1),I75/12,0)) -> 16500 | P75: =IF(OR(G75="",I75=0),0,IF(DATE(2026,9,1)>=DATE(YEAR(G75),MONTH(G75),1),I75/12,0)) -> 16500 | Q75: =IF(OR(G75="",I75=0),0,IF(DATE(2026,10,1)>=DATE(YEAR(G75),MONTH(G75),1),I75/12,0)) -> 16500 | R75: =IF(OR(G75="",I75=0),0,IF(DATE(2026,11,1)>=DATE(YEAR(G75),MONTH(G75),1),I75/12,0)) -> 16500 | S75: =IF(OR(G75="",I75=0),0,IF(DATE(2026,12,1)>=DATE(YEAR(G75),MONTH(G75),1),I75/12,0)) -> 16500 | T75: =SUM(L75:S75) -> 132000 | U75: =IF(OR(G75="",I75=0),0,IF(DATE(2027,1,1)>=DATE(YEAR(G75),MONTH(G75),1),I75/12,0)) -> 16500 | V75: =IF(OR(G75="",I75=0),0,IF(DATE(2027,2,1)>=DATE(YEAR(G75),MONTH(G75),1),I75/12,0)) -> 16500 | W75: =IF(OR(G75="",I75=0),0,IF(DATE(2027,3,1)>=DATE(YEAR(G75),MONTH(G75),1),I75/12,0)) -> 16500 | X75: =IF(OR(G75="",I75=0),0,IF(DATE(2027,4,1)>=DATE(YEAR(G75),MONTH(G75),1),I75/12,0)) -> 16500 | Y75: =IF(OR(G75="",I75=0),0,IF(DATE(2027,5,1)>=DATE(YEAR(G75),MONTH(G75),1),I75/12,0)) -> 16500 | Z75: =IF(OR(G75="",I75=0),0,IF(DATE(2027,6,1)>=DATE(YEAR(G75),MONTH(G75),1),I75/12,0)) -> 16500 | AA75: =IF(OR(G75="",I75=0),0,IF(DATE(2027,7,1)>=DATE(YEAR(G75),MONTH(G75),1),I75/12,0)) -> 16500 | AB75: =IF(OR(G75="",I75=0),0,IF(DATE(2027,8,1)>=DATE(YEAR(G75),MONTH(G75),1),I75/12,0)) -> 16500 | AC75: =IF(OR(G75="",I75=0),0,IF(DATE(2027,9,1)>=DATE(YEAR(G75),MONTH(G75),1),I75/12,0)) -> 16500 | AD75: =IF(OR(G75="",I75=0),0,IF(DATE(2027,10,1)>=DATE(YEAR(G75),MONTH(G75),1),I75/12,0)) -> 16500 | AE75: =IF(OR(G75="",I75=0),0,IF(DATE(2027,11,1)>=DATE(YEAR(G75),MONTH(G75),1),I75/12,0)) -> 16500 | AF75: =IF(OR(G75="",I75=0),0,IF(DATE(2027,12,1)>=DATE(YEAR(G75),MONTH(G75),1),I75/12,0)) -> 16500 | AG75: =SUM(U75:AF75) -> 198000 | AH75: =T75+AG75 -> 330000 | AI75: =IF(OR(E75="",AH75=""),"",E75*AH75) -> 198000
A76: 6 | B76: =IF(B11="","",B11) -> Zaghami | C76: =IF(C11="","",C11) -> Yazan Darwish | D76: =IF(D11="","",D11) -> Proposal Sent | E76: =IF(E11="","",E11) -> 0.6 | F76: =IF(F11="","",F11) -> Dammam 2nd Ind -Tad WH | G76: =IF(G11="","",G11) -> 46235 | H76: 0.75 | I76: =IF(OR(H76="",H11=""),0,H76*H11) -> 157500 | J76: =IF(J11="","",J11) -> 250 | K76: =IF(K11="","",K11) -> 0 | L76: =IF(OR(G76="",I76=0),0,IF(DATE(2026,5,1)>=DATE(YEAR(G76),MONTH(G76),1),I76/12,0)) -> 0 | M76: =IF(OR(G76="",I76=0),0,IF(DATE(2026,6,1)>=DATE(YEAR(G76),MONTH(G76),1),I76/12,0)) -> 0 | N76: =IF(OR(G76="",I76=0),0,IF(DATE(2026,7,1)>=DATE(YEAR(G76),MONTH(G76),1),I76/12,0)) -> 0 | O76: =IF(OR(G76="",I76=0),0,IF(DATE(2026,8,1)>=DATE(YEAR(G76),MONTH(G76),1),I76/12,0)) -> 13125 | P76: =IF(OR(G76="",I76=0),0,IF(DATE(2026,9,1)>=DATE(YEAR(G76),MONTH(G76),1),I76/12,0)) -> 13125 | Q76: =IF(OR(G76="",I76=0),0,IF(DATE(2026,10,1)>=DATE(YEAR(G76),MONTH(G76),1),I76/12,0)) -> 13125 | R76: =IF(OR(G76="",I76=0),0,IF(DATE(2026,11,1)>=DATE(YEAR(G76),MONTH(G76),1),I76/12,0)) -> 13125 | S76: =IF(OR(G76="",I76=0),0,IF(DATE(2026,12,1)>=DATE(YEAR(G76),MONTH(G76),1),I76/12,0)) -> 13125 | T76: =SUM(L76:S76) -> 65625 | U76: =IF(OR(G76="",I76=0),0,IF(DATE(2027,1,1)>=DATE(YEAR(G76),MONTH(G76),1),I76/12,0)) -> 13125 | V76: =IF(OR(G76="",I76=0),0,IF(DATE(2027,2,1)>=DATE(YEAR(G76),MONTH(G76),1),I76/12,0)) -> 13125 | W76: =IF(OR(G76="",I76=0),0,IF(DATE(2027,3,1)>=DATE(YEAR(G76),MONTH(G76),1),I76/12,0)) -> 13125 | X76: =IF(OR(G76="",I76=0),0,IF(DATE(2027,4,1)>=DATE(YEAR(G76),MONTH(G76),1),I76/12,0)) -> 13125 | Y76: =IF(OR(G76="",I76=0),0,IF(DATE(2027,5,1)>=DATE(YEAR(G76),MONTH(G76),1),I76/12,0)) -> 13125 | Z76: =IF(OR(G76="",I76=0),0,IF(DATE(2027,6,1)>=DATE(YEAR(G76),MONTH(G76),1),I76/12,0)) -> 13125 | AA76: =IF(OR(G76="",I76=0),0,IF(DATE(2027,7,1)>=DATE(YEAR(G76),MONTH(G76),1),I76/12,0)) -> 13125 | AB76: =IF(OR(G76="",I76=0),0,IF(DATE(2027,8,1)>=DATE(YEAR(G76),MONTH(G76),1),I76/12,0)) -> 13125 | AC76: =IF(OR(G76="",I76=0),0,IF(DATE(2027,9,1)>=DATE(YEAR(G76),MONTH(G76),1),I76/12,0)) -> 13125 | AD76: =IF(OR(G76="",I76=0),0,IF(DATE(2027,10,1)>=DATE(YEAR(G76),MONTH(G76),1),I76/12,0)) -> 13125 | AE76: =IF(OR(G76="",I76=0),0,IF(DATE(2027,11,1)>=DATE(YEAR(G76),MONTH(G76),1),I76/12,0)) -> 13125 | AF76: =IF(OR(G76="",I76=0),0,IF(DATE(2027,12,1)>=DATE(YEAR(G76),MONTH(G76),1),I76/12,0)) -> 13125 | AG76: =SUM(U76:AF76) -> 157500 | AH76: =T76+AG76 -> 223125 | AI76: =IF(OR(E76="",AH76=""),"",E76*AH76) -> 133875
A77: 7 | B77: =IF(B12="","",B12) -> Transworld Saudi Logistics | C77: =IF(C12="","",C12) -> Yazan Darwish | D77: =IF(D12="","",D12) -> Proposal Sent | E77: =IF(E12="","",E12) -> 0.6 | F77: =IF(F12="","",F12) -> Dammam 2nd Ind -Tad WH | G77: =IF(G12="","",G12) -> 46174 | H77: 0.75 | I77: =IF(OR(H77="",H12=""),0,H77*H12) -> 121875 | J77: =IF(J12="","",J12) -> 250 | K77: =IF(K12="","",K12) -> 0 | L77: =IF(OR(G77="",I77=0),0,IF(DATE(2026,5,1)>=DATE(YEAR(G77),MONTH(G77),1),I77/12,0)) -> 0 | M77: =IF(OR(G77="",I77=0),0,IF(DATE(2026,6,1)>=DATE(YEAR(G77),MONTH(G77),1),I77/12,0)) -> 10156.25 | N77: =IF(OR(G77="",I77=0),0,IF(DATE(2026,7,1)>=DATE(YEAR(G77),MONTH(G77),1),I77/12,0)) -> 10156.25 | O77: =IF(OR(G77="",I77=0),0,IF(DATE(2026,8,1)>=DATE(YEAR(G77),MONTH(G77),1),I77/12,0)) -> 10156.25 | P77: =IF(OR(G77="",I77=0),0,IF(DATE(2026,9,1)>=DATE(YEAR(G77),MONTH(G77),1),I77/12,0)) -> 10156.25 | Q77: =IF(OR(G77="",I77=0),0,IF(DATE(2026,10,1)>=DATE(YEAR(G77),MONTH(G77),1),I77/12,0)) -> 10156.25 | R77: =IF(OR(G77="",I77=0),0,IF(DATE(2026,11,1)>=DATE(YEAR(G77),MONTH(G77),1),I77/12,0)) -> 10156.25 | S77: =IF(OR(G77="",I77=0),0,IF(DATE(2026,12,1)>=DATE(YEAR(G77),MONTH(G77),1),I77/12,0)) -> 10156.25 | T77: =SUM(L77:S77) -> 71093.75 | U77: =IF(OR(G77="",I77=0),0,IF(DATE(2027,1,1)>=DATE(YEAR(G77),MONTH(G77),1),I77/12,0)) -> 10156.25 | V77: =IF(OR(G77="",I77=0),0,IF(DATE(2027,2,1)>=DATE(YEAR(G77),MONTH(G77),1),I77/12,0)) -> 10156.25 | W77: =IF(OR(G77="",I77=0),0,IF(DATE(2027,3,1)>=DATE(YEAR(G77),MONTH(G77),1),I77/12,0)) -> 10156.25 | X77: =IF(OR(G77="",I77=0),0,IF(DATE(2027,4,1)>=DATE(YEAR(G77),MONTH(G77),1),I77/12,0)) -> 10156.25 | Y77: =IF(OR(G77="",I77=0),0,IF(DATE(2027,5,1)>=DATE(YEAR(G77),MONTH(G77),1),I77/12,0)) -> 10156.25 | Z77: =IF(OR(G77="",I77=0),0,IF(DATE(2027,6,1)>=DATE(YEAR(G77),MONTH(G77),1),I77/12,0)) -> 10156.25 | AA77: =IF(OR(G77="",I77=0),0,IF(DATE(2027,7,1)>=DATE(YEAR(G77),MONTH(G77),1),I77/12,0)) -> 10156.25 | AB77: =IF(OR(G77="",I77=0),0,IF(DATE(2027,8,1)>=DATE(YEAR(G77),MONTH(G77),1),I77/12,0)) -> 10156.25 | AC77: =IF(OR(G77="",I77=0),0,IF(DATE(2027,9,1)>=DATE(YEAR(G77),MONTH(G77),1),I77/12,0)) -> 10156.25 | AD77: =IF(OR(G77="",I77=0),0,IF(DATE(2027,10,1)>=DATE(YEAR(G77),MONTH(G77),1),I77/12,0)) -> 10156.25 | AE77: =IF(OR(G77="",I77=0),0,IF(DATE(2027,11,1)>=DATE(YEAR(G77),MONTH(G77),1),I77/12,0)) -> 10156.25 | AF77: =IF(OR(G77="",I77=0),0,IF(DATE(2027,12,1)>=DATE(YEAR(G77),MONTH(G77),1),I77/12,0)) -> 10156.25 | AG77: =SUM(U77:AF77) -> 121875 | AH77: =T77+AG77 -> 192968.75 | AI77: =IF(OR(E77="",AH77=""),"",E77*AH77) -> 115781.25
A78: 8 | B78: =IF(B13="","",B13) -> i-Energy | C78: =IF(C13="","",C13) -> Yazan Darwish | D78: =IF(D13="","",D13) -> Proposal Sent | E78: =IF(E13="","",E13) -> 0.6 | F78: =IF(F13="","",F13) -> Dammam 2nd Ind -Tad WH | G78: =IF(G13="","",G13) -> 46143 | H78: 0.75 | I78: =IF(OR(H78="",H13=""),0,H78*H13) -> 112500 | J78: =IF(J13="","",J13) -> 250 | K78: =IF(K13="","",K13) -> 0 | L78: =IF(OR(G78="",I78=0),0,IF(DATE(2026,5,1)>=DATE(YEAR(G78),MONTH(G78),1),I78/12,0)) -> 9375 | M78: =IF(OR(G78="",I78=0),0,IF(DATE(2026,6,1)>=DATE(YEAR(G78),MONTH(G78),1),I78/12,0)) -> 9375 | N78: =IF(OR(G78="",I78=0),0,IF(DATE(2026,7,1)>=DATE(YEAR(G78),MONTH(G78),1),I78/12,0)) -> 9375 | O78: =IF(OR(G78="",I78=0),0,IF(DATE(2026,8,1)>=DATE(YEAR(G78),MONTH(G78),1),I78/12,0)) -> 9375 | P78: =IF(OR(G78="",I78=0),0,IF(DATE(2026,9,1)>=DATE(YEAR(G78),MONTH(G78),1),I78/12,0)) -> 9375 | Q78: =IF(OR(G78="",I78=0),0,IF(DATE(2026,10,1)>=DATE(YEAR(G78),MONTH(G78),1),I78/12,0)) -> 9375 | R78: =IF(OR(G78="",I78=0),0,IF(DATE(2026,11,1)>=DATE(YEAR(G78),MONTH(G78),1),I78/12,0)) -> 9375 | S78: =IF(OR(G78="",I78=0),0,IF(DATE(2026,12,1)>=DATE(YEAR(G78),MONTH(G78),1),I78/12,0)) -> 9375 | T78: =SUM(L78:S78) -> 75000 | U78: =IF(OR(G78="",I78=0),0,IF(DATE(2027,1,1)>=DATE(YEAR(G78),MONTH(G78),1),I78/12,0)) -> 9375 | V78: =IF(OR(G78="",I78=0),0,IF(DATE(2027,2,1)>=DATE(YEAR(G78),MONTH(G78),1),I78/12,0)) -> 9375 | W78: =IF(OR(G78="",I78=0),0,IF(DATE(2027,3,1)>=DATE(YEAR(G78),MONTH(G78),1),I78/12,0)) -> 9375 | X78: =IF(OR(G78="",I78=0),0,IF(DATE(2027,4,1)>=DATE(YEAR(G78),MONTH(G78),1),I78/12,0)) -> 9375 | Y78: =IF(OR(G78="",I78=0),0,IF(DATE(2027,5,1)>=DATE(YEAR(G78),MONTH(G78),1),I78/12,0)) -> 9375 | Z78: =IF(OR(G78="",I78=0),0,IF(DATE(2027,6,1)>=DATE(YEAR(G78),MONTH(G78),1),I78/12,0)) -> 9375 | AA78: =IF(OR(G78="",I78=0),0,IF(DATE(2027,7,1)>=DATE(YEAR(G78),MONTH(G78),1),I78/12,0)) -> 9375 | AB78: =IF(OR(G78="",I78=0),0,IF(DATE(2027,8,1)>=DATE(YEAR(G78),MONTH(G78),1),I78/12,0)) -> 9375 | AC78: =IF(OR(G78="",I78=0),0,IF(DATE(2027,9,1)>=DATE(YEAR(G78),MONTH(G78),1),I78/12,0)) -> 9375 | AD78: =IF(OR(G78="",I78=0),0,IF(DATE(2027,10,1)>=DATE(YEAR(G78),MONTH(G78),1),I78/12,0)) -> 9375 | AE78: =IF(OR(G78="",I78=0),0,IF(DATE(2027,11,1)>=DATE(YEAR(G78),MONTH(G78),1),I78/12,0)) -> 9375 | AF78: =IF(OR(G78="",I78=0),0,IF(DATE(2027,12,1)>=DATE(YEAR(G78),MONTH(G78),1),I78/12,0)) -> 9375 | AG78: =SUM(U78:AF78) -> 112500 | AH78: =T78+AG78 -> 187500 | AI78: =IF(OR(E78="",AH78=""),"",E78*AH78) -> 112500
A79: 9 | B79: =IF(B14="","",B14) -> FMS Group | C79: =IF(C14="","",C14) -> Yazan Darwish | D79: =IF(D14="","",D14) -> Proposal Sent | E79: =IF(E14="","",E14) -> 0.6 | F79: =IF(F14="","",F14) -> Dammam 2nd Ind -Tad WH | G79: =IF(G14="","",G14) -> 46174 | H79: 0.75 | I79: =IF(OR(H79="",H14=""),0,H79*H14) -> 37500 | J79: =IF(J14="","",J14) -> 100 | K79: =IF(K14="","",K14) -> 0 | L79: =IF(OR(G79="",I79=0),0,IF(DATE(2026,5,1)>=DATE(YEAR(G79),MONTH(G79),1),I79/12,0)) -> 0 | M79: =IF(OR(G79="",I79=0),0,IF(DATE(2026,6,1)>=DATE(YEAR(G79),MONTH(G79),1),I79/12,0)) -> 3125 | N79: =IF(OR(G79="",I79=0),0,IF(DATE(2026,7,1)>=DATE(YEAR(G79),MONTH(G79),1),I79/12,0)) -> 3125 | O79: =IF(OR(G79="",I79=0),0,IF(DATE(2026,8,1)>=DATE(YEAR(G79),MONTH(G79),1),I79/12,0)) -> 3125 | P79: =IF(OR(G79="",I79=0),0,IF(DATE(2026,9,1)>=DATE(YEAR(G79),MONTH(G79),1),I79/12,0)) -> 3125 | Q79: =IF(OR(G79="",I79=0),0,IF(DATE(2026,10,1)>=DATE(YEAR(G79),MONTH(G79),1),I79/12,0)) -> 3125 | R79: =IF(OR(G79="",I79=0),0,IF(DATE(2026,11,1)>=DATE(YEAR(G79),MONTH(G79),1),I79/12,0)) -> 3125 | S79: =IF(OR(G79="",I79=0),0,IF(DATE(2026,12,1)>=DATE(YEAR(G79),MONTH(G79),1),I79/12,0)) -> 3125 | T79: =SUM(L79:S79) -> 21875 | U79: =IF(OR(G79="",I79=0),0,IF(DATE(2027,1,1)>=DATE(YEAR(G79),MONTH(G79),1),I79/12,0)) -> 3125 | V79: =IF(OR(G79="",I79=0),0,IF(DATE(2027,2,1)>=DATE(YEAR(G79),MONTH(G79),1),I79/12,0)) -> 3125 | W79: =IF(OR(G79="",I79=0),0,IF(DATE(2027,3,1)>=DATE(YEAR(G79),MONTH(G79),1),I79/12,0)) -> 3125 | X79: =IF(OR(G79="",I79=0),0,IF(DATE(2027,4,1)>=DATE(YEAR(G79),MONTH(G79),1),I79/12,0)) -> 3125 | Y79: =IF(OR(G79="",I79=0),0,IF(DATE(2027,5,1)>=DATE(YEAR(G79),MONTH(G79),1),I79/12,0)) -> 3125 | Z79: =IF(OR(G79="",I79=0),0,IF(DATE(2027,6,1)>=DATE(YEAR(G79),MONTH(G79),1),I79/12,0)) -> 3125 | AA79: =IF(OR(G79="",I79=0),0,IF(DATE(2027,7,1)>=DATE(YEAR(G79),MONTH(G79),1),I79/12,0)) -> 3125 | AB79: =IF(OR(G79="",I79=0),0,IF(DATE(2027,8,1)>=DATE(YEAR(G79),MONTH(G79),1),I79/12,0)) -> 3125 | AC79: =IF(OR(G79="",I79=0),0,IF(DATE(2027,9,1)>=DATE(YEAR(G79),MONTH(G79),1),I79/12,0)) -> 3125 | AD79: =IF(OR(G79="",I79=0),0,IF(DATE(2027,10,1)>=DATE(YEAR(G79),MONTH(G79),1),I79/12,0)) -> 3125 | AE79: =IF(OR(G79="",I79=0),0,IF(DATE(2027,11,1)>=DATE(YEAR(G79),MONTH(G79),1),I79/12,0)) -> 3125 | AF79: =IF(OR(G79="",I79=0),0,IF(DATE(2027,12,1)>=DATE(YEAR(G79),MONTH(G79),1),I79/12,0)) -> 3125 | AG79: =SUM(U79:AF79) -> 37500 | AH79: =T79+AG79 -> 59375 | AI79: =IF(OR(E79="",AH79=""),"",E79*AH79) -> 35625
A80: 10 | B80: =IF(B15="","",B15) -> El Ajou Group | C80: =IF(C15="","",C15) -> Yazan Darwish | D80: =IF(D15="","",D15) -> Proposal Sent | E80: =IF(E15="","",E15) -> 0.6 | F80: =IF(F15="","",F15) -> Dammam 2nd Ind -Tad WH | G80: =IF(G15="","",G15) -> 46204 | H80: 0.75 | I80: =IF(OR(H80="",H15=""),0,H80*H15) -> 58500 | J80: =IF(J15="","",J15) -> 100 | K80: =IF(K15="","",K15) -> 0 | L80: =IF(OR(G80="",I80=0),0,IF(DATE(2026,5,1)>=DATE(YEAR(G80),MONTH(G80),1),I80/12,0)) -> 0 | M80: =IF(OR(G80="",I80=0),0,IF(DATE(2026,6,1)>=DATE(YEAR(G80),MONTH(G80),1),I80/12,0)) -> 0 | N80: =IF(OR(G80="",I80=0),0,IF(DATE(2026,7,1)>=DATE(YEAR(G80),MONTH(G80),1),I80/12,0)) -> 4875 | O80: =IF(OR(G80="",I80=0),0,IF(DATE(2026,8,1)>=DATE(YEAR(G80),MONTH(G80),1),I80/12,0)) -> 4875 | P80: =IF(OR(G80="",I80=0),0,IF(DATE(2026,9,1)>=DATE(YEAR(G80),MONTH(G80),1),I80/12,0)) -> 4875 | Q80: =IF(OR(G80="",I80=0),0,IF(DATE(2026,10,1)>=DATE(YEAR(G80),MONTH(G80),1),I80/12,0)) -> 4875 | R80: =IF(OR(G80="",I80=0),0,IF(DATE(2026,11,1)>=DATE(YEAR(G80),MONTH(G80),1),I80/12,0)) -> 4875 | S80: =IF(OR(G80="",I80=0),0,IF(DATE(2026,12,1)>=DATE(YEAR(G80),MONTH(G80),1),I80/12,0)) -> 4875 | T80: =SUM(L80:S80) -> 29250 | U80: =IF(OR(G80="",I80=0),0,IF(DATE(2027,1,1)>=DATE(YEAR(G80),MONTH(G80),1),I80/12,0)) -> 4875 | V80: =IF(OR(G80="",I80=0),0,IF(DATE(2027,2,1)>=DATE(YEAR(G80),MONTH(G80),1),I80/12,0)) -> 4875 | W80: =IF(OR(G80="",I80=0),0,IF(DATE(2027,3,1)>=DATE(YEAR(G80),MONTH(G80),1),I80/12,0)) -> 4875 | X80: =IF(OR(G80="",I80=0),0,IF(DATE(2027,4,1)>=DATE(YEAR(G80),MONTH(G80),1),I80/12,0)) -> 4875 | Y80: =IF(OR(G80="",I80=0),0,IF(DATE(2027,5,1)>=DATE(YEAR(G80),MONTH(G80),1),I80/12,0)) -> 4875 | Z80: =IF(OR(G80="",I80=0),0,IF(DATE(2027,6,1)>=DATE(YEAR(G80),MONTH(G80),1),I80/12,0)) -> 4875 | AA80: =IF(OR(G80="",I80=0),0,IF(DATE(2027,7,1)>=DATE(YEAR(G80),MONTH(G80),1),I80/12,0)) -> 4875 | AB80: =IF(OR(G80="",I80=0),0,IF(DATE(2027,8,1)>=DATE(YEAR(G80),MONTH(G80),1),I80/12,0)) -> 4875 | AC80: =IF(OR(G80="",I80=0),0,IF(DATE(2027,9,1)>=DATE(YEAR(G80),MONTH(G80),1),I80/12,0)) -> 4875 | AD80: =IF(OR(G80="",I80=0),0,IF(DATE(2027,10,1)>=DATE(YEAR(G80),MONTH(G80),1),I80/12,0)) -> 4875 | AE80: =IF(OR(G80="",I80=0),0,IF(DATE(2027,11,1)>=DATE(YEAR(G80),MONTH(G80),1),I80/12,0)) -> 4875 | AF80: =IF(OR(G80="",I80=0),0,IF(DATE(2027,12,1)>=DATE(YEAR(G80),MONTH(G80),1),I80/12,0)) -> 4875 | AG80: =SUM(U80:AF80) -> 58500 | AH80: =T80+AG80 -> 87750 | AI80: =IF(OR(E80="",AH80=""),"",E80*AH80) -> 52650
A81: 11 | B81: =IF(B16="","",B16) -> JAS | C81: =IF(C16="","",C16) -> Yazan Darwish | D81: =IF(D16="","",D16) -> Shortlisted | E81: =IF(E16="","",E16) -> 0.75 | F81: =IF(F16="","",F16) -> Jubail 1 | G81: =IF(G16="","",G16) -> 46174 | H81: 0.75 | I81: =IF(OR(H81="",H16=""),0,H81*H16) -> 693000 | J81: =IF(J16="","",J16) -> 1400 | K81: =IF(K16="","",K16) -> 0 | L81: =IF(OR(G81="",I81=0),0,IF(DATE(2026,5,1)>=DATE(YEAR(G81),MONTH(G81),1),I81/12,0)) -> 0 | M81: =IF(OR(G81="",I81=0),0,IF(DATE(2026,6,1)>=DATE(YEAR(G81),MONTH(G81),1),I81/12,0)) -> 57750 | N81: =IF(OR(G81="",I81=0),0,IF(DATE(2026,7,1)>=DATE(YEAR(G81),MONTH(G81),1),I81/12,0)) -> 57750 | O81: =IF(OR(G81="",I81=0),0,IF(DATE(2026,8,1)>=DATE(YEAR(G81),MONTH(G81),1),I81/12,0)) -> 57750 | P81: =IF(OR(G81="",I81=0),0,IF(DATE(2026,9,1)>=DATE(YEAR(G81),MONTH(G81),1),I81/12,0)) -> 57750 | Q81: =IF(OR(G81="",I81=0),0,IF(DATE(2026,10,1)>=DATE(YEAR(G81),MONTH(G81),1),I81/12,0)) -> 57750 | R81: =IF(OR(G81="",I81=0),0,IF(DATE(2026,11,1)>=DATE(YEAR(G81),MONTH(G81),1),I81/12,0)) -> 57750 | S81: =IF(OR(G81="",I81=0),0,IF(DATE(2026,12,1)>=DATE(YEAR(G81),MONTH(G81),1),I81/12,0)) -> 57750 | T81: =SUM(L81:S81) -> 404250 | U81: =IF(OR(G81="",I81=0),0,IF(DATE(2027,1,1)>=DATE(YEAR(G81),MONTH(G81),1),I81/12,0)) -> 57750 | V81: =IF(OR(G81="",I81=0),0,IF(DATE(2027,2,1)>=DATE(YEAR(G81),MONTH(G81),1),I81/12,0)) -> 57750 | W81: =IF(OR(G81="",I81=0),0,IF(DATE(2027,3,1)>=DATE(YEAR(G81),MONTH(G81),1),I81/12,0)) -> 57750 | X81: =IF(OR(G81="",I81=0),0,IF(DATE(2027,4,1)>=DATE(YEAR(G81),MONTH(G81),1),I81/12,0)) -> 57750 | Y81: =IF(OR(G81="",I81=0),0,IF(DATE(2027,5,1)>=DATE(YEAR(G81),MONTH(G81),1),I81/12,0)) -> 57750 | Z81: =IF(OR(G81="",I81=0),0,IF(DATE(2027,6,1)>=DATE(YEAR(G81),MONTH(G81),1),I81/12,0)) -> 57750 | AA81: =IF(OR(G81="",I81=0),0,IF(DATE(2027,7,1)>=DATE(YEAR(G81),MONTH(G81),1),I81/12,0)) -> 57750 | AB81: =IF(OR(G81="",I81=0),0,IF(DATE(2027,8,1)>=DATE(YEAR(G81),MONTH(G81),1),I81/12,0)) -> 57750 | AC81: =IF(OR(G81="",I81=0),0,IF(DATE(2027,9,1)>=DATE(YEAR(G81),MONTH(G81),1),I81/12,0)) -> 57750 | AD81: =IF(OR(G81="",I81=0),0,IF(DATE(2027,10,1)>=DATE(YEAR(G81),MONTH(G81),1),I81/12,0)) -> 57750 | AE81: =IF(OR(G81="",I81=0),0,IF(DATE(2027,11,1)>=DATE(YEAR(G81),MONTH(G81),1),I81/12,0)) -> 57750 | AF81: =IF(OR(G81="",I81=0),0,IF(DATE(2027,12,1)>=DATE(YEAR(G81),MONTH(G81),1),I81/12,0)) -> 57750 | AG81: =SUM(U81:AF81) -> 693000 | AH81: =T81+AG81 -> 1097250 | AI81: =IF(OR(E81="",AH81=""),"",E81*AH81) -> 822937.5
A82: 12 | B82: =IF(B17="","",B17) -> LX Pantos Logistics | C82: =IF(C17="","",C17) -> Yazan Darwish | D82: =IF(D17="","",D17) -> Shortlisted | E82: =IF(E17="","",E17) -> 0.75 | F82: =IF(F17="","",F17) -> Jubail 1 | G82: =IF(G17="","",G17) -> 46143 | H82: 0.75 | I82: =IF(OR(H82="",H17=""),0,H82*H17) -> 544500 | J82: =IF(J17="","",J17) -> 1000 | K82: =IF(K17="","",K17) -> 0 | L82: =IF(OR(G82="",I82=0),0,IF(DATE(2026,5,1)>=DATE(YEAR(G82),MONTH(G82),1),I82/12,0)) -> 45375 | M82: =IF(OR(G82="",I82=0),0,IF(DATE(2026,6,1)>=DATE(YEAR(G82),MONTH(G82),1),I82/12,0)) -> 45375 | N82: =IF(OR(G82="",I82=0),0,IF(DATE(2026,7,1)>=DATE(YEAR(G82),MONTH(G82),1),I82/12,0)) -> 45375 | O82: =IF(OR(G82="",I82=0),0,IF(DATE(2026,8,1)>=DATE(YEAR(G82),MONTH(G82),1),I82/12,0)) -> 45375 | P82: =IF(OR(G82="",I82=0),0,IF(DATE(2026,9,1)>=DATE(YEAR(G82),MONTH(G82),1),I82/12,0)) -> 45375 | Q82: =IF(OR(G82="",I82=0),0,IF(DATE(2026,10,1)>=DATE(YEAR(G82),MONTH(G82),1),I82/12,0)) -> 45375 | R82: =IF(OR(G82="",I82=0),0,IF(DATE(2026,11,1)>=DATE(YEAR(G82),MONTH(G82),1),I82/12,0)) -> 45375 | S82: =IF(OR(G82="",I82=0),0,IF(DATE(2026,12,1)>=DATE(YEAR(G82),MONTH(G82),1),I82/12,0)) -> 45375 | T82: =SUM(L82:S82) -> 363000 | U82: =IF(OR(G82="",I82=0),0,IF(DATE(2027,1,1)>=DATE(YEAR(G82),MONTH(G82),1),I82/12,0)) -> 45375 | V82: =IF(OR(G82="",I82=0),0,IF(DATE(2027,2,1)>=DATE(YEAR(G82),MONTH(G82),1),I82/12,0)) -> 45375 | W82: =IF(OR(G82="",I82=0),0,IF(DATE(2027,3,1)>=DATE(YEAR(G82),MONTH(G82),1),I82/12,0)) -> 45375 | X82: =IF(OR(G82="",I82=0),0,IF(DATE(2027,4,1)>=DATE(YEAR(G82),MONTH(G82),1),I82/12,0)) -> 45375 | Y82: =IF(OR(G82="",I82=0),0,IF(DATE(2027,5,1)>=DATE(YEAR(G82),MONTH(G82),1),I82/12,0)) -> 45375 | Z82: =IF(OR(G82="",I82=0),0,IF(DATE(2027,6,1)>=DATE(YEAR(G82),MONTH(G82),1),I82/12,0)) -> 45375 | AA82: =IF(OR(G82="",I82=0),0,IF(DATE(2027,7,1)>=DATE(YEAR(G82),MONTH(G82),1),I82/12,0)) -> 45375 | AB82: =IF(OR(G82="",I82=0),0,IF(DATE(2027,8,1)>=DATE(YEAR(G82),MONTH(G82),1),I82/12,0)) -> 45375 | AC82: =IF(OR(G82="",I82=0),0,IF(DATE(2027,9,1)>=DATE(YEAR(G82),MONTH(G82),1),I82/12,0)) -> 45375 | AD82: =IF(OR(G82="",I82=0),0,IF(DATE(2027,10,1)>=DATE(YEAR(G82),MONTH(G82),1),I82/12,0)) -> 45375 | AE82: =IF(OR(G82="",I82=0),0,IF(DATE(2027,11,1)>=DATE(YEAR(G82),MONTH(G82),1),I82/12,0)) -> 45375 | AF82: =IF(OR(G82="",I82=0),0,IF(DATE(2027,12,1)>=DATE(YEAR(G82),MONTH(G82),1),I82/12,0)) -> 45375 | AG82: =SUM(U82:AF82) -> 544500 | AH82: =T82+AG82 -> 907500 | AI82: =IF(OR(E82="",AH82=""),"",E82*AH82) -> 680625
... A130: 60 | B130: =IF(B65="","",B65) | C130: =IF(C65="","",C65) | D130: =IF(D65="","",D65) | E130: =IF(E65="","",E65) -> 0 | F130: =IF(F65="","",F65) | G130: =IF(G65="","",G65) | H130: 0.75 | I130: =IF(OR(H130="",H65=""),0,H130*H65) -> 0 | J130: =IF(J65="","",J65) -> 0 | K130: =IF(K65="","",K65) -> 0 | L130: =IF(OR(G130="",I130=0),0,IF(DATE(2026,5,1)>=DATE(YEAR(G130),MONTH(G130),1),I130/12,0)) -> 0 | M130: =IF(OR(G130="",I130=0),0,IF(DATE(2026,6,1)>=DATE(YEAR(G130),MONTH(G130),1),I130/12,0)) -> 0 | N130: =IF(OR(G130="",I130=0),0,IF(DATE(2026,7,1)>=DATE(YEAR(G130),MONTH(G130),1),I130/12,0)) -> 0 | O130: =IF(OR(G130="",I130=0),0,IF(DATE(2026,8,1)>=DATE(YEAR(G130),MONTH(G130),1),I130/12,0)) -> 0 | P130: =IF(OR(G130="",I130=0),0,IF(DATE(2026,9,1)>=DATE(YEAR(G130),MONTH(G130),1),I130/12,0)) -> 0 | Q130: =IF(OR(G130="",I130=0),0,IF(DATE(2026,10,1)>=DATE(YEAR(G130),MONTH(G130),1),I130/12,0)) -> 0 | R130: =IF(OR(G130="",I130=0),0,IF(DATE(2026,11,1)>=DATE(YEAR(G130),MONTH(G130),1),I130/12,0)) -> 0 | S130: =IF(OR(G130="",I130=0),0,IF(DATE(2026,12,1)>=DATE(YEAR(G130),MONTH(G130),1),I130/12,0)) -> 0 | T130: =SUM(L130:S130) -> 0 | U130: =IF(OR(G130="",I130=0),0,IF(DATE(2027,1,1)>=DATE(YEAR(G130),MONTH(G130),1),I130/12,0)) -> 0 | V130: =IF(OR(G130="",I130=0),0,IF(DATE(2027,2,1)>=DATE(YEAR(G130),MONTH(G130),1),I130/12,0)) -> 0 | W130: =IF(OR(G130="",I130=0),0,IF(DATE(2027,3,1)>=DATE(YEAR(G130),MONTH(G130),1),I130/12,0)) -> 0 | X130: =IF(OR(G130="",I130=0),0,IF(DATE(2027,4,1)>=DATE(YEAR(G130),MONTH(G130),1),I130/12,0)) -> 0 | Y130: =IF(OR(G130="",I130=0),0,IF(DATE(2027,5,1)>=DATE(YEAR(G130),MONTH(G130),1),I130/12,0)) -> 0 | Z130: =IF(OR(G130="",I130=0),0,IF(DATE(2027,6,1)>=DATE(YEAR(G130),MONTH(G130),1),I130/12,0)) -> 0 | AA130: =IF(OR(G130="",I130=0),0,IF(DATE(2027,7,1)>=DATE(YEAR(G130),MONTH(G130),1),I130/12,0)) -> 0 | AB130: =IF(OR(G130="",I130=0),0,IF(DATE(2027,8,1)>=DATE(YEAR(G130),MONTH(G130),1),I130/12,0)) -> 0 | AC130: =IF(OR(G130="",I130=0),0,IF(DATE(2027,9,1)>=DATE(YEAR(G130),MONTH(G130),1),I130/12,0)) -> 0 | AD130: =IF(OR(G130="",I130=0),0,IF(DATE(2027,10,1)>=DATE(YEAR(G130),MONTH(G130),1),I130/12,0)) -> 0 | AE130: =IF(OR(G130="",I130=0),0,IF(DATE(2027,11,1)>=DATE(YEAR(G130),MONTH(G130),1),I130/12,0)) -> 0 | AF130: =IF(OR(G130="",I130=0),0,IF(DATE(2027,12,1)>=DATE(YEAR(G130),MONTH(G130),1),I130/12,0)) -> 0 | AG130: =SUM(U130:AF130) -> 0 | AH130: =T130+AG130 -> 0 | AI130: =IF(OR(E130="",AH130=""),"",E130*AH130) -> 0
B131: TOTAL COSTS (Unweighted) | L131: =SUM(L71:L130) -> 762502 | M131: =SUM(M71:M130) -> 1272145.8 | N131: =SUM(N71:N130) -> 2009083.2 | O131: =SUM(O71:O130) -> 2123458.2 | P131: =SUM(P71:P130) -> 2266583.2 | Q131: =SUM(Q71:Q130) -> 2266583.2 | R131: =SUM(R71:R130) -> 2647958.2 | S131: =SUM(S71:S130) -> 2647958.2 | T131: =SUM(L131:S131) -> 15996272 | U131: =SUM(U71:U130) -> 2647958.2 | V131: =SUM(V71:V130) -> 2647958.2 | W131: =SUM(W71:W130) -> 2647958.2 | X131: =SUM(X71:X130) -> 2647958.2 | Y131: =SUM(Y71:Y130) -> 2647958.2 | Z131: =SUM(Z71:Z130) -> 2647958.2 | AA131: =SUM(AA71:AA130) -> 2647958.2 | AB131: =SUM(AB71:AB130) -> 2647958.2 | ... AF131: =SUM(AF71:AF130) -> 2647958.2 | AG131: =SUM(U131:AF131) -> 31775499 | AH131: =T131+AG131 -> 47771771
B132: TOTAL COSTS (Probability-Weighted) | L132: =SUMPRODUCT(E71:E130,L71:L130) -> 646097.45 | M132: =SUMPRODUCT(E71:E130,M71:M130) -> 1004573.7 | N132: =SUMPRODUCT(E71:E130,N71:N130) -> 1394704.9 | O132: =SUMPRODUCT(E71:E130,O71:O130) -> 1463329.9 | P132: =SUMPRODUCT(E71:E130,P71:P130) -> 1549205 | Q132: =SUMPRODUCT(E71:E130,Q71:Q130) -> 1549205 | R132: =SUMPRODUCT(E71:E130,R71:R130) -> 1778030 | S132: =SUMPRODUCT(E71:E130,S71:S130) -> 1778030 | T132: =SUM(L132:S132) -> 11163176 | U132: =SUMPRODUCT(E71:E130,U71:U130) -> 1778030 | V132: =SUMPRODUCT(E71:E130,V71:V130) -> 1778030 | W132: =SUMPRODUCT(E71:E130,W71:W130) -> 1778030 | X132: =SUMPRODUCT(E71:E130,X71:X130) -> 1778030 | Y132: =SUMPRODUCT(E71:E130,Y71:Y130) -> 1778030 | Z132: =SUMPRODUCT(E71:E130,Z71:Z130) -> 1778030 | AA132: =SUMPRODUCT(E71:E130,AA71:AA130) -> 1778030 | AB132: =SUMPRODUCT(E71:E130,AB71:AB130) -> 1778030 | AC132: =SUMPRODUCT(E71:E130,AC71:AC130) -> 1778030 | AD132: =SUMPRODUCT(E71:E130,AD71:AD130) -> 1778030 | AE132: =SUMPRODUCT(E71:E130,AE71:AE130) -> 1778030 | AF132: =SUMPRODUCT(E71:E130,AF71:AF130) -> 1778030 | AG132: =SUM(U132:AF132) -> 21336359 | AH132: =T132+AG132 -> 32499535
A134: 3. GROSS PROFIT IMPACT
A135: # | B135: Metric | L135: May-26 | M135: Jun-26 | N135: Jul-26 | O135: Aug-26 | P135: Sep-26 | Q135: Oct-26 | R135: Nov-26 | S135: Dec-26 | T135: 2026 Total | U135: Jan-27 | V135: Feb-27 | W135: Mar-27 | X135: Apr-27 | Y135: May-27 | Z135: Jun-27 | AA135: Jul-27 | AB135: Aug-27 | AC135: Sep-27 | AD135: Oct-27 | AE135: Nov-27 | AF135: Dec-27 | AG135: 2027 Total | AH135: Grand Total | AJ135: Notes
B136: GP (Unweighted) | L136: =L66-L131 -> 254167.33 | M136: =M66-M131 -> 424048.58 | N136: =N66-N131 -> 669694.42 | O136: =O66-O131 -> 707819.42 | P136: =P66-P131 -> 755527.75 | Q136: =Q66-Q131 -> 755527.75 | R136: =R66-R131 -> 882652.75 | S136: =S66-S131 -> 882652.75 | T136: =SUM(L136:S136) -> 5332090.8 | U136: =U66-U131 -> 882652.75 | V136: =V66-V131 -> 882652.75 | W136: =W66-W131 -> 882652.75 | X136: =X66-X131 -> 882652.75 | Y136: =Y66-Y131 -> 882652.75 | Z136: =Z66-Z131 -> 882652.75 | AA136: =AA66-AA131 -> 882652.75 | AB136: =AB66-AB131 -> 882652.75 | ... AF136: =AF66-AF131 -> 882652.75 | AG136: =SUM(U136:AF136) -> 10591833 | AH136: =T136+AG136 -> 15923924
B137: GP (Probability-Weighted) | L137: =L67-L132 -> 215365.82 | M137: =M67-M132 -> 334857.9 | N137: =N67-N132 -> 464901.65 | O137: =O67-O132 -> 487776.65 | P137: =P67-P132 -> 516401.65 | Q137: =Q67-Q132 -> 516401.65 | R137: =R67-R132 -> 592676.65 | S137: =S67-S132 -> 592676.65 | T137: =SUM(L137:S137) -> 3721058.6 | U137: =U67-U132 -> 592676.65 | V137: =V67-V132 -> 592676.65 | W137: =W67-W132 -> 592676.65 | X137: =X67-X132 -> 592676.65 | Y137: =Y67-Y132 -> 592676.65 | Z137: =Z67-Z132 -> 592676.65 | AA137: =AA67-AA132 -> 592676.65 | AB137: =AB67-AB132 -> 592676.65 | ... AF137: =AF67-AF132 -> 592676.65 | AG137: =SUM(U137:AF137) -> 7112119.8 | AH137: =T137+AG137 -> 10833178
B138: GP % (Weighted) | L138: =IFERROR(L137/L67,0) -> 0.25 | M138: =IFERROR(M137/M67,0) -> 0.25 | N138: =IFERROR(N137/N67,0) -> 0.25 | O138: =IFERROR(O137/O67,0) -> 0.25 | P138: =IFERROR(P137/P67,0) -> 0.25 | Q138: =IFERROR(Q137/Q67,0) -> 0.25 | R138: =IFERROR(R137/R67,0) -> 0.25 | S138: =IFERROR(S137/S67,0) -> 0.25 | ... AH138: =IFERROR(AH137/AH67,0) -> 0.25
A140: GP per Stage (Unweighted) — Revenue minus Cost, filtered by Stage
B141: GP — Closed Lost | C141: 0 | L141: =SUMIFS(L6:L65,D6:D65,"Closed Lost")-SUMIFS(L71:L130,D71:D130,"Closed Lost") -> 0 | M141: =SUMIFS(M6:M65,D6:D65,"Closed Lost")-SUMIFS(M71:M130,D71:D130,"Closed Lost") -> 0 | N141: =SUMIFS(N6:N65,D6:D65,"Closed Lost")-SUMIFS(N71:N130,D71:D130,"Closed Lost") -> 0 | O141: =SUMIFS(O6:O65,D6:D65,"Closed Lost")-SUMIFS(O71:O130,D71:D130,"Closed Lost") -> 0 | P141: =SUMIFS(P6:P65,D6:D65,"Closed Lost")-SUMIFS(P71:P130,D71:D130,"Closed Lost") -> 0 | Q141: =SUMIFS(Q6:Q65,D6:D65,"Closed Lost")-SUMIFS(Q71:Q130,D71:D130,"Closed Lost") -> 0 | R141: =SUMIFS(R6:R65,D6:D65,"Closed Lost")-SUMIFS(R71:R130,D71:D130,"Closed Lost") -> 0 | S141: =SUMIFS(S6:S65,D6:D65,"Closed Lost")-SUMIFS(S71:S130,D71:D130,"Closed Lost") -> 0 | T141: =SUM(L141:S141) -> 0 | U141: =SUMIFS(U6:U65,D6:D65,"Closed Lost")-SUMIFS(U71:U130,D71:D130,"Closed Lost") -> 0 | V141: =SUMIFS(V6:V65,D6:D65,"Closed Lost")-SUMIFS(V71:V130,D71:D130,"Closed Lost") -> 0 | W141: =SUMIFS(W6:W65,D6:D65,"Closed Lost")-SUMIFS(W71:W130,D71:D130,"Closed Lost") -> 0 | X141: =SUMIFS(X6:X65,D6:D65,"Closed Lost")-SUMIFS(X71:X130,D71:D130,"Closed Lost") -> 0 | Y141: =SUMIFS(Y6:Y65,D6:D65,"Closed Lost")-SUMIFS(Y71:Y130,D71:D130,"Closed Lost") -> 0 | Z141: =SUMIFS(Z6:Z65,D6:D65,"Closed Lost")-SUMIFS(Z71:Z130,D71:D130,"Closed Lost") -> 0 | AA141: =SUMIFS(AA6:AA65,D6:D65,"Closed Lost")-SUMIFS(AA71:AA130,D71:D130,"Closed Lost") -> 0 | AB141: =SUMIFS(AB6:AB65,D6:D65,"Closed Lost")-SUMIFS(AB71:AB130,D71:D130,"Closed Lost") -> 0 | AC141: =SUMIFS(AC6:AC65,D6:D65,"Closed Lost")-SUMIFS(AC71:AC130,D71:D130,"Closed Lost") -> 0 | AD141: =SUMIFS(AD6:AD65,D6:D65,"Closed Lost")-SUMIFS(AD71:AD130,D71:D130,"Closed Lost") -> 0 | AE141: =SUMIFS(AE6:AE65,D6:D65,"Closed Lost")-SUMIFS(AE71:AE130,D71:D130,"Closed Lost") -> 0 | AF141: =SUMIFS(AF6:AF65,D6:D65,"Closed Lost")-SUMIFS(AF71:AF130,D71:D130,"Closed Lost") -> 0 | AG141: =SUM(U141:AF141) -> 0 | AH141: =T141+AG141 -> 0
B142: GP — Prospecting | C142: 0.2 | L142: =SUMIFS(L6:L65,D6:D65,"Prospecting")-SUMIFS(L71:L130,D71:D130,"Prospecting") -> 0 | M142: =SUMIFS(M6:M65,D6:D65,"Prospecting")-SUMIFS(M71:M130,D71:D130,"Prospecting") -> 0 | N142: =SUMIFS(N6:N65,D6:D65,"Prospecting")-SUMIFS(N71:N130,D71:D130,"Prospecting") -> 50000 | O142: =SUMIFS(O6:O65,D6:D65,"Prospecting")-SUMIFS(O71:O130,D71:D130,"Prospecting") -> 50000 | P142: =SUMIFS(P6:P65,D6:D65,"Prospecting")-SUMIFS(P71:P130,D71:D130,"Prospecting") -> 50000 | Q142: =SUMIFS(Q6:Q65,D6:D65,"Prospecting")-SUMIFS(Q71:Q130,D71:D130,"Prospecting") -> 50000 | R142: =SUMIFS(R6:R65,D6:D65,"Prospecting")-SUMIFS(R71:R130,D71:D130,"Prospecting") -> 50000 | S142: =SUMIFS(S6:S65,D6:D65,"Prospecting")-SUMIFS(S71:S130,D71:D130,"Prospecting") -> 50000 | T142: =SUM(L142:S142) -> 300000 | U142: =SUMIFS(U6:U65,D6:D65,"Prospecting")-SUMIFS(U71:U130,D71:D130,"Prospecting") -> 50000 | V142: =SUMIFS(V6:V65,D6:D65,"Prospecting")-SUMIFS(V71:V130,D71:D130,"Prospecting") -> 50000 | W142: =SUMIFS(W6:W65,D6:D65,"Prospecting")-SUMIFS(W71:W130,D71:D130,"Prospecting") -> 50000 | X142: =SUMIFS(X6:X65,D6:D65,"Prospecting")-SUMIFS(X71:X130,D71:D130,"Prospecting") -> 50000 | Y142: =SUMIFS(Y6:Y65,D6:D65,"Prospecting")-SUMIFS(Y71:Y130,D71:D130,"Prospecting") -> 50000 | Z142: =SUMIFS(Z6:Z65,D6:D65,"Prospecting")-SUMIFS(Z71:Z130,D71:D130,"Prospecting") -> 50000 | AA142: =SUMIFS(AA6:AA65,D6:D65,"Prospecting")-SUMIFS(AA71:AA130,D71:D130,"Prospecting") -> 50000 | AB142: =SUMIFS(AB6:AB65,D6:D65,"Prospecting")-SUMIFS(AB71:AB130,D71:D130,"Prospecting") -> 50000 | AC142: =SUMIFS(AC6:AC65,D6:D65,"Prospecting")-SUMIFS(AC71:AC130,D71:D130,"Prospecting") -> 50000 | AD142: =SUMIFS(AD6:AD65,D6:D65,"Prospecting")-SUMIFS(AD71:AD130,D71:D130,"Prospecting") -> 50000 | AE142: =SUMIFS(AE6:AE65,D6:D65,"Prospecting")-SUMIFS(AE71:AE130,D71:D130,"Prospecting") -> 50000 | AF142: =SUMIFS(AF6:AF65,D6:D65,"Prospecting")-SUMIFS(AF71:AF130,D71:D130,"Prospecting") -> 50000 | AG142: =SUM(U142:AF142) -> 600000 | AH142: =T142+AG142 -> 900000
B143: GP — Qualified | C143: 0.4 | L143: =SUMIFS(L6:L65,D6:D65,"Qualified")-SUMIFS(L71:L130,D71:D130,"Qualified") -> 0 | M143: =SUMIFS(M6:M65,D6:D65,"Qualified")-SUMIFS(M71:M130,D71:D130,"Qualified") -> 17708.333 | N143: =SUMIFS(N6:N65,D6:D65,"Qualified")-SUMIFS(N71:N130,D71:D130,"Qualified") -> 17708.333 | O143: =SUMIFS(O6:O65,D6:D65,"Qualified")-SUMIFS(O71:O130,D71:D130,"Qualified") -> 17708.333 | P143: =SUMIFS(P6:P65,D6:D65,"Qualified")-SUMIFS(P71:P130,D71:D130,"Qualified") -> 17708.333 | Q143: =SUMIFS(Q6:Q65,D6:D65,"Qualified")-SUMIFS(Q71:Q130,D71:D130,"Qualified") -> 17708.333 | R143: =SUMIFS(R6:R65,D6:D65,"Qualified")-SUMIFS(R71:R130,D71:D130,"Qualified") -> 17708.333 | S143: =SUMIFS(S6:S65,D6:D65,"Qualified")-SUMIFS(S71:S130,D71:D130,"Qualified") -> 17708.333 | T143: =SUM(L143:S143) -> 123958.33 | U143: =SUMIFS(U6:U65,D6:D65,"Qualified")-SUMIFS(U71:U130,D71:D130,"Qualified") -> 17708.333 | V143: =SUMIFS(V6:V65,D6:D65,"Qualified")-SUMIFS(V71:V130,D71:D130,"Qualified") -> 17708.333 | W143: =SUMIFS(W6:W65,D6:D65,"Qualified")-SUMIFS(W71:W130,D71:D130,"Qualified") -> 17708.333 | X143: =SUMIFS(X6:X65,D6:D65,"Qualified")-SUMIFS(X71:X130,D71:D130,"Qualified") -> 17708.333 | Y143: =SUMIFS(Y6:Y65,D6:D65,"Qualified")-SUMIFS(Y71:Y130,D71:D130,"Qualified") -> 17708.333 | Z143: =SUMIFS(Z6:Z65,D6:D65,"Qualified")-SUMIFS(Z71:Z130,D71:D130,"Qualified") -> 17708.333 | AA143: =SUMIFS(AA6:AA65,D6:D65,"Qualified")-SUMIFS(AA71:AA130,D71:D130,"Qualified") -> 17708.333 | AB143: =SUMIFS(AB6:AB65,D6:D65,"Qualified")-SUMIFS(AB71:AB130,D71:D130,"Qualified") -> 17708.333 | AC143: =SUMIFS(AC6:AC65,D6:D65,"Qualified")-SUMIFS(AC71:AC130,D71:D130,"Qualified") -> 17708.333 | AD143: =SUMIFS(AD6:AD65,D6:D65,"Qualified")-SUMIFS(AD71:AD130,D71:D130,"Qualified") -> 17708.333 | AE143: =SUMIFS(AE6:AE65,D6:D65,"Qualified")-SUMIFS(AE71:AE130,D71:D130,"Qualified") -> 17708.333 | AF143: =SUMIFS(AF6:AF65,D6:D65,"Qualified")-SUMIFS(AF71:AF130,D71:D130,"Qualified") -> 17708.333 | AG143: =SUM(U143:AF143) -> 212500 | AH143: =T143+AG143 -> 336458.33
B144: GP — Proposal Sent | C144: 0.6 | L144: =SUMIFS(L6:L65,D6:D65,"Proposal Sent")-SUMIFS(L71:L130,D71:D130,"Proposal Sent") -> 77238.167 | M144: =SUMIFS(M6:M65,D6:D65,"Proposal Sent")-SUMIFS(M71:M130,D71:D130,"Proposal Sent") -> 138711.08 | N144: =SUMIFS(N6:N65,D6:D65,"Proposal Sent")-SUMIFS(N71:N130,D71:D130,"Proposal Sent") -> 316648.58 | O144: =SUMIFS(O6:O65,D6:D65,"Proposal Sent")-SUMIFS(O71:O130,D71:D130,"Proposal Sent") -> 354773.58 | P144: =SUMIFS(P6:P65,D6:D65,"Proposal Sent")-SUMIFS(P71:P130,D71:D130,"Proposal Sent") -> 402481.92 | Q144: =SUMIFS(Q6:Q65,D6:D65,"Proposal Sent")-SUMIFS(Q71:Q130,D71:D130,"Proposal Sent") -> 402481.92 | R144: =SUMIFS(R6:R65,D6:D65,"Proposal Sent")-SUMIFS(R71:R130,D71:D130,"Proposal Sent") -> 529606.92 | S144: =SUMIFS(S6:S65,D6:D65,"Proposal Sent")-SUMIFS(S71:S130,D71:D130,"Proposal Sent") -> 529606.92 | T144: =SUM(L144:S144) -> 2751549.1 | U144: =SUMIFS(U6:U65,D6:D65,"Proposal Sent")-SUMIFS(U71:U130,D71:D130,"Proposal Sent") -> 529606.92 | V144: =SUMIFS(V6:V65,D6:D65,"Proposal Sent")-SUMIFS(V71:V130,D71:D130,"Proposal Sent") -> 529606.92 | W144: =SUMIFS(W6:W65,D6:D65,"Proposal Sent")-SUMIFS(W71:W130,D71:D130,"Proposal Sent") -> 529606.92 | X144: =SUMIFS(X6:X65,D6:D65,"Proposal Sent")-SUMIFS(X71:X130,D71:D130,"Proposal Sent") -> 529606.92 | Y144: =SUMIFS(Y6:Y65,D6:D65,"Proposal Sent")-SUMIFS(Y71:Y130,D71:D130,"Proposal Sent") -> 529606.92 | Z144: =SUMIFS(Z6:Z65,D6:D65,"Proposal Sent")-SUMIFS(Z71:Z130,D71:D130,"Proposal Sent") -> 529606.92 | AA144: =SUMIFS(AA6:AA65,D6:D65,"Proposal Sent")-SUMIFS(AA71:AA130,D71:D130,"Proposal Sent") -> 529606.92 | AB144: =SUMIFS(AB6:AB65,D6:D65,"Proposal Sent")-SUMIFS(AB71:AB130,D71:D130,"Proposal Sent") -> 529606.92 | AC144: =SUMIFS(AC6:AC65,D6:D65,"Proposal Sent")-SUMIFS(AC71:AC130,D71:D130,"Proposal Sent") -> 529606.92 | AD144: =SUMIFS(AD6:AD65,D6:D65,"Proposal Sent")-SUMIFS(AD71:AD130,D71:D130,"Proposal Sent") -> 529606.92 | AE144: =SUMIFS(AE6:AE65,D6:D65,"Proposal Sent")-SUMIFS(AE71:AE130,D71:D130,"Proposal Sent") -> 529606.92 | AF144: =SUMIFS(AF6:AF65,D6:D65,"Proposal Sent")-SUMIFS(AF71:AF130,D71:D130,"Proposal Sent") -> 529606.92 | AG144: =SUM(U144:AF144) -> 6355283 | AH144: =T144+AG144 -> 9106832.1
B145: GP — Shortlisted | C145: 0.75 | L145: =SUMIFS(L6:L65,D6:D65,"Shortlisted")-SUMIFS(L71:L130,D71:D130,"Shortlisted") -> 15125 | M145: =SUMIFS(M6:M65,D6:D65,"Shortlisted")-SUMIFS(M71:M130,D71:D130,"Shortlisted") -> 55825 | N145: =SUMIFS(N6:N65,D6:D65,"Shortlisted")-SUMIFS(N71:N130,D71:D130,"Shortlisted") -> 73533.333 | O145: =SUMIFS(O6:O65,D6:D65,"Shortlisted")-SUMIFS(O71:O130,D71:D130,"Shortlisted") -> 73533.333 | P145: =SUMIFS(P6:P65,D6:D65,"Shortlisted")-SUMIFS(P71:P130,D71:D130,"Shortlisted") -> 73533.333 | Q145: =SUMIFS(Q6:Q65,D6:D65,"Shortlisted")-SUMIFS(Q71:Q130,D71:D130,"Shortlisted") -> 73533.333 | R145: =SUMIFS(R6:R65,D6:D65,"Shortlisted")-SUMIFS(R71:R130,D71:D130,"Shortlisted") -> 73533.333 | S145: =SUMIFS(S6:S65,D6:D65,"Shortlisted")-SUMIFS(S71:S130,D71:D130,"Shortlisted") -> 73533.333 | T145: =SUM(L145:S145) -> 512150 | U145: =SUMIFS(U6:U65,D6:D65,"Shortlisted")-SUMIFS(U71:U130,D71:D130,"Shortlisted") -> 73533.333 | V145: =SUMIFS(V6:V65,D6:D65,"Shortlisted")-SUMIFS(V71:V130,D71:D130,"Shortlisted") -> 73533.333 | W145: =SUMIFS(W6:W65,D6:D65,"Shortlisted")-SUMIFS(W71:W130,D71:D130,"Shortlisted") -> 73533.333 | X145: =SUMIFS(X6:X65,D6:D65,"Shortlisted")-SUMIFS(X71:X130,D71:D130,"Shortlisted") -> 73533.333 | Y145: =SUMIFS(Y6:Y65,D6:D65,"Shortlisted")-SUMIFS(Y71:Y130,D71:D130,"Shortlisted") -> 73533.333 | Z145: =SUMIFS(Z6:Z65,D6:D65,"Shortlisted")-SUMIFS(Z71:Z130,D71:D130,"Shortlisted") -> 73533.333 | AA145: =SUMIFS(AA6:AA65,D6:D65,"Shortlisted")-SUMIFS(AA71:AA130,D71:D130,"Shortlisted") -> 73533.333 | AB145: =SUMIFS(AB6:AB65,D6:D65,"Shortlisted")-SUMIFS(AB71:AB130,D71:D130,"Shortlisted") -> 73533.333 | AC145: =SUMIFS(AC6:AC65,D6:D65,"Shortlisted")-SUMIFS(AC71:AC130,D71:D130,"Shortlisted") -> 73533.333 | AD145: =SUMIFS(AD6:AD65,D6:D65,"Shortlisted")-SUMIFS(AD71:AD130,D71:D130,"Shortlisted") -> 73533.333 | AE145: =SUMIFS(AE6:AE65,D6:D65,"Shortlisted")-SUMIFS(AE71:AE130,D71:D130,"Shortlisted") -> 73533.333 | AF145: =SUMIFS(AF6:AF65,D6:D65,"Shortlisted")-SUMIFS(AF71:AF130,D71:D130,"Shortlisted") -> 73533.333 | AG145: =SUM(U145:AF145) -> 882400 | AH145: =T145+AG145 -> 1394550
B146: GP — Contract Negotiation | C146: 0.9 | L146: =SUMIFS(L6:L65,D6:D65,"Contract Negotiation")-SUMIFS(L71:L130,D71:D130,"Contract Negotiation") -> 41250 | M146: =SUMIFS(M6:M65,D6:D65,"Contract Negotiation")-SUMIFS(M71:M130,D71:D130,"Contract Negotiation") -> 91250 | N146: =SUMIFS(N6:N65,D6:D65,"Contract Negotiation")-SUMIFS(N71:N130,D71:D130,"Contract Negotiation") -> 91250 | O146: =SUMIFS(O6:O65,D6:D65,"Contract Negotiation")-SUMIFS(O71:O130,D71:D130,"Contract Negotiation") -> 91250 | P146: =SUMIFS(P6:P65,D6:D65,"Contract Negotiation")-SUMIFS(P71:P130,D71:D130,"Contract Negotiation") -> 91250 | Q146: =SUMIFS(Q6:Q65,D6:D65,"Contract Negotiation")-SUMIFS(Q71:Q130,D71:D130,"Contract Negotiation") -> 91250 | R146: =SUMIFS(R6:R65,D6:D65,"Contract Negotiation")-SUMIFS(R71:R130,D71:D130,"Contract Negotiation") -> 91250 | S146: =SUMIFS(S6:S65,D6:D65,"Contract Negotiation")-SUMIFS(S71:S130,D71:D130,"Contract Negotiation") -> 91250 | T146: =SUM(L146:S146) -> 680000 | U146: =SUMIFS(U6:U65,D6:D65,"Contract Negotiation")-SUMIFS(U71:U130,D71:D130,"Contract Negotiation") -> 91250 | V146: =SUMIFS(V6:V65,D6:D65,"Contract Negotiation")-SUMIFS(V71:V130,D71:D130,"Contract Negotiation") -> 91250 | W146: =SUMIFS(W6:W65,D6:D65,"Contract Negotiation")-SUMIFS(W71:W130,D71:D130,"Contract Negotiation") -> 91250 | X146: =SUMIFS(X6:X65,D6:D65,"Contract Negotiation")-SUMIFS(X71:X130,D71:D130,"Contract Negotiation") -> 91250 | Y146: =SUMIFS(Y6:Y65,D6:D65,"Contract Negotiation")-SUMIFS(Y71:Y130,D71:D130,"Contract Negotiation") -> 91250 | Z146: =SUMIFS(Z6:Z65,D6:D65,"Contract Negotiation")-SUMIFS(Z71:Z130,D71:D130,"Contract Negotiation") -> 91250 | AA146: =SUMIFS(AA6:AA65,D6:D65,"Contract Negotiation")-SUMIFS(AA71:AA130,D71:D130,"Contract Negotiation") -> 91250 | AB146: =SUMIFS(AB6:AB65,D6:D65,"Contract Negotiation")-SUMIFS(AB71:AB130,D71:D130,"Contract Negotiation") -> 91250 | AC146: =SUMIFS(AC6:AC65,D6:D65,"Contract Negotiation")-SUMIFS(AC71:AC130,D71:D130,"Contract Negotiation") -> 91250 | AD146: =SUMIFS(AD6:AD65,D6:D65,"Contract Negotiation")-SUMIFS(AD71:AD130,D71:D130,"Contract Negotiation") -> 91250 | AE146: =SUMIFS(AE6:AE65,D6:D65,"Contract Negotiation")-SUMIFS(AE71:AE130,D71:D130,"Contract Negotiation") -> 91250 | AF146: =SUMIFS(AF6:AF65,D6:D65,"Contract Negotiation")-SUMIFS(AF71:AF130,D71:D130,"Contract Negotiation") -> 91250 | AG146: =SUM(U146:AF146) -> 1095000 | AH146: =T146+AG146 -> 1775000
B147: GP — Closed Won | C147: 1 | L147: =SUMIFS(L6:L65,D6:D65,"Closed Won")-SUMIFS(L71:L130,D71:D130,"Closed Won") -> 120554.17 | M147: =SUMIFS(M6:M65,D6:D65,"Closed Won")-SUMIFS(M71:M130,D71:D130,"Closed Won") -> 120554.17 | N147: =SUMIFS(N6:N65,D6:D65,"Closed Won")-SUMIFS(N71:N130,D71:D130,"Closed Won") -> 120554.17 | O147: =SUMIFS(O6:O65,D6:D65,"Closed Won")-SUMIFS(O71:O130,D71:D130,"Closed Won") -> 120554.17 | P147: =SUMIFS(P6:P65,D6:D65,"Closed Won")-SUMIFS(P71:P130,D71:D130,"Closed Won") -> 120554.17 | Q147: =SUMIFS(Q6:Q65,D6:D65,"Closed Won")-SUMIFS(Q71:Q130,D71:D130,"Closed Won") -> 120554.17 | R147: =SUMIFS(R6:R65,D6:D65,"Closed Won")-SUMIFS(R71:R130,D71:D130,"Closed Won") -> 120554.17 | S147: =SUMIFS(S6:S65,D6:D65,"Closed Won")-SUMIFS(S71:S130,D71:D130,"Closed Won") -> 120554.17 | T147: =SUM(L147:S147) -> 964433.33 | U147: =SUMIFS(U6:U65,D6:D65,"Closed Won")-SUMIFS(U71:U130,D71:D130,"Closed Won") -> 120554.17 | V147: =SUMIFS(V6:V65,D6:D65,"Closed Won")-SUMIFS(V71:V130,D71:D130,"Closed Won") -> 120554.17 | W147: =SUMIFS(W6:W65,D6:D65,"Closed Won")-SUMIFS(W71:W130,D71:D130,"Closed Won") -> 120554.17 | X147: =SUMIFS(X6:X65,D6:D65,"Closed Won")-SUMIFS(X71:X130,D71:D130,"Closed Won") -> 120554.17 | Y147: =SUMIFS(Y6:Y65,D6:D65,"Closed Won")-SUMIFS(Y71:Y130,D71:D130,"Closed Won") -> 120554.17 | Z147: =SUMIFS(Z6:Z65,D6:D65,"Closed Won")-SUMIFS(Z71:Z130,D71:D130,"Closed Won") -> 120554.17 | AA147: =SUMIFS(AA6:AA65,D6:D65,"Closed Won")-SUMIFS(AA71:AA130,D71:D130,"Closed Won") -> 120554.17 | AB147: =SUMIFS(AB6:AB65,D6:D65,"Closed Won")-SUMIFS(AB71:AB130,D71:D130,"Closed Won") -> 120554.17 | AC147: =SUMIFS(AC6:AC65,D6:D65,"Closed Won")-SUMIFS(AC71:AC130,D71:D130,"Closed Won") -> 120554.17 | AD147: =SUMIFS(AD6:AD65,D6:D65,"Closed Won")-SUMIFS(AD71:AD130,D71:D130,"Closed Won") -> 120554.17 | AE147: =SUMIFS(AE6:AE65,D6:D65,"Closed Won")-SUMIFS(AE71:AE130,D71:D130,"Closed Won") -> 120554.17 | AF147: =SUMIFS(AF6:AF65,D6:D65,"Closed Won")-SUMIFS(AF71:AF130,D71:D130,"Closed Won") -> 120554.17 | AG147: =SUM(U147:AF147) -> 1446650 | AH147: =T147+AG147 -> 2411083.3
A149: Revenue per Stage (Unweighted) — Section 1 revenue, filtered by stage
B150: Revenue — Closed Lost | C150: 0 | L150: =SUMIFS(L6:L65,D6:D65,"Closed Lost") -> 0 | M150: =SUMIFS(M6:M65,D6:D65,"Closed Lost") -> 0 | N150: =SUMIFS(N6:N65,D6:D65,"Closed Lost") -> 0 | O150: =SUMIFS(O6:O65,D6:D65,"Closed Lost") -> 0 | P150: =SUMIFS(P6:P65,D6:D65,"Closed Lost") -> 0 | Q150: =SUMIFS(Q6:Q65,D6:D65,"Closed Lost") -> 0 | R150: =SUMIFS(R6:R65,D6:D65,"Closed Lost") -> 0 | S150: =SUMIFS(S6:S65,D6:D65,"Closed Lost") -> 0 | T150: =SUM(L150:S150) -> 0 | U150: =SUMIFS(U6:U65,D6:D65,"Closed Lost") -> 0 | V150: =SUMIFS(V6:V65,D6:D65,"Closed Lost") -> 0 | W150: =SUMIFS(W6:W65,D6:D65,"Closed Lost") -> 0 | X150: =SUMIFS(X6:X65,D6:D65,"Closed Lost") -> 0 | Y150: =SUMIFS(Y6:Y65,D6:D65,"Closed Lost") -> 0 | Z150: =SUMIFS(Z6:Z65,D6:D65,"Closed Lost") -> 0 | AA150: =SUMIFS(AA6:AA65,D6:D65,"Closed Lost") -> 0 | AB150: =SUMIFS(AB6:AB65,D6:D65,"Closed Lost") -> 0 | AC150: =SUMIFS(AC6:AC65,D6:D65,"Closed Lost") -> 0 | AD150: =SUMIFS(AD6:AD65,D6:D65,"Closed Lost") -> 0 | AE150: =SUMIFS(AE6:AE65,D6:D65,"Closed Lost") -> 0 | AF150: =SUMIFS(AF6:AF65,D6:D65,"Closed Lost") -> 0 | AG150: =SUM(U150:AF150) -> 0 | AH150: =T150+AG150 -> 0
B151: Revenue — Prospecting | C151: 0.2 | L151: =SUMIFS(L6:L65,D6:D65,"Prospecting") -> 0 | M151: =SUMIFS(M6:M65,D6:D65,"Prospecting") -> 0 | N151: =SUMIFS(N6:N65,D6:D65,"Prospecting") -> 200000 | O151: =SUMIFS(O6:O65,D6:D65,"Prospecting") -> 200000 | P151: =SUMIFS(P6:P65,D6:D65,"Prospecting") -> 200000 | Q151: =SUMIFS(Q6:Q65,D6:D65,"Prospecting") -> 200000 | R151: =SUMIFS(R6:R65,D6:D65,"Prospecting") -> 200000 | S151: =SUMIFS(S6:S65,D6:D65,"Prospecting") -> 200000 | T151: =SUM(L151:S151) -> 1200000 | U151: =SUMIFS(U6:U65,D6:D65,"Prospecting") -> 200000 | V151: =SUMIFS(V6:V65,D6:D65,"Prospecting") -> 200000 | W151: =SUMIFS(W6:W65,D6:D65,"Prospecting") -> 200000 | X151: =SUMIFS(X6:X65,D6:D65,"Prospecting") -> 200000 | Y151: =SUMIFS(Y6:Y65,D6:D65,"Prospecting") -> 200000 | Z151: =SUMIFS(Z6:Z65,D6:D65,"Prospecting") -> 200000 | AA151: =SUMIFS(AA6:AA65,D6:D65,"Prospecting") -> 200000 | AB151: =SUMIFS(AB6:AB65,D6:D65,"Prospecting") -> 200000 | AC151: =SUMIFS(AC6:AC65,D6:D65,"Prospecting") -> 200000 | AD151: =SUMIFS(AD6:AD65,D6:D65,"Prospecting") -> 200000 | AE151: =SUMIFS(AE6:AE65,D6:D65,"Prospecting") -> 200000 | AF151: =SUMIFS(AF6:AF65,D6:D65,"Prospecting") -> 200000 | AG151: =SUM(U151:AF151) -> 2400000 | AH151: =T151+AG151 -> 3600000
B152: Revenue — Qualified | C152: 0.4 | L152: =SUMIFS(L6:L65,D6:D65,"Qualified") -> 0 | M152: =SUMIFS(M6:M65,D6:D65,"Qualified") -> 70833.333 | N152: =SUMIFS(N6:N65,D6:D65,"Qualified") -> 70833.333 | O152: =SUMIFS(O6:O65,D6:D65,"Qualified") -> 70833.333 | P152: =SUMIFS(P6:P65,D6:D65,"Qualified") -> 70833.333 | Q152: =SUMIFS(Q6:Q65,D6:D65,"Qualified") -> 70833.333 | R152: =SUMIFS(R6:R65,D6:D65,"Qualified") -> 70833.333 | S152: =SUMIFS(S6:S65,D6:D65,"Qualified") -> 70833.333 | T152: =SUM(L152:S152) -> 495833.33 | U152: =SUMIFS(U6:U65,D6:D65,"Qualified") -> 70833.333 | V152: =SUMIFS(V6:V65,D6:D65,"Qualified") -> 70833.333 | W152: =SUMIFS(W6:W65,D6:D65,"Qualified") -> 70833.333 | X152: =SUMIFS(X6:X65,D6:D65,"Qualified") -> 70833.333 | Y152: =SUMIFS(Y6:Y65,D6:D65,"Qualified") -> 70833.333 | Z152: =SUMIFS(Z6:Z65,D6:D65,"Qualified") -> 70833.333 | AA152: =SUMIFS(AA6:AA65,D6:D65,"Qualified") -> 70833.333 | AB152: =SUMIFS(AB6:AB65,D6:D65,"Qualified") -> 70833.333 | AC152: =SUMIFS(AC6:AC65,D6:D65,"Qualified") -> 70833.333 | AD152: =SUMIFS(AD6:AD65,D6:D65,"Qualified") -> 70833.333 | AE152: =SUMIFS(AE6:AE65,D6:D65,"Qualified") -> 70833.333 | AF152: =SUMIFS(AF6:AF65,D6:D65,"Qualified") -> 70833.333 | AG152: =SUM(U152:AF152) -> 850000 | AH152: =T152+AG152 -> 1345833.3
B153: Revenue — Proposal Sent | C153: 0.6 | L153: =SUMIFS(L6:L65,D6:D65,"Proposal Sent") -> 308952.67 | M153: =SUMIFS(M6:M65,D6:D65,"Proposal Sent") -> 554844.33 | N153: =SUMIFS(N6:N65,D6:D65,"Proposal Sent") -> 1266594.3 | O153: =SUMIFS(O6:O65,D6:D65,"Proposal Sent") -> 1419094.3 | P153: =SUMIFS(P6:P65,D6:D65,"Proposal Sent") -> 1609927.7 | Q153: =SUMIFS(Q6:Q65,D6:D65,"Proposal Sent") -> 1609927.7 | R153: =SUMIFS(R6:R65,D6:D65,"Proposal Sent") -> 2118427.7 | S153: =SUMIFS(S6:S65,D6:D65,"Proposal Sent") -> 2118427.7 | T153: =SUM(L153:S153) -> 11006196 | U153: =SUMIFS(U6:U65,D6:D65,"Proposal Sent") -> 2118427.7 | V153: =SUMIFS(V6:V65,D6:D65,"Proposal Sent") -> 2118427.7 | W153: =SUMIFS(W6:W65,D6:D65,"Proposal Sent") -> 2118427.7 | X153: =SUMIFS(X6:X65,D6:D65,"Proposal Sent") -> 2118427.7 | Y153: =SUMIFS(Y6:Y65,D6:D65,"Proposal Sent") -> 2118427.7 | Z153: =SUMIFS(Z6:Z65,D6:D65,"Proposal Sent") -> 2118427.7 | AA153: =SUMIFS(AA6:AA65,D6:D65,"Proposal Sent") -> 2118427.7 | AB153: =SUMIFS(AB6:AB65,D6:D65,"Proposal Sent") -> 2118427.7 | AC153: =SUMIFS(AC6:AC65,D6:D65,"Proposal Sent") -> 2118427.7 | AD153: =SUMIFS(AD6:AD65,D6:D65,"Proposal Sent") -> 2118427.7 | AE153: =SUMIFS(AE6:AE65,D6:D65,"Proposal Sent") -> 2118427.7 | AF153: =SUMIFS(AF6:AF65,D6:D65,"Proposal Sent") -> 2118427.7 | AG153: =SUM(U153:AF153) -> 25421132 | AH153: =T153+AG153 -> 36427328
B154: Revenue — Shortlisted | C154: 0.75 | L154: =SUMIFS(L6:L65,D6:D65,"Shortlisted") -> 60500 | M154: =SUMIFS(M6:M65,D6:D65,"Shortlisted") -> 223300 | N154: =SUMIFS(N6:N65,D6:D65,"Shortlisted") -> 294133.33 | O154: =SUMIFS(O6:O65,D6:D65,"Shortlisted") -> 294133.33 | P154: =SUMIFS(P6:P65,D6:D65,"Shortlisted") -> 294133.33 | Q154: =SUMIFS(Q6:Q65,D6:D65,"Shortlisted") -> 294133.33 | R154: =SUMIFS(R6:R65,D6:D65,"Shortlisted") -> 294133.33 | S154: =SUMIFS(S6:S65,D6:D65,"Shortlisted") -> 294133.33 | T154: =SUM(L154:S154) -> 2048600 | U154: =SUMIFS(U6:U65,D6:D65,"Shortlisted") -> 294133.33 | V154: =SUMIFS(V6:V65,D6:D65,"Shortlisted") -> 294133.33 | W154: =SUMIFS(W6:W65,D6:D65,"Shortlisted") -> 294133.33 | X154: =SUMIFS(X6:X65,D6:D65,"Shortlisted") -> 294133.33 | Y154: =SUMIFS(Y6:Y65,D6:D65,"Shortlisted") -> 294133.33 | Z154: =SUMIFS(Z6:Z65,D6:D65,"Shortlisted") -> 294133.33 | AA154: =SUMIFS(AA6:AA65,D6:D65,"Shortlisted") -> 294133.33 | AB154: =SUMIFS(AB6:AB65,D6:D65,"Shortlisted") -> 294133.33 | AC154: =SUMIFS(AC6:AC65,D6:D65,"Shortlisted") -> 294133.33 | AD154: =SUMIFS(AD6:AD65,D6:D65,"Shortlisted") -> 294133.33 | AE154: =SUMIFS(AE6:AE65,D6:D65,"Shortlisted") -> 294133.33 | AF154: =SUMIFS(AF6:AF65,D6:D65,"Shortlisted") -> 294133.33 | AG154: =SUM(U154:AF154) -> 3529600 | AH154: =T154+AG154 -> 5578200
B155: Revenue — Contract Negotiation | C155: 0.9 | L155: =SUMIFS(L6:L65,D6:D65,"Contract Negotiation") -> 165000 | M155: =SUMIFS(M6:M65,D6:D65,"Contract Negotiation") -> 365000 | N155: =SUMIFS(N6:N65,D6:D65,"Contract Negotiation") -> 365000 | O155: =SUMIFS(O6:O65,D6:D65,"Contract Negotiation") -> 365000 | P155: =SUMIFS(P6:P65,D6:D65,"Contract Negotiation") -> 365000 | Q155: =SUMIFS(Q6:Q65,D6:D65,"Contract Negotiation") -> 365000 | R155: =SUMIFS(R6:R65,D6:D65,"Contract Negotiation") -> 365000 | S155: =SUMIFS(S6:S65,D6:D65,"Contract Negotiation") -> 365000 | T155: =SUM(L155:S155) -> 2720000 | U155: =SUMIFS(U6:U65,D6:D65,"Contract Negotiation") -> 365000 | V155: =SUMIFS(V6:V65,D6:D65,"Contract Negotiation") -> 365000 | W155: =SUMIFS(W6:W65,D6:D65,"Contract Negotiation") -> 365000 | X155: =SUMIFS(X6:X65,D6:D65,"Contract Negotiation") -> 365000 | Y155: =SUMIFS(Y6:Y65,D6:D65,"Contract Negotiation") -> 365000 | Z155: =SUMIFS(Z6:Z65,D6:D65,"Contract Negotiation") -> 365000 | AA155: =SUMIFS(AA6:AA65,D6:D65,"Contract Negotiation") -> 365000 | AB155: =SUMIFS(AB6:AB65,D6:D65,"Contract Negotiation") -> 365000 | AC155: =SUMIFS(AC6:AC65,D6:D65,"Contract Negotiation") -> 365000 | AD155: =SUMIFS(AD6:AD65,D6:D65,"Contract Negotiation") -> 365000 | AE155: =SUMIFS(AE6:AE65,D6:D65,"Contract Negotiation") -> 365000 | AF155: =SUMIFS(AF6:AF65,D6:D65,"Contract Negotiation") -> 365000 | AG155: =SUM(U155:AF155) -> 4380000 | AH155: =T155+AG155 -> 7100000
B156: Revenue — Closed Won | C156: 1 | L156: =SUMIFS(L6:L65,D6:D65,"Closed Won") -> 482216.67 | M156: =SUMIFS(M6:M65,D6:D65,"Closed Won") -> 482216.67 | N156: =SUMIFS(N6:N65,D6:D65,"Closed Won") -> 482216.67 | O156: =SUMIFS(O6:O65,D6:D65,"Closed Won") -> 482216.67 | P156: =SUMIFS(P6:P65,D6:D65,"Closed Won") -> 482216.67 | Q156: =SUMIFS(Q6:Q65,D6:D65,"Closed Won") -> 482216.67 | R156: =SUMIFS(R6:R65,D6:D65,"Closed Won") -> 482216.67 | S156: =SUMIFS(S6:S65,D6:D65,"Closed Won") -> 482216.67 | T156: =SUM(L156:S156) -> 3857733.3 | U156: =SUMIFS(U6:U65,D6:D65,"Closed Won") -> 482216.67 | V156: =SUMIFS(V6:V65,D6:D65,"Closed Won") -> 482216.67 | W156: =SUMIFS(W6:W65,D6:D65,"Closed Won") -> 482216.67 | X156: =SUMIFS(X6:X65,D6:D65,"Closed Won") -> 482216.67 | Y156: =SUMIFS(Y6:Y65,D6:D65,"Closed Won") -> 482216.67 | Z156: =SUMIFS(Z6:Z65,D6:D65,"Closed Won") -> 482216.67 | AA156: =SUMIFS(AA6:AA65,D6:D65,"Closed Won") -> 482216.67 | AB156: =SUMIFS(AB6:AB65,D6:D65,"Closed Won") -> 482216.67 | AC156: =SUMIFS(AC6:AC65,D6:D65,"Closed Won") -> 482216.67 | AD156: =SUMIFS(AD6:AD65,D6:D65,"Closed Won") -> 482216.67 | AE156: =SUMIFS(AE6:AE65,D6:D65,"Closed Won") -> 482216.67 | AF156: =SUMIFS(AF6:AF65,D6:D65,"Closed Won") -> 482216.67 | AG156: =SUM(U156:AF156) -> 5786600 | AH156: =T156+AG156 -> 9644333.3
A158: 4. SPACE AVAILABILITY — PALLET POSITIONS
A159: # | B159: Warehouse | C159: Total Locations (Physical Rac locations) | D159: Total Capacity (Bin + Manual ) | E159: Occupied Capacity ( Physical + Floor + Manual ) | F159: Utilization % | G159: Sellable Capacity | H159: Committed Capacity | I159: Blocked Locations | J159: Virtual Locations | L159: May-26 | M159: Jun-26 | N159: Jul-26 | O159: Aug-26 | P159: Sep-26 | Q159: Oct-26 | R159: Nov-26 | S159: Dec-26 | T159: 2026 Avg | U159: Jan-27 | V159: Feb-27 | W159: Mar-27 | X159: Apr-27 | Y159: May-27 | Z159: Jun-27 | AA159: Jul-27 | AB159: Aug-27 | AC159: Sep-27 | AD159: Oct-27 | AE159: Nov-27 | AF159: Dec-27 | AG159: 2027 Avg | AH159: Avg | AJ159: Notes
A160: 4A. Remaining Available Pallet Positions (= Warehouse Capacity - Cumulative Committed [Closed Won + Contract Negotiation + Shortlisted])
A161: 1 | B161: Dammam Port | C161: =IFERROR(VLOOKUP("Dammam Port",'Warehouse Pallet data input'!$A$4:$J$13,3,FALSE()),0) -> 28694 | D161: =IFERROR(VLOOKUP("Dammam Port",'Warehouse Pallet data input'!$A$4:$J$13,4,FALSE()),0) -> 34755 | E161: =IFERROR(VLOOKUP("Dammam Port",'Warehouse Pallet data input'!$A$4:$J$13,5,FALSE()),0) -> 29782 | F161: =IFERROR(E161/D161,0) -> 0.85691267 | G161: =IFERROR(VLOOKUP("Dammam Port",'Warehouse Pallet data input'!$A$4:$J$13,7,FALSE()),0) -> 4973 | H161: =IFERROR(VLOOKUP("Dammam Port",'Warehouse Pallet data input'!$A$4:$J$13,8,FALSE()),0) -> 23400 | I161: =IFERROR(VLOOKUP("Dammam Port",'Warehouse Pallet data input'!$A$4:$J$13,9,FALSE()),0) -> 0 | J161: =IFERROR(VLOOKUP("Dammam Port",'Warehouse Pallet data input'!$A$4:$J$13,10,FALSE()),0) -> 0 | L161: =G161-L173 -> 4673 | M161: =G161-M173 -> 4673 | N161: =G161-N173 -> 4673 | O161: =G161-O173 -> 4673 | P161: =G161-P173 -> 4673 | Q161: =G161-Q173 -> 4673 | R161: =G161-R173 -> 4673 | S161: =G161-S173 -> 4673 | T161: =IFERROR(AVERAGE(L161:S161),0) -> 4673 | U161: =(-$H161+$J161)-U173 -> -23700 | V161: =(-$H161+$J161)-V173 -> -23700 | W161: =(-$H161+$J161)-W173 -> -23700 | X161: =(-$H161+$J161)-X173 -> -23700 | Y161: =(-$H161+$J161)-Y173 -> -23700 | Z161: =(-$H161+$J161)-Z173 -> -23700 | AA161: =(-$H161+$J161)-AA173 -> -23700 | AB161: =(-$H161+$J161)-AB173 -> -23700 | ... AF161: =(-$H161+$J161)-AF173 -> -23700 | AG161: =IFERROR(AVERAGE(U161:AF161),0) -> -23700 | AH161: =IFERROR(AVERAGE(L161:S161,U161:AF161),0) -> -12350.8
A162: 2 | B162: Dammam 2nd Ind -Tad WH | C162: =IFERROR(VLOOKUP("Dammam 2nd Ind -Tad WH",'Warehouse Pallet data input'!$A$4:$J$13,3,FALSE()),0) -> 16153 | D162: =IFERROR(VLOOKUP("Dammam 2nd Ind -Tad WH",'Warehouse Pallet data input'!$A$4:$J$13,4,FALSE()),0) -> 18654 | E162: =IFERROR(VLOOKUP("Dammam 2nd Ind -Tad WH",'Warehouse Pallet data input'!$A$4:$J$13,5,FALSE()),0) -> 8607 | F162: =IFERROR(E162/D162,0) -> 0.46140238 | G162: =IFERROR(VLOOKUP("Dammam 2nd Ind -Tad WH",'Warehouse Pallet data input'!$A$4:$J$13,7,FALSE()),0) -> 10047 | H162: =IFERROR(VLOOKUP("Dammam 2nd Ind -Tad WH",'Warehouse Pallet data input'!$A$4:$J$13,8,FALSE()),0) -> 0 | I162: =IFERROR(VLOOKUP("Dammam 2nd Ind -Tad WH",'Warehouse Pallet data input'!$A$4:$J$13,9,FALSE()),0) -> 3619 | J162: =IFERROR(VLOOKUP("Dammam 2nd Ind -Tad WH",'Warehouse Pallet data input'!$A$4:$J$13,10,FALSE()),0) -> 0 | L162: =G162-L174 -> 6957 | M162: =G162-M174 -> 2957 | N162: =G162-N174 -> 2957 | O162: =G162-O174 -> 2957 | P162: =G162-P174 -> 2957 | Q162: =G162-Q174 -> 2957 | R162: =G162-R174 -> 2957 | S162: =G162-S174 -> 2957 | T162: =IFERROR(AVERAGE(L162:S162),0) -> 3457 | U162: =(-$H162+$J162)-U174 -> -1590 | V162: =(-$H162+$J162)-V174 -> -1590 | W162: =(-$H162+$J162)-W174 -> -1590 | X162: =(-$H162+$J162)-X174 -> -1590 | Y162: =(-$H162+$J162)-Y174 -> -1590 | Z162: =(-$H162+$J162)-Z174 -> -1590 | AA162: =(-$H162+$J162)-AA174 -> -1590 | AB162: =(-$H162+$J162)-AB174 -> -1590 | ... AF162: =(-$H162+$J162)-AF174 -> -1590 | AG162: =IFERROR(AVERAGE(U162:AF162),0) -> -1590 | AH162: =IFERROR(AVERAGE(L162:S162,U162:AF162),0) -> 428.8
A163: 3 | B163: Jubail 1 | C163: =IFERROR(VLOOKUP("Jubail 1",'Warehouse Pallet data input'!$A$4:$J$13,3,FALSE()),0) -> 31172 | D163: =IFERROR(VLOOKUP("Jubail 1",'Warehouse Pallet data input'!$A$4:$J$13,4,FALSE()),0) -> 35542 | E163: =IFERROR(VLOOKUP("Jubail 1",'Warehouse Pallet data input'!$A$4:$J$13,5,FALSE()),0) -> 11836 | F163: =IFERROR(E163/D163,0) -> 0.33301446 | G163: =IFERROR(VLOOKUP("Jubail 1",'Warehouse Pallet data input'!$A$4:$J$13,7,FALSE()),0) -> 23706 | H163: =IFERROR(VLOOKUP("Jubail 1",'Warehouse Pallet data input'!$A$4:$J$13,8,FALSE()),0) -> 13157 | I163: =IFERROR(VLOOKUP("Jubail 1",'Warehouse Pallet data input'!$A$4:$J$13,9,FALSE()),0) -> 146 | J163: =IFERROR(VLOOKUP("Jubail 1",'Warehouse Pallet data input'!$A$4:$J$13,10,FALSE()),0) -> 144 | L163: =G163-L175 -> 21506 | M163: =G163-M175 -> 19376 | N163: =G163-N175 -> 19376 | O163: =G163-O175 -> 19376 | P163: =G163-P175 -> 19376 | Q163: =G163-Q175 -> 19376 | R163: =G163-R175 -> 19376 | S163: =G163-S175 -> 19376 | T163: =IFERROR(AVERAGE(L163:S163),0) -> 19642.25 | U163: =(-$H163+$J163)-U175 -> -14213 | V163: =(-$H163+$J163)-V175 -> -14213 | W163: =(-$H163+$J163)-W175 -> -14213 | X163: =(-$H163+$J163)-X175 -> -14213 | Y163: =(-$H163+$J163)-Y175 -> -14213 | Z163: =(-$H163+$J163)-Z175 -> -14213 | AA163: =(-$H163+$J163)-AA175 -> -14213 | AB163: =(-$H163+$J163)-AB175 -> -14213 | ... AF163: =(-$H163+$J163)-AF175 -> -14213 | AG163: =IFERROR(AVERAGE(U163:AF163),0) -> -14213 | AH163: =IFERROR(AVERAGE(L163:S163,U163:AF163),0) -> -670.9
A164: 4 | B164: Jubail 2 | C164: =IFERROR(VLOOKUP("Jubail 2",'Warehouse Pallet data input'!$A$4:$J$13,3,FALSE()),0) -> 8152 | D164: =IFERROR(VLOOKUP("Jubail 2",'Warehouse Pallet data input'!$A$4:$J$13,4,FALSE()),0) -> 29258 | E164: =IFERROR(VLOOKUP("Jubail 2",'Warehouse Pallet data input'!$A$4:$J$13,5,FALSE()),0) -> 10011 | F164: =IFERROR(E164/D164,0) -> 0.34216283 | G164: =IFERROR(VLOOKUP("Jubail 2",'Warehouse Pallet data input'!$A$4:$J$13,7,FALSE()),0) -> 19247 | H164: =IFERROR(VLOOKUP("Jubail 2",'Warehouse Pallet data input'!$A$4:$J$13,8,FALSE()),0) -> 0 | I164: =IFERROR(VLOOKUP("Jubail 2",'Warehouse Pallet data input'!$A$4:$J$13,9,FALSE()),0) -> 0 | J164: =IFERROR(VLOOKUP("Jubail 2",'Warehouse Pallet data input'!$A$4:$J$13,10,FALSE()),0) -> 0 | L164: =G164-L176 -> 19247 | M164: =G164-M176 -> 19247 | N164: =G164-N176 -> 19247 | O164: =G164-O176 -> 19247 | P164: =G164-P176 -> 19247 | Q164: =G164-Q176 -> 19247 | R164: =G164-R176 -> 19247 | S164: =G164-S176 -> 19247 | T164: =IFERROR(AVERAGE(L164:S164),0) -> 19247 | U164: =(-$H164+$J164)-U176 -> 0 | V164: =(-$H164+$J164)-V176 -> 0 | W164: =(-$H164+$J164)-W176 -> 0 | X164: =(-$H164+$J164)-X176 -> 0 | Y164: =(-$H164+$J164)-Y176 -> 0 | Z164: =(-$H164+$J164)-Z176 -> 0 | AA164: =(-$H164+$J164)-AA176 -> 0 | AB164: =(-$H164+$J164)-AB176 -> 0 | ... AF164: =(-$H164+$J164)-AF176 -> 0 | AG164: =IFERROR(AVERAGE(U164:AF164),0) -> 0 | AH164: =IFERROR(AVERAGE(L164:S164,U164:AF164),0) -> 7698.8
A165: 5 | B165: Jubail Total | C165: =IF((C163+C164)<>0,(C163+C164),IFERROR(VLOOKUP("Jubail Total",'Warehouse Pallet data input'!$A$4:$J$13,3,FALSE()),0)) -> 39324 | D165: =IF((D163+D164)<>0,(D163+D164),IFERROR(VLOOKUP("Jubail Total",'Warehouse Pallet data input'!$A$4:$J$13,4,FALSE()),0)) -> 64800 | E165: =IF((E163+E164)<>0,(E163+E164),IFERROR(VLOOKUP("Jubail Total",'Warehouse Pallet data input'!$A$4:$J$13,5,FALSE()),0)) -> 21847 | F165: =IFERROR(E165/D165,0) -> 0.33714506 | G165: =IF((G163+G164)<>0,(G163+G164),IFERROR(VLOOKUP("Jubail Total",'Warehouse Pallet data input'!$A$4:$J$13,7,FALSE()),0)) -> 42953 | H165: =IF((H163+H164)<>0,(H163+H164),IFERROR(VLOOKUP("Jubail Total",'Warehouse Pallet data input'!$A$4:$J$13,8,FALSE()),0)) -> 13157 | I165: =IF((I163+I164)<>0,(I163+I164),IFERROR(VLOOKUP("Jubail Total",'Warehouse Pallet data input'!$A$4:$J$13,9,FALSE()),0)) -> 146 | J165: =IF((J163+J164)<>0,(J163+J164),IFERROR(VLOOKUP("Jubail Total",'Warehouse Pallet data input'!$A$4:$J$13,10,FALSE()),0)) -> 144 | L165: =G165-L177 -> 40753 | M165: =G165-M177 -> 38623 | N165: =G165-N177 -> 38623 | O165: =G165-O177 -> 38623 | P165: =G165-P177 -> 38623 | Q165: =G165-Q177 -> 38623 | R165: =G165-R177 -> 38623 | S165: =G165-S177 -> 38623 | T165: =IFERROR(AVERAGE(L165:S165),0) -> 38889.25 | U165: =(-$H165+$J165)-U177 -> -14213 | V165: =(-$H165+$J165)-V177 -> -14213 | W165: =(-$H165+$J165)-W177 -> -14213 | X165: =(-$H165+$J165)-X177 -> -14213 | Y165: =(-$H165+$J165)-Y177 -> -14213 | Z165: =(-$H165+$J165)-Z177 -> -14213 | AA165: =(-$H165+$J165)-AA177 -> -14213 | AB165: =(-$H165+$J165)-AB177 -> -14213 | ... AF165: =(-$H165+$J165)-AF177 -> -14213 | AG165: =IFERROR(AVERAGE(U165:AF165),0) -> -14213 | AH165: =IFERROR(AVERAGE(L165:S165,U165:AF165),0) -> 7027.9
A166: 6 | B166: Jeddah Modon 3A | C166: =IFERROR(VLOOKUP("Jeddah Modon 3A",'Warehouse Pallet data input'!$A$4:$J$13,3,FALSE()),0) -> 36212 | D166: =IFERROR(VLOOKUP("Jeddah Modon 3A",'Warehouse Pallet data input'!$A$4:$J$13,4,FALSE()),0) -> 36840 | E166: =IFERROR(VLOOKUP("Jeddah Modon 3A",'Warehouse Pallet data input'!$A$4:$J$13,5,FALSE()),0) -> 17127 | F166: =IFERROR(E166/D166,0) -> 0.46490228 | G166: =IFERROR(VLOOKUP("Jeddah Modon 3A",'Warehouse Pallet data input'!$A$4:$J$13,7,FALSE()),0) -> 19713 | H166: =IFERROR(VLOOKUP("Jeddah Modon 3A",'Warehouse Pallet data input'!$A$4:$J$13,8,FALSE()),0) -> 300 | I166: =IFERROR(VLOOKUP("Jeddah Modon 3A",'Warehouse Pallet data input'!$A$4:$J$13,9,FALSE()),0) -> 9038 | J166: =IFERROR(VLOOKUP("Jeddah Modon 3A",'Warehouse Pallet data input'!$A$4:$J$13,10,FALSE()),0) -> 134 | L166: =G166-L178 -> 16713 | M166: =G166-M178 -> 15213 | N166: =G166-N178 -> 15213 | O166: =G166-O178 -> 15213 | P166: =G166-P178 -> 15213 | Q166: =G166-Q178 -> 15213 | R166: =G166-R178 -> 15213 | S166: =G166-S178 -> 15213 | T166: =IFERROR(AVERAGE(L166:S166),0) -> 15400.5 | U166: =(-$H166+$J166)-U178 -> -166 | V166: =(-$H166+$J166)-V178 -> -166 | W166: =(-$H166+$J166)-W178 -> -166 | X166: =(-$H166+$J166)-X178 -> -166 | Y166: =(-$H166+$J166)-Y178 -> -166 | Z166: =(-$H166+$J166)-Z178 -> -166 | AA166: =(-$H166+$J166)-AA178 -> -166 | AB166: =(-$H166+$J166)-AB178 -> -166 | ... AF166: =(-$H166+$J166)-AF178 -> -166 | AG166: =IFERROR(AVERAGE(U166:AF166),0) -> -166 | AH166: =IFERROR(AVERAGE(L166:S166,U166:AF166),0) -> 6060.6
A167: 7 | B167: Jeddah Modon 3B | C167: =IFERROR(VLOOKUP("Jeddah Modon 3B",'Warehouse Pallet data input'!$A$4:$J$13,3,FALSE()),0) -> 12177 | D167: =IFERROR(VLOOKUP("Jeddah Modon 3B",'Warehouse Pallet data input'!$A$4:$J$13,4,FALSE()),0) -> 14189 | E167: =IFERROR(VLOOKUP("Jeddah Modon 3B",'Warehouse Pallet data input'!$A$4:$J$13,5,FALSE()),0) -> 13503 | F167: =IFERROR(E167/D167,0) -> 0.95165269 | G167: =IFERROR(VLOOKUP("Jeddah Modon 3B",'Warehouse Pallet data input'!$A$4:$J$13,7,FALSE()),0) -> 686 | H167: =IFERROR(VLOOKUP("Jeddah Modon 3B",'Warehouse Pallet data input'!$A$4:$J$13,8,FALSE()),0) -> 2600 | I167: =IFERROR(VLOOKUP("Jeddah Modon 3B",'Warehouse Pallet data input'!$A$4:$J$13,9,FALSE()),0) -> 3734 | J167: =IFERROR(VLOOKUP("Jeddah Modon 3B",'Warehouse Pallet data input'!$A$4:$J$13,10,FALSE()),0) -> 0 | L167: =G167-L179 -> -4814 | M167: =G167-M179 -> -4814 | N167: =G167-N179 -> -4814 | O167: =G167-O179 -> -4814 | P167: =G167-P179 -> -4814 | Q167: =G167-Q179 -> -4814 | R167: =G167-R179 -> -4814 | S167: =G167-S179 -> -4814 | T167: =IFERROR(AVERAGE(L167:S167),0) -> -4814 | U167: =(-$H167+$J167)-U179 -> -8100 | V167: =(-$H167+$J167)-V179 -> -8100 | W167: =(-$H167+$J167)-W179 -> -8100 | X167: =(-$H167+$J167)-X179 -> -8100 | Y167: =(-$H167+$J167)-Y179 -> -8100 | Z167: =(-$H167+$J167)-Z179 -> -8100 | AA167: =(-$H167+$J167)-AA179 -> -8100 | AB167: =(-$H167+$J167)-AB179 -> -8100 | ... AF167: =(-$H167+$J167)-AF179 -> -8100 | AG167: =IFERROR(AVERAGE(U167:AF167),0) -> -8100 | AH167: =IFERROR(AVERAGE(L167:S167,U167:AF167),0) -> -6785.6
A168: 8 | B168: RUH Tayba | C168: =IFERROR(VLOOKUP("RUH Tayba",'Warehouse Pallet data input'!$A$4:$J$13,3,FALSE()),0) -> 0 | D168: =IFERROR(VLOOKUP("RUH Tayba",'Warehouse Pallet data input'!$A$4:$J$13,4,FALSE()),0) -> 11132 | E168: =IFERROR(VLOOKUP("RUH Tayba",'Warehouse Pallet data input'!$A$4:$J$13,5,FALSE()),0) -> 8134 | F168: =IFERROR(E168/D168,0) -> 0.73068631 | G168: =IFERROR(VLOOKUP("RUH Tayba",'Warehouse Pallet data input'!$A$4:$J$13,7,FALSE()),0) -> 2998 | H168: =IFERROR(VLOOKUP("RUH Tayba",'Warehouse Pallet data input'!$A$4:$J$13,8,FALSE()),0) -> 317 | I168: =IFERROR(VLOOKUP("RUH Tayba",'Warehouse Pallet data input'!$A$4:$J$13,9,FALSE()),0) -> 0 | J168: =IFERROR(VLOOKUP("RUH Tayba",'Warehouse Pallet data input'!$A$4:$J$13,10,FALSE()),0) -> 0 | L168: =G168-L180 -> 2998 | M168: =G168-M180 -> 2998 | N168: =G168-N180 -> 2998 | O168: =G168-O180 -> 2998 | P168: =G168-P180 -> 2998 | Q168: =G168-Q180 -> 2998 | R168: =G168-R180 -> 2998 | S168: =G168-S180 -> 2998 | T168: =IFERROR(AVERAGE(L168:S168),0) -> 2998 | U168: =(-$H168+$J168)-U180 -> -317 | V168: =(-$H168+$J168)-V180 -> -317 | W168: =(-$H168+$J168)-W180 -> -317 | X168: =(-$H168+$J168)-X180 -> -317 | Y168: =(-$H168+$J168)-Y180 -> -317 | Z168: =(-$H168+$J168)-Z180 -> -317 | AA168: =(-$H168+$J168)-AA180 -> -317 | AB168: =(-$H168+$J168)-AB180 -> -317 | ... AF168: =(-$H168+$J168)-AF180 -> -317 | AG168: =IFERROR(AVERAGE(U168:AF168),0) -> -317 | AH168: =IFERROR(AVERAGE(L168:S168,U168:AF168),0) -> 1009
A169: 9 | B169: Subcontractor | C169: =IFERROR(VLOOKUP("Subcontractor",'Warehouse Pallet data input'!$A$4:$J$13,3,FALSE()),0) -> 0 | D169: =IFERROR(VLOOKUP("Subcontractor",'Warehouse Pallet data input'!$A$4:$J$13,4,FALSE()),0) -> 0 | E169: =IFERROR(VLOOKUP("Subcontractor",'Warehouse Pallet data input'!$A$4:$J$13,5,FALSE()),0) -> 0 | F169: =IFERROR(E169/D169,0) -> 0 | G169: =IFERROR(VLOOKUP("Subcontractor",'Warehouse Pallet data input'!$A$4:$J$13,7,FALSE()),0) -> 7500 | H169: =IFERROR(VLOOKUP("Subcontractor",'Warehouse Pallet data input'!$A$4:$J$13,8,FALSE()),0) -> 0 | I169: =IFERROR(VLOOKUP("Subcontractor",'Warehouse Pallet data input'!$A$4:$J$13,9,FALSE()),0) -> 0 | J169: =IFERROR(VLOOKUP("Subcontractor",'Warehouse Pallet data input'!$A$4:$J$13,10,FALSE()),0) -> 0 | L169: =G169-L181 -> 5000 | M169: =G169-M181 -> 5000 | N169: =G169-N181 -> 5000 | O169: =G169-O181 -> 5000 | P169: =G169-P181 -> 5000 | Q169: =G169-Q181 -> 5000 | R169: =G169-R181 -> 5000 | S169: =G169-S181 -> 5000 | T169: =IFERROR(AVERAGE(L169:S169),0) -> 5000 | U169: =(-$H169+$J169)-U181 -> -2500 | V169: =(-$H169+$J169)-V181 -> -2500 | W169: =(-$H169+$J169)-W181 -> -2500 | X169: =(-$H169+$J169)-X181 -> -2500 | Y169: =(-$H169+$J169)-Y181 -> -2500 | Z169: =(-$H169+$J169)-Z181 -> -2500 | AA169: =(-$H169+$J169)-AA181 -> -2500 | AB169: =(-$H169+$J169)-AB181 -> -2500 | ... AF169: =(-$H169+$J169)-AF181 -> -2500 | AG169: =IFERROR(AVERAGE(U169:AF169),0) -> -2500 | AH169: =IFERROR(AVERAGE(L169:S169,U169:AF169),0) -> 500
A170: 10 | B170: Contract Logistics | C170: =IFERROR(VLOOKUP("Contract Logistics",'Warehouse Pallet data input'!$A$4:$J$13,3,FALSE()),0) -> 0 | D170: =IFERROR(VLOOKUP("Contract Logistics",'Warehouse Pallet data input'!$A$4:$J$13,4,FALSE()),0) -> 0 | E170: =IFERROR(VLOOKUP("Contract Logistics",'Warehouse Pallet data input'!$A$4:$J$13,5,FALSE()),0) -> 0 | F170: =IFERROR(E170/D170,0) -> 0 | G170: =IFERROR(VLOOKUP("Contract Logistics",'Warehouse Pallet data input'!$A$4:$J$13,7,FALSE()),0) -> 0 | H170: =IFERROR(VLOOKUP("Contract Logistics",'Warehouse Pallet data input'!$A$4:$J$13,8,FALSE()),0) -> 0 | I170: =IFERROR(VLOOKUP("Contract Logistics",'Warehouse Pallet data input'!$A$4:$J$13,9,FALSE()),0) -> 0 | J170: =IFERROR(VLOOKUP("Contract Logistics",'Warehouse Pallet data input'!$A$4:$J$13,10,FALSE()),0) -> 0 | L170: =G170-L182 -> 0 | M170: =G170-M182 -> 0 | N170: =G170-N182 -> 0 | O170: =G170-O182 -> 0 | P170: =G170-P182 -> 0 | Q170: =G170-Q182 -> 0 | R170: =G170-R182 -> 0 | S170: =G170-S182 -> 0 | T170: =IFERROR(AVERAGE(L170:S170),0) -> 0 | U170: =(-$H170+$J170)-U182 -> 0 | V170: =(-$H170+$J170)-V182 -> 0 | W170: =(-$H170+$J170)-W182 -> 0 | X170: =(-$H170+$J170)-X182 -> 0 | Y170: =(-$H170+$J170)-Y182 -> 0 | Z170: =(-$H170+$J170)-Z182 -> 0 | AA170: =(-$H170+$J170)-AA182 -> 0 | AB170: =(-$H170+$J170)-AB182 -> 0 | ... AF170: =(-$H170+$J170)-AF182 -> 0 | AG170: =IFERROR(AVERAGE(U170:AF170),0) -> 0 | AH170: =IFERROR(AVERAGE(L170:S170,U170:AF170),0) -> 0
B171: Total Remaining Available Pallet Positions | C171: =SUM(C161:C170)-IF((C163+C164)<>0,C165,0) -> 132560 | D171: =SUM(D161:D170)-IF((D163+D164)<>0,D165,0) -> 180370 | E171: =SUM(E161:E170)-IF((E163+E164)<>0,E165,0) -> 99000 | F171: =IFERROR(E171/D171,0) -> 0.54887176 | G171: =SUM(G161:G170)-IF((G163+G164)<>0,G165,0) -> 88870 | H171: =SUM(H161:H170)-IF((H163+H164)<>0,H165,0) -> 39774 | I171: =SUM(I161:I170)-IF((I163+I164)<>0,I165,0) -> 16537 | J171: =SUM(J161:J170)-IF((J163+J164)<>0,J165,0) -> 278 | L171: =$G$171-L183 -> 72280 | M171: =$G$171-M183 -> 64650 | N171: =$G$171-N183 -> 64650 | O171: =$G$171-O183 -> 64650 | P171: =$G$171-P183 -> 64650 | Q171: =$G$171-Q183 -> 64650 | R171: =$G$171-R183 -> 64650 | S171: =$G$171-S183 -> 64650 | T171: =IFERROR(AVERAGE(L171:S171),0) -> 65603.75 | U171: =(-$H171+$J171)-U183 -> -50586 | V171: =(-$H171+$J171)-V183 -> -50586 | W171: =(-$H171+$J171)-W183 -> -50586 | X171: =(-$H171+$J171)-X183 -> -50586 | Y171: =(-$H171+$J171)-Y183 -> -50586 | Z171: =(-$H171+$J171)-Z183 -> -50586 | AA171: =(-$H171+$J171)-AA183 -> -50586 | AB171: =(-$H171+$J171)-AB183 -> -50586 | ... AF171: =(-$H171+$J171)-AF183 -> -50586 | AG171: =IFERROR(AVERAGE(U171:AF171),0) -> -50586 | AH171: =IFERROR(AVERAGE(L171:S171,U171:AF171),0) -> -4110.1
A172: 4B. Committed Pallet Positions (auto: cumulative based on go live date) — Closed Won + Contract Negotiation + Shortlisted
A173: 1 | B173: Dammam Port | C173: =C161 -> 28694 | D173: =D161 -> 34755 | E173: =E161 -> 29782 | F173: =F161 -> 0.85691267 | G173: =G161 -> 4973 | H173: =H161 -> 23400 | I173: =I161 -> 0 | J173: =J161 -> 0 | L173: =SUMIFS(J6:J65,F6:F65,$B$173,G6:G65,"<"&DATE(2026,6,1),D6:D65,"Closed Won")+SUMIFS(J6:J65,F6:F65,$B$173,G6:G65,"<"&DATE(2026,6,1),D6:D65,"Contract Negotiation")+SUMIFS(J6:J65,F6:F65,$B$173,G6:G65,"<"&DATE(2026,6,1),D6:D65,"Shortlisted") -> 300 | M173: =SUMIFS(J6:J65,F6:F65,$B$173,G6:G65,"<"&DATE(2026,7,1),D6:D65,"Closed Won")+SUMIFS(J6:J65,F6:F65,$B$173,G6:G65,"<"&DATE(2026,7,1),D6:D65,"Contract Negotiation")+SUMIFS(J6:J65,F6:F65,$B$173,G6:G65,"<"&DATE(2026,7,1),D6:D65,"Shortlisted") -> 300 | N173: =SUMIFS(J6:J65,F6:F65,$B$173,G6:G65,"<"&DATE(2026,8,1),D6:D65,"Closed Won")+SUMIFS(J6:J65,F6:F65,$B$173,G6:G65,"<"&DATE(2026,8,1),D6:D65,"Contract Negotiation")+SUMIFS(J6:J65,F6:F65,$B$173,G6:G65,"<"&DATE(2026,8,1),D6:D65,"Shortlisted") -> 300 | O173: =SUMIFS(J6:J65,F6:F65,$B$173,G6:G65,"<"&DATE(2026,9,1),D6:D65,"Closed Won")+SUMIFS(J6:J65,F6:F65,$B$173,G6:G65,"<"&DATE(2026,9,1),D6:D65,"Contract Negotiation")+SUMIFS(J6:J65,F6:F65,$B$173,G6:G65,"<"&DATE(2026,9,1),D6:D65,"Shortlisted") -> 300 | P173: =SUMIFS(J6:J65,F6:F65,$B$173,G6:G65,"<"&DATE(2026,10,1),D6:D65,"Closed Won")+SUMIFS(J6:J65,F6:F65,$B$173,G6:G65,"<"&DATE(2026,10,1),D6:D65,"Contract Negotiation")+SUMIFS(J6:J65,F6:F65,$B$173,G6:G65,"<"&DATE(2026,10,1),D6:D65,"Shortlisted") -> 300 | Q173: =SUMIFS(J6:J65,F6:F65,$B$173,G6:G65,"<"&DATE(2026,11,1),D6:D65,"Closed Won")+SUMIFS(J6:J65,F6:F65,$B$173,G6:G65,"<"&DATE(2026,11,1),D6:D65,"Contract Negotiation")+SUMIFS(J6:J65,F6:F65,$B$173,G6:G65,"<"&DATE(2026,11,1),D6:D65,"Shortlisted") -> 300 | R173: =SUMIFS(J6:J65,F6:F65,$B$173,G6:G65,"<"&DATE(2026,12,1),D6:D65,"Closed Won")+SUMIFS(J6:J65,F6:F65,$B$173,G6:G65,"<"&DATE(2026,12,1),D6:D65,"Contract Negotiation")+SUMIFS(J6:J65,F6:F65,$B$173,G6:G65,"<"&DATE(2026,12,1),D6:D65,"Shortlisted") -> 300 | S173: =SUMIFS(J6:J65,F6:F65,$B$173,G6:G65,"<"&DATE(2027,1,1),D6:D65,"Closed Won")+SUMIFS(J6:J65,F6:F65,$B$173,G6:G65,"<"&DATE(2027,1,1),D6:D65,"Contract Negotiation")+SUMIFS(J6:J65,F6:F65,$B$173,G6:G65,"<"&DATE(2027,1,1),D6:D65,"Shortlisted") -> 300 | T173: =IFERROR(AVERAGE(L173:S173),0) -> 300 | U173: =SUMIFS(J6:J65,F6:F65,$B$173,G6:G65,"<"&DATE(2027,2,1),D6:D65,"Closed Won") -> 300 | V173: =SUMIFS(J6:J65,F6:F65,$B$173,G6:G65,"<"&DATE(2027,3,1),D6:D65,"Closed Won") -> 300 | W173: =SUMIFS(J6:J65,F6:F65,$B$173,G6:G65,"<"&DATE(2027,4,1),D6:D65,"Closed Won") -> 300 | X173: =SUMIFS(J6:J65,F6:F65,$B$173,G6:G65,"<"&DATE(2027,5,1),D6:D65,"Closed Won") -> 300 | Y173: =SUMIFS(J6:J65,F6:F65,$B$173,G6:G65,"<"&DATE(2027,6,1),D6:D65,"Closed Won") -> 300 | Z173: =SUMIFS(J6:J65,F6:F65,$B$173,G6:G65,"<"&DATE(2027,7,1),D6:D65,"Closed Won") -> 300 | AA173: =SUMIFS(J6:J65,F6:F65,$B$173,G6:G65,"<"&DATE(2027,8,1),D6:D65,"Closed Won") -> 300 | AB173: =SUMIFS(J6:J65,F6:F65,$B$173,G6:G65,"<"&DATE(2027,9,1),D6:D65,"Closed Won") -> 300 | AC173: =SUMIFS(J6:J65,F6:F65,$B$173,G6:G65,"<"&DATE(2027,10,1),D6:D65,"Closed Won") -> 300 | AD173: =SUMIFS(J6:J65,F6:F65,$B$173,G6:G65,"<"&DATE(2027,11,1),D6:D65,"Closed Won") -> 300 | AE173: =SUMIFS(J6:J65,F6:F65,$B$173,G6:G65,"<"&DATE(2027,12,1),D6:D65,"Closed Won") -> 300 | AF173: =SUMIFS(J6:J65,F6:F65,$B$173,G6:G65,"<"&DATE(2028,1,1),D6:D65,"Closed Won") -> 300 | AG173: =IFERROR(AVERAGE(U173:AF173),0) -> 300 | AH173: =IFERROR(AVERAGE(L173:S173,U173:AF173),0) -> 300
A174: 2 | B174: Dammam 2nd Ind -Tad WH | C174: =C162 -> 16153 | D174: =D162 -> 18654 | E174: =E162 -> 8607 | F174: =F162 -> 0.46140238 | G174: =G162 -> 10047 | H174: =H162 -> 0 | I174: =I162 -> 3619 | J174: =J162 -> 0 | L174: =SUMIFS(J6:J65,F6:F65,$B$174,G6:G65,"<"&DATE(2026,6,1),D6:D65,"Closed Won")+SUMIFS(J6:J65,F6:F65,$B$174,G6:G65,"<"&DATE(2026,6,1),D6:D65,"Contract Negotiation")+SUMIFS(J6:J65,F6:F65,$B$174,G6:G65,"<"&DATE(2026,6,1),D6:D65,"Shortlisted") -> 3090 | M174: =SUMIFS(J6:J65,F6:F65,$B$174,G6:G65,"<"&DATE(2026,7,1),D6:D65,"Closed Won")+SUMIFS(J6:J65,F6:F65,$B$174,G6:G65,"<"&DATE(2026,7,1),D6:D65,"Contract Negotiation")+SUMIFS(J6:J65,F6:F65,$B$174,G6:G65,"<"&DATE(2026,7,1),D6:D65,"Shortlisted") -> 7090 | N174: =SUMIFS(J6:J65,F6:F65,$B$174,G6:G65,"<"&DATE(2026,8,1),D6:D65,"Closed Won")+SUMIFS(J6:J65,F6:F65,$B$174,G6:G65,"<"&DATE(2026,8,1),D6:D65,"Contract Negotiation")+SUMIFS(J6:J65,F6:F65,$B$174,G6:G65,"<"&DATE(2026,8,1),D6:D65,"Shortlisted") -> 7090 | O174: =SUMIFS(J6:J65,F6:F65,$B$174,G6:G65,"<"&DATE(2026,9,1),D6:D65,"Closed Won")+SUMIFS(J6:J65,F6:F65,$B$174,G6:G65,"<"&DATE(2026,9,1),D6:D65,"Contract Negotiation")+SUMIFS(J6:J65,F6:F65,$B$174,G6:G65,"<"&DATE(2026,9,1),D6:D65,"Shortlisted") -> 7090 | P174: =SUMIFS(J6:J65,F6:F65,$B$174,G6:G65,"<"&DATE(2026,10,1),D6:D65,"Closed Won")+SUMIFS(J6:J65,F6:F65,$B$174,G6:G65,"<"&DATE(2026,10,1),D6:D65,"Contract Negotiation")+SUMIFS(J6:J65,F6:F65,$B$174,G6:G65,"<"&DATE(2026,10,1),D6:D65,"Shortlisted") -> 7090 | Q174: =SUMIFS(J6:J65,F6:F65,$B$174,G6:G65,"<"&DATE(2026,11,1),D6:D65,"Closed Won")+SUMIFS(J6:J65,F6:F65,$B$174,G6:G65,"<"&DATE(2026,11,1),D6:D65,"Contract Negotiation")+SUMIFS(J6:J65,F6:F65,$B$174,G6:G65,"<"&DATE(2026,11,1),D6:D65,"Shortlisted") -> 7090 | R174: =SUMIFS(J6:J65,F6:F65,$B$174,G6:G65,"<"&DATE(2026,12,1),D6:D65,"Closed Won")+SUMIFS(J6:J65,F6:F65,$B$174,G6:G65,"<"&DATE(2026,12,1),D6:D65,"Contract Negotiation")+SUMIFS(J6:J65,F6:F65,$B$174,G6:G65,"<"&DATE(2026,12,1),D6:D65,"Shortlisted") -> 7090 | S174: =SUMIFS(J6:J65,F6:F65,$B$174,G6:G65,"<"&DATE(2027,1,1),D6:D65,"Closed Won")+SUMIFS(J6:J65,F6:F65,$B$174,G6:G65,"<"&DATE(2027,1,1),D6:D65,"Contract Negotiation")+SUMIFS(J6:J65,F6:F65,$B$174,G6:G65,"<"&DATE(2027,1,1),D6:D65,"Shortlisted") -> 7090 | T174: =IFERROR(AVERAGE(L174:S174),0) -> 6590 | U174: =SUMIFS(J6:J65,F6:F65,$B$174,G6:G65,"<"&DATE(2027,2,1),D6:D65,"Closed Won") -> 1590 | V174: =SUMIFS(J6:J65,F6:F65,$B$174,G6:G65,"<"&DATE(2027,3,1),D6:D65,"Closed Won") -> 1590 | W174: =SUMIFS(J6:J65,F6:F65,$B$174,G6:G65,"<"&DATE(2027,4,1),D6:D65,"Closed Won") -> 1590 | X174: =SUMIFS(J6:J65,F6:F65,$B$174,G6:G65,"<"&DATE(2027,5,1),D6:D65,"Closed Won") -> 1590 | Y174: =SUMIFS(J6:J65,F6:F65,$B$174,G6:G65,"<"&DATE(2027,6,1),D6:D65,"Closed Won") -> 1590 | Z174: =SUMIFS(J6:J65,F6:F65,$B$174,G6:G65,"<"&DATE(2027,7,1),D6:D65,"Closed Won") -> 1590 | AA174: =SUMIFS(J6:J65,F6:F65,$B$174,G6:G65,"<"&DATE(2027,8,1),D6:D65,"Closed Won") -> 1590 | AB174: =SUMIFS(J6:J65,F6:F65,$B$174,G6:G65,"<"&DATE(2027,9,1),D6:D65,"Closed Won") -> 1590 | AC174: =SUMIFS(J6:J65,F6:F65,$B$174,G6:G65,"<"&DATE(2027,10,1),D6:D65,"Closed Won") -> 1590 | AD174: =SUMIFS(J6:J65,F6:F65,$B$174,G6:G65,"<"&DATE(2027,11,1),D6:D65,"Closed Won") -> 1590 | AE174: =SUMIFS(J6:J65,F6:F65,$B$174,G6:G65,"<"&DATE(2027,12,1),D6:D65,"Closed Won") -> 1590 | AF174: =SUMIFS(J6:J65,F6:F65,$B$174,G6:G65,"<"&DATE(2028,1,1),D6:D65,"Closed Won") -> 1590 | AG174: =IFERROR(AVERAGE(U174:AF174),0) -> 1590 | AH174: =IFERROR(AVERAGE(L174:S174,U174:AF174),0) -> 3590
A175: 3 | B175: Jubail 1 | C175: =C163 -> 31172 | D175: =D163 -> 35542 | E175: =E163 -> 11836 | F175: =F163 -> 0.33301446 | G175: =G163 -> 23706 | H175: =H163 -> 13157 | I175: =I163 -> 146 | J175: =J163 -> 144 | L175: =SUMIFS(J6:J65,F6:F65,$B$175,G6:G65,"<"&DATE(2026,6,1),D6:D65,"Closed Won")+SUMIFS(J6:J65,F6:F65,$B$175,G6:G65,"<"&DATE(2026,6,1),D6:D65,"Contract Negotiation")+SUMIFS(J6:J65,F6:F65,$B$175,G6:G65,"<"&DATE(2026,6,1),D6:D65,"Shortlisted") -> 2200 | M175: =SUMIFS(J6:J65,F6:F65,$B$175,G6:G65,"<"&DATE(2026,7,1),D6:D65,"Closed Won")+SUMIFS(J6:J65,F6:F65,$B$175,G6:G65,"<"&DATE(2026,7,1),D6:D65,"Contract Negotiation")+SUMIFS(J6:J65,F6:F65,$B$175,G6:G65,"<"&DATE(2026,7,1),D6:D65,"Shortlisted") -> 4330 | N175: =SUMIFS(J6:J65,F6:F65,$B$175,G6:G65,"<"&DATE(2026,8,1),D6:D65,"Closed Won")+SUMIFS(J6:J65,F6:F65,$B$175,G6:G65,"<"&DATE(2026,8,1),D6:D65,"Contract Negotiation")+SUMIFS(J6:J65,F6:F65,$B$175,G6:G65,"<"&DATE(2026,8,1),D6:D65,"Shortlisted") -> 4330 | O175: =SUMIFS(J6:J65,F6:F65,$B$175,G6:G65,"<"&DATE(2026,9,1),D6:D65,"Closed Won")+SUMIFS(J6:J65,F6:F65,$B$175,G6:G65,"<"&DATE(2026,9,1),D6:D65,"Contract Negotiation")+SUMIFS(J6:J65,F6:F65,$B$175,G6:G65,"<"&DATE(2026,9,1),D6:D65,"Shortlisted") -> 4330 | P175: =SUMIFS(J6:J65,F6:F65,$B$175,G6:G65,"<"&DATE(2026,10,1),D6:D65,"Closed Won")+SUMIFS(J6:J65,F6:F65,$B$175,G6:G65,"<"&DATE(2026,10,1),D6:D65,"Contract Negotiation")+SUMIFS(J6:J65,F6:F65,$B$175,G6:G65,"<"&DATE(2026,10,1),D6:D65,"Shortlisted") -> 4330 | Q175: =SUMIFS(J6:J65,F6:F65,$B$175,G6:G65,"<"&DATE(2026,11,1),D6:D65,"Closed Won")+SUMIFS(J6:J65,F6:F65,$B$175,G6:G65,"<"&DATE(2026,11,1),D6:D65,"Contract Negotiation")+SUMIFS(J6:J65,F6:F65,$B$175,G6:G65,"<"&DATE(2026,11,1),D6:D65,"Shortlisted") -> 4330 | R175: =SUMIFS(J6:J65,F6:F65,$B$175,G6:G65,"<"&DATE(2026,12,1),D6:D65,"Closed Won")+SUMIFS(J6:J65,F6:F65,$B$175,G6:G65,"<"&DATE(2026,12,1),D6:D65,"Contract Negotiation")+SUMIFS(J6:J65,F6:F65,$B$175,G6:G65,"<"&DATE(2026,12,1),D6:D65,"Shortlisted") -> 4330 | S175: =SUMIFS(J6:J65,F6:F65,$B$175,G6:G65,"<"&DATE(2027,1,1),D6:D65,"Closed Won")+SUMIFS(J6:J65,F6:F65,$B$175,G6:G65,"<"&DATE(2027,1,1),D6:D65,"Contract Negotiation")+SUMIFS(J6:J65,F6:F65,$B$175,G6:G65,"<"&DATE(2027,1,1),D6:D65,"Shortlisted") -> 4330 | T175: =IFERROR(AVERAGE(L175:S175),0) -> 4063.75 | U175: =SUMIFS(J6:J65,F6:F65,$B$175,G6:G65,"<"&DATE(2027,2,1),D6:D65,"Closed Won") -> 1200 | V175: =SUMIFS(J6:J65,F6:F65,$B$175,G6:G65,"<"&DATE(2027,3,1),D6:D65,"Closed Won") -> 1200 | W175: =SUMIFS(J6:J65,F6:F65,$B$175,G6:G65,"<"&DATE(2027,4,1),D6:D65,"Closed Won") -> 1200 | X175: =SUMIFS(J6:J65,F6:F65,$B$175,G6:G65,"<"&DATE(2027,5,1),D6:D65,"Closed Won") -> 1200 | Y175: =SUMIFS(J6:J65,F6:F65,$B$175,G6:G65,"<"&DATE(2027,6,1),D6:D65,"Closed Won") -> 1200 | Z175: =SUMIFS(J6:J65,F6:F65,$B$175,G6:G65,"<"&DATE(2027,7,1),D6:D65,"Closed Won") -> 1200 | AA175: =SUMIFS(J6:J65,F6:F65,$B$175,G6:G65,"<"&DATE(2027,8,1),D6:D65,"Closed Won") -> 1200 | AB175: =SUMIFS(J6:J65,F6:F65,$B$175,G6:G65,"<"&DATE(2027,9,1),D6:D65,"Closed Won") -> 1200 | AC175: =SUMIFS(J6:J65,F6:F65,$B$175,G6:G65,"<"&DATE(2027,10,1),D6:D65,"Closed Won") -> 1200 | AD175: =SUMIFS(J6:J65,F6:F65,$B$175,G6:G65,"<"&DATE(2027,11,1),D6:D65,"Closed Won") -> 1200 | AE175: =SUMIFS(J6:J65,F6:F65,$B$175,G6:G65,"<"&DATE(2027,12,1),D6:D65,"Closed Won") -> 1200 | AF175: =SUMIFS(J6:J65,F6:F65,$B$175,G6:G65,"<"&DATE(2028,1,1),D6:D65,"Closed Won") -> 1200 | AG175: =IFERROR(AVERAGE(U175:AF175),0) -> 1200 | AH175: =IFERROR(AVERAGE(L175:S175,U175:AF175),0) -> 2345.5
A176: 4 | B176: Jubail 2 | C176: =C164 -> 8152 | D176: =D164 -> 29258 | E176: =E164 -> 10011 | F176: =F164 -> 0.34216283 | G176: =G164 -> 19247 | H176: =H164 -> 0 | I176: =I164 -> 0 | J176: =J164 -> 0 | L176: =SUMIFS(J6:J65,F6:F65,$B$176,G6:G65,"<"&DATE(2026,6,1),D6:D65,"Closed Won")+SUMIFS(J6:J65,F6:F65,$B$176,G6:G65,"<"&DATE(2026,6,1),D6:D65,"Contract Negotiation")+SUMIFS(J6:J65,F6:F65,$B$176,G6:G65,"<"&DATE(2026,6,1),D6:D65,"Shortlisted") -> 0 | M176: =SUMIFS(J6:J65,F6:F65,$B$176,G6:G65,"<"&DATE(2026,7,1),D6:D65,"Closed Won")+SUMIFS(J6:J65,F6:F65,$B$176,G6:G65,"<"&DATE(2026,7,1),D6:D65,"Contract Negotiation")+SUMIFS(J6:J65,F6:F65,$B$176,G6:G65,"<"&DATE(2026,7,1),D6:D65,"Shortlisted") -> 0 | N176: =SUMIFS(J6:J65,F6:F65,$B$176,G6:G65,"<"&DATE(2026,8,1),D6:D65,"Closed Won")+SUMIFS(J6:J65,F6:F65,$B$176,G6:G65,"<"&DATE(2026,8,1),D6:D65,"Contract Negotiation")+SUMIFS(J6:J65,F6:F65,$B$176,G6:G65,"<"&DATE(2026,8,1),D6:D65,"Shortlisted") -> 0 | O176: =SUMIFS(J6:J65,F6:F65,$B$176,G6:G65,"<"&DATE(2026,9,1),D6:D65,"Closed Won")+SUMIFS(J6:J65,F6:F65,$B$176,G6:G65,"<"&DATE(2026,9,1),D6:D65,"Contract Negotiation")+SUMIFS(J6:J65,F6:F65,$B$176,G6:G65,"<"&DATE(2026,9,1),D6:D65,"Shortlisted") -> 0 | P176: =SUMIFS(J6:J65,F6:F65,$B$176,G6:G65,"<"&DATE(2026,10,1),D6:D65,"Closed Won")+SUMIFS(J6:J65,F6:F65,$B$176,G6:G65,"<"&DATE(2026,10,1),D6:D65,"Contract Negotiation")+SUMIFS(J6:J65,F6:F65,$B$176,G6:G65,"<"&DATE(2026,10,1),D6:D65,"Shortlisted") -> 0 | Q176: =SUMIFS(J6:J65,F6:F65,$B$176,G6:G65,"<"&DATE(2026,11,1),D6:D65,"Closed Won")+SUMIFS(J6:J65,F6:F65,$B$176,G6:G65,"<"&DATE(2026,11,1),D6:D65,"Contract Negotiation")+SUMIFS(J6:J65,F6:F65,$B$176,G6:G65,"<"&DATE(2026,11,1),D6:D65,"Shortlisted") -> 0 | R176: =SUMIFS(J6:J65,F6:F65,$B$176,G6:G65,"<"&DATE(2026,12,1),D6:D65,"Closed Won")+SUMIFS(J6:J65,F6:F65,$B$176,G6:G65,"<"&DATE(2026,12,1),D6:D65,"Contract Negotiation")+SUMIFS(J6:J65,F6:F65,$B$176,G6:G65,"<"&DATE(2026,12,1),D6:D65,"Shortlisted") -> 0 | S176: =SUMIFS(J6:J65,F6:F65,$B$176,G6:G65,"<"&DATE(2027,1,1),D6:D65,"Closed Won")+SUMIFS(J6:J65,F6:F65,$B$176,G6:G65,"<"&DATE(2027,1,1),D6:D65,"Contract Negotiation")+SUMIFS(J6:J65,F6:F65,$B$176,G6:G65,"<"&DATE(2027,1,1),D6:D65,"Shortlisted") -> 0 | T176: =IFERROR(AVERAGE(L176:S176),0) -> 0 | U176: =SUMIFS(J6:J65,F6:F65,$B$176,G6:G65,"<"&DATE(2027,2,1),D6:D65,"Closed Won") -> 0 | V176: =SUMIFS(J6:J65,F6:F65,$B$176,G6:G65,"<"&DATE(2027,3,1),D6:D65,"Closed Won") -> 0 | W176: =SUMIFS(J6:J65,F6:F65,$B$176,G6:G65,"<"&DATE(2027,4,1),D6:D65,"Closed Won") -> 0 | X176: =SUMIFS(J6:J65,F6:F65,$B$176,G6:G65,"<"&DATE(2027,5,1),D6:D65,"Closed Won") -> 0 | Y176: =SUMIFS(J6:J65,F6:F65,$B$176,G6:G65,"<"&DATE(2027,6,1),D6:D65,"Closed Won") -> 0 | Z176: =SUMIFS(J6:J65,F6:F65,$B$176,G6:G65,"<"&DATE(2027,7,1),D6:D65,"Closed Won") -> 0 | AA176: =SUMIFS(J6:J65,F6:F65,$B$176,G6:G65,"<"&DATE(2027,8,1),D6:D65,"Closed Won") -> 0 | AB176: =SUMIFS(J6:J65,F6:F65,$B$176,G6:G65,"<"&DATE(2027,9,1),D6:D65,"Closed Won") -> 0 | AC176: =SUMIFS(J6:J65,F6:F65,$B$176,G6:G65,"<"&DATE(2027,10,1),D6:D65,"Closed Won") -> 0 | AD176: =SUMIFS(J6:J65,F6:F65,$B$176,G6:G65,"<"&DATE(2027,11,1),D6:D65,"Closed Won") -> 0 | AE176: =SUMIFS(J6:J65,F6:F65,$B$176,G6:G65,"<"&DATE(2027,12,1),D6:D65,"Closed Won") -> 0 | AF176: =SUMIFS(J6:J65,F6:F65,$B$176,G6:G65,"<"&DATE(2028,1,1),D6:D65,"Closed Won") -> 0 | AG176: =IFERROR(AVERAGE(U176:AF176),0) -> 0 | AH176: =IFERROR(AVERAGE(L176:S176,U176:AF176),0) -> 0
A177: 5 | B177: Jubail Total | C177: =C165 -> 39324 | D177: =D165 -> 64800 | E177: =E165 -> 21847 | F177: =F165 -> 0.33714506 | G177: =G165 -> 42953 | H177: =H165 -> 13157 | I177: =I165 -> 146 | J177: =J165 -> 144 | L177: =L175+L176 -> 2200 | M177: =M175+M176 -> 4330 | N177: =N175+N176 -> 4330 | O177: =O175+O176 -> 4330 | P177: =P175+P176 -> 4330 | Q177: =Q175+Q176 -> 4330 | R177: =R175+R176 -> 4330 | S177: =S175+S176 -> 4330 | T177: =IFERROR(AVERAGE(L177:S177),0) -> 4063.75 | U177: =U175+U176 -> 1200 | V177: =V175+V176 -> 1200 | W177: =W175+W176 -> 1200 | X177: =X175+X176 -> 1200 | Y177: =Y175+Y176 -> 1200 | Z177: =Z175+Z176 -> 1200 | AA177: =AA175+AA176 -> 1200 | AB177: =AB175+AB176 -> 1200 | ... AF177: =AF175+AF176 -> 1200 | AG177: =IFERROR(AVERAGE(U177:AF177),0) -> 1200 | AH177: =IFERROR(AVERAGE(L177:S177,U177:AF177),0) -> 2345.5
A178: 6 | B178: Jeddah Modon 3A | C178: =C166 -> 36212 | D178: =D166 -> 36840 | E178: =E166 -> 17127 | F178: =F166 -> 0.46490228 | G178: =G166 -> 19713 | H178: =H166 -> 300 | I178: =I166 -> 9038 | J178: =J166 -> 134 | L178: =SUMIFS(J6:J65,F6:F65,$B$178,G6:G65,"<"&DATE(2026,6,1),D6:D65,"Closed Won")+SUMIFS(J6:J65,F6:F65,$B$178,G6:G65,"<"&DATE(2026,6,1),D6:D65,"Contract Negotiation")+SUMIFS(J6:J65,F6:F65,$B$178,G6:G65,"<"&DATE(2026,6,1),D6:D65,"Shortlisted") -> 3000 | M178: =SUMIFS(J6:J65,F6:F65,$B$178,G6:G65,"<"&DATE(2026,7,1),D6:D65,"Closed Won")+SUMIFS(J6:J65,F6:F65,$B$178,G6:G65,"<"&DATE(2026,7,1),D6:D65,"Contract Negotiation")+SUMIFS(J6:J65,F6:F65,$B$178,G6:G65,"<"&DATE(2026,7,1),D6:D65,"Shortlisted") -> 4500 | N178: =SUMIFS(J6:J65,F6:F65,$B$178,G6:G65,"<"&DATE(2026,8,1),D6:D65,"Closed Won")+SUMIFS(J6:J65,F6:F65,$B$178,G6:G65,"<"&DATE(2026,8,1),D6:D65,"Contract Negotiation")+SUMIFS(J6:J65,F6:F65,$B$178,G6:G65,"<"&DATE(2026,8,1),D6:D65,"Shortlisted") -> 4500 | O178: =SUMIFS(J6:J65,F6:F65,$B$178,G6:G65,"<"&DATE(2026,9,1),D6:D65,"Closed Won")+SUMIFS(J6:J65,F6:F65,$B$178,G6:G65,"<"&DATE(2026,9,1),D6:D65,"Contract Negotiation")+SUMIFS(J6:J65,F6:F65,$B$178,G6:G65,"<"&DATE(2026,9,1),D6:D65,"Shortlisted") -> 4500 | P178: =SUMIFS(J6:J65,F6:F65,$B$178,G6:G65,"<"&DATE(2026,10,1),D6:D65,"Closed Won")+SUMIFS(J6:J65,F6:F65,$B$178,G6:G65,"<"&DATE(2026,10,1),D6:D65,"Contract Negotiation")+SUMIFS(J6:J65,F6:F65,$B$178,G6:G65,"<"&DATE(2026,10,1),D6:D65,"Shortlisted") -> 4500 | Q178: =SUMIFS(J6:J65,F6:F65,$B$178,G6:G65,"<"&DATE(2026,11,1),D6:D65,"Closed Won")+SUMIFS(J6:J65,F6:F65,$B$178,G6:G65,"<"&DATE(2026,11,1),D6:D65,"Contract Negotiation")+SUMIFS(J6:J65,F6:F65,$B$178,G6:G65,"<"&DATE(2026,11,1),D6:D65,"Shortlisted") -> 4500 | R178: =SUMIFS(J6:J65,F6:F65,$B$178,G6:G65,"<"&DATE(2026,12,1),D6:D65,"Closed Won")+SUMIFS(J6:J65,F6:F65,$B$178,G6:G65,"<"&DATE(2026,12,1),D6:D65,"Contract Negotiation")+SUMIFS(J6:J65,F6:F65,$B$178,G6:G65,"<"&DATE(2026,12,1),D6:D65,"Shortlisted") -> 4500 | S178: =SUMIFS(J6:J65,F6:F65,$B$178,G6:G65,"<"&DATE(2027,1,1),D6:D65,"Closed Won")+SUMIFS(J6:J65,F6:F65,$B$178,G6:G65,"<"&DATE(2027,1,1),D6:D65,"Contract Negotiation")+SUMIFS(J6:J65,F6:F65,$B$178,G6:G65,"<"&DATE(2027,1,1),D6:D65,"Shortlisted") -> 4500 | T178: =IFERROR(AVERAGE(L178:S178),0) -> 4312.5 | U178: =SUMIFS(J6:J65,F6:F65,$B$178,G6:G65,"<"&DATE(2027,2,1),D6:D65,"Closed Won") -> 0 | V178: =SUMIFS(J6:J65,F6:F65,$B$178,G6:G65,"<"&DATE(2027,3,1),D6:D65,"Closed Won") -> 0 | W178: =SUMIFS(J6:J65,F6:F65,$B$178,G6:G65,"<"&DATE(2027,4,1),D6:D65,"Closed Won") -> 0 | X178: =SUMIFS(J6:J65,F6:F65,$B$178,G6:G65,"<"&DATE(2027,5,1),D6:D65,"Closed Won") -> 0 | Y178: =SUMIFS(J6:J65,F6:F65,$B$178,G6:G65,"<"&DATE(2027,6,1),D6:D65,"Closed Won") -> 0 | Z178: =SUMIFS(J6:J65,F6:F65,$B$178,G6:G65,"<"&DATE(2027,7,1),D6:D65,"Closed Won") -> 0 | AA178: =SUMIFS(J6:J65,F6:F65,$B$178,G6:G65,"<"&DATE(2027,8,1),D6:D65,"Closed Won") -> 0 | AB178: =SUMIFS(J6:J65,F6:F65,$B$178,G6:G65,"<"&DATE(2027,9,1),D6:D65,"Closed Won") -> 0 | AC178: =SUMIFS(J6:J65,F6:F65,$B$178,G6:G65,"<"&DATE(2027,10,1),D6:D65,"Closed Won") -> 0 | AD178: =SUMIFS(J6:J65,F6:F65,$B$178,G6:G65,"<"&DATE(2027,11,1),D6:D65,"Closed Won") -> 0 | AE178: =SUMIFS(J6:J65,F6:F65,$B$178,G6:G65,"<"&DATE(2027,12,1),D6:D65,"Closed Won") -> 0 | AF178: =SUMIFS(J6:J65,F6:F65,$B$178,G6:G65,"<"&DATE(2028,1,1),D6:D65,"Closed Won") -> 0 | AG178: =IFERROR(AVERAGE(U178:AF178),0) -> 0 | AH178: =IFERROR(AVERAGE(L178:S178,U178:AF178),0) -> 1725
A179: 7 | B179: Jeddah Modon 3B | C179: =C167 -> 12177 | D179: =D167 -> 14189 | E179: =E167 -> 13503 | F179: =F167 -> 0.95165269 | G179: =G167 -> 686 | H179: =H167 -> 2600 | I179: =I167 -> 3734 | J179: =J167 -> 0 | L179: =SUMIFS(J6:J65,F6:F65,$B$179,G6:G65,"<"&DATE(2026,6,1),D6:D65,"Closed Won")+SUMIFS(J6:J65,F6:F65,$B$179,G6:G65,"<"&DATE(2026,6,1),D6:D65,"Contract Negotiation")+SUMIFS(J6:J65,F6:F65,$B$179,G6:G65,"<"&DATE(2026,6,1),D6:D65,"Shortlisted") -> 5500 | M179: =SUMIFS(J6:J65,F6:F65,$B$179,G6:G65,"<"&DATE(2026,7,1),D6:D65,"Closed Won")+SUMIFS(J6:J65,F6:F65,$B$179,G6:G65,"<"&DATE(2026,7,1),D6:D65,"Contract Negotiation")+SUMIFS(J6:J65,F6:F65,$B$179,G6:G65,"<"&DATE(2026,7,1),D6:D65,"Shortlisted") -> 5500 | N179: =SUMIFS(J6:J65,F6:F65,$B$179,G6:G65,"<"&DATE(2026,8,1),D6:D65,"Closed Won")+SUMIFS(J6:J65,F6:F65,$B$179,G6:G65,"<"&DATE(2026,8,1),D6:D65,"Contract Negotiation")+SUMIFS(J6:J65,F6:F65,$B$179,G6:G65,"<"&DATE(2026,8,1),D6:D65,"Shortlisted") -> 5500 | O179: =SUMIFS(J6:J65,F6:F65,$B$179,G6:G65,"<"&DATE(2026,9,1),D6:D65,"Closed Won")+SUMIFS(J6:J65,F6:F65,$B$179,G6:G65,"<"&DATE(2026,9,1),D6:D65,"Contract Negotiation")+SUMIFS(J6:J65,F6:F65,$B$179,G6:G65,"<"&DATE(2026,9,1),D6:D65,"Shortlisted") -> 5500 | P179: =SUMIFS(J6:J65,F6:F65,$B$179,G6:G65,"<"&DATE(2026,10,1),D6:D65,"Closed Won")+SUMIFS(J6:J65,F6:F65,$B$179,G6:G65,"<"&DATE(2026,10,1),D6:D65,"Contract Negotiation")+SUMIFS(J6:J65,F6:F65,$B$179,G6:G65,"<"&DATE(2026,10,1),D6:D65,"Shortlisted") -> 5500 | Q179: =SUMIFS(J6:J65,F6:F65,$B$179,G6:G65,"<"&DATE(2026,11,1),D6:D65,"Closed Won")+SUMIFS(J6:J65,F6:F65,$B$179,G6:G65,"<"&DATE(2026,11,1),D6:D65,"Contract Negotiation")+SUMIFS(J6:J65,F6:F65,$B$179,G6:G65,"<"&DATE(2026,11,1),D6:D65,"Shortlisted") -> 5500 | R179: =SUMIFS(J6:J65,F6:F65,$B$179,G6:G65,"<"&DATE(2026,12,1),D6:D65,"Closed Won")+SUMIFS(J6:J65,F6:F65,$B$179,G6:G65,"<"&DATE(2026,12,1),D6:D65,"Contract Negotiation")+SUMIFS(J6:J65,F6:F65,$B$179,G6:G65,"<"&DATE(2026,12,1),D6:D65,"Shortlisted") -> 5500 | S179: =SUMIFS(J6:J65,F6:F65,$B$179,G6:G65,"<"&DATE(2027,1,1),D6:D65,"Closed Won")+SUMIFS(J6:J65,F6:F65,$B$179,G6:G65,"<"&DATE(2027,1,1),D6:D65,"Contract Negotiation")+SUMIFS(J6:J65,F6:F65,$B$179,G6:G65,"<"&DATE(2027,1,1),D6:D65,"Shortlisted") -> 5500 | T179: =IFERROR(AVERAGE(L179:S179),0) -> 5500 | U179: =SUMIFS(J6:J65,F6:F65,$B$179,G6:G65,"<"&DATE(2027,2,1),D6:D65,"Closed Won") -> 5500 | V179: =SUMIFS(J6:J65,F6:F65,$B$179,G6:G65,"<"&DATE(2027,3,1),D6:D65,"Closed Won") -> 5500 | W179: =SUMIFS(J6:J65,F6:F65,$B$179,G6:G65,"<"&DATE(2027,4,1),D6:D65,"Closed Won") -> 5500 | X179: =SUMIFS(J6:J65,F6:F65,$B$179,G6:G65,"<"&DATE(2027,5,1),D6:D65,"Closed Won") -> 5500 | Y179: =SUMIFS(J6:J65,F6:F65,$B$179,G6:G65,"<"&DATE(2027,6,1),D6:D65,"Closed Won") -> 5500 | Z179: =SUMIFS(J6:J65,F6:F65,$B$179,G6:G65,"<"&DATE(2027,7,1),D6:D65,"Closed Won") -> 5500 | AA179: =SUMIFS(J6:J65,F6:F65,$B$179,G6:G65,"<"&DATE(2027,8,1),D6:D65,"Closed Won") -> 5500 | AB179: =SUMIFS(J6:J65,F6:F65,$B$179,G6:G65,"<"&DATE(2027,9,1),D6:D65,"Closed Won") -> 5500 | AC179: =SUMIFS(J6:J65,F6:F65,$B$179,G6:G65,"<"&DATE(2027,10,1),D6:D65,"Closed Won") -> 5500 | AD179: =SUMIFS(J6:J65,F6:F65,$B$179,G6:G65,"<"&DATE(2027,11,1),D6:D65,"Closed Won") -> 5500 | AE179: =SUMIFS(J6:J65,F6:F65,$B$179,G6:G65,"<"&DATE(2027,12,1),D6:D65,"Closed Won") -> 5500 | AF179: =SUMIFS(J6:J65,F6:F65,$B$179,G6:G65,"<"&DATE(2028,1,1),D6:D65,"Closed Won") -> 5500 | AG179: =IFERROR(AVERAGE(U179:AF179),0) -> 5500 | AH179: =IFERROR(AVERAGE(L179:S179,U179:AF179),0) -> 5500
A180: 8 | B180: RUH Tayba | C180: =C168 -> 0 | D180: =D168 -> 11132 | E180: =E168 -> 8134 | F180: =F168 -> 0.73068631 | G180: =G168 -> 2998 | H180: =H168 -> 317 | I180: =I168 -> 0 | J180: =J168 -> 0 | L180: =SUMIFS(J6:J65,F6:F65,$B$180,G6:G65,"<"&DATE(2026,6,1),D6:D65,"Closed Won")+SUMIFS(J6:J65,F6:F65,$B$180,G6:G65,"<"&DATE(2026,6,1),D6:D65,"Contract Negotiation")+SUMIFS(J6:J65,F6:F65,$B$180,G6:G65,"<"&DATE(2026,6,1),D6:D65,"Shortlisted") -> 0 | M180: =SUMIFS(J6:J65,F6:F65,$B$180,G6:G65,"<"&DATE(2026,7,1),D6:D65,"Closed Won")+SUMIFS(J6:J65,F6:F65,$B$180,G6:G65,"<"&DATE(2026,7,1),D6:D65,"Contract Negotiation")+SUMIFS(J6:J65,F6:F65,$B$180,G6:G65,"<"&DATE(2026,7,1),D6:D65,"Shortlisted") -> 0 | N180: =SUMIFS(J6:J65,F6:F65,$B$180,G6:G65,"<"&DATE(2026,8,1),D6:D65,"Closed Won")+SUMIFS(J6:J65,F6:F65,$B$180,G6:G65,"<"&DATE(2026,8,1),D6:D65,"Contract Negotiation")+SUMIFS(J6:J65,F6:F65,$B$180,G6:G65,"<"&DATE(2026,8,1),D6:D65,"Shortlisted") -> 0 | O180: =SUMIFS(J6:J65,F6:F65,$B$180,G6:G65,"<"&DATE(2026,9,1),D6:D65,"Closed Won")+SUMIFS(J6:J65,F6:F65,$B$180,G6:G65,"<"&DATE(2026,9,1),D6:D65,"Contract Negotiation")+SUMIFS(J6:J65,F6:F65,$B$180,G6:G65,"<"&DATE(2026,9,1),D6:D65,"Shortlisted") -> 0 | P180: =SUMIFS(J6:J65,F6:F65,$B$180,G6:G65,"<"&DATE(2026,10,1),D6:D65,"Closed Won")+SUMIFS(J6:J65,F6:F65,$B$180,G6:G65,"<"&DATE(2026,10,1),D6:D65,"Contract Negotiation")+SUMIFS(J6:J65,F6:F65,$B$180,G6:G65,"<"&DATE(2026,10,1),D6:D65,"Shortlisted") -> 0 | Q180: =SUMIFS(J6:J65,F6:F65,$B$180,G6:G65,"<"&DATE(2026,11,1),D6:D65,"Closed Won")+SUMIFS(J6:J65,F6:F65,$B$180,G6:G65,"<"&DATE(2026,11,1),D6:D65,"Contract Negotiation")+SUMIFS(J6:J65,F6:F65,$B$180,G6:G65,"<"&DATE(2026,11,1),D6:D65,"Shortlisted") -> 0 | R180: =SUMIFS(J6:J65,F6:F65,$B$180,G6:G65,"<"&DATE(2026,12,1),D6:D65,"Closed Won")+SUMIFS(J6:J65,F6:F65,$B$180,G6:G65,"<"&DATE(2026,12,1),D6:D65,"Contract Negotiation")+SUMIFS(J6:J65,F6:F65,$B$180,G6:G65,"<"&DATE(2026,12,1),D6:D65,"Shortlisted") -> 0 | S180: =SUMIFS(J6:J65,F6:F65,$B$180,G6:G65,"<"&DATE(2027,1,1),D6:D65,"Closed Won")+SUMIFS(J6:J65,F6:F65,$B$180,G6:G65,"<"&DATE(2027,1,1),D6:D65,"Contract Negotiation")+SUMIFS(J6:J65,F6:F65,$B$180,G6:G65,"<"&DATE(2027,1,1),D6:D65,"Shortlisted") -> 0 | T180: =IFERROR(AVERAGE(L180:S180),0) -> 0 | U180: =SUMIFS(J6:J65,F6:F65,$B$180,G6:G65,"<"&DATE(2027,2,1),D6:D65,"Closed Won") -> 0 | V180: =SUMIFS(J6:J65,F6:F65,$B$180,G6:G65,"<"&DATE(2027,3,1),D6:D65,"Closed Won") -> 0 | W180: =SUMIFS(J6:J65,F6:F65,$B$180,G6:G65,"<"&DATE(2027,4,1),D6:D65,"Closed Won") -> 0 | X180: =SUMIFS(J6:J65,F6:F65,$B$180,G6:G65,"<"&DATE(2027,5,1),D6:D65,"Closed Won") -> 0 | Y180: =SUMIFS(J6:J65,F6:F65,$B$180,G6:G65,"<"&DATE(2027,6,1),D6:D65,"Closed Won") -> 0 | Z180: =SUMIFS(J6:J65,F6:F65,$B$180,G6:G65,"<"&DATE(2027,7,1),D6:D65,"Closed Won") -> 0 | AA180: =SUMIFS(J6:J65,F6:F65,$B$180,G6:G65,"<"&DATE(2027,8,1),D6:D65,"Closed Won") -> 0 | AB180: =SUMIFS(J6:J65,F6:F65,$B$180,G6:G65,"<"&DATE(2027,9,1),D6:D65,"Closed Won") -> 0 | AC180: =SUMIFS(J6:J65,F6:F65,$B$180,G6:G65,"<"&DATE(2027,10,1),D6:D65,"Closed Won") -> 0 | AD180: =SUMIFS(J6:J65,F6:F65,$B$180,G6:G65,"<"&DATE(2027,11,1),D6:D65,"Closed Won") -> 0 | AE180: =SUMIFS(J6:J65,F6:F65,$B$180,G6:G65,"<"&DATE(2027,12,1),D6:D65,"Closed Won") -> 0 | AF180: =SUMIFS(J6:J65,F6:F65,$B$180,G6:G65,"<"&DATE(2028,1,1),D6:D65,"Closed Won") -> 0 | AG180: =IFERROR(AVERAGE(U180:AF180),0) -> 0 | AH180: =IFERROR(AVERAGE(L180:S180,U180:AF180),0) -> 0
A181: 9 | B181: Subcontractor | C181: =C169 -> 0 | D181: =D169 -> 0 | E181: =E169 -> 0 | F181: =F169 -> 0 | G181: =G169 -> 7500 | H181: =H169 -> 0 | I181: =I169 -> 0 | J181: =J169 -> 0 | L181: =SUMIFS(J6:J65,F6:F65,$B$181,G6:G65,"<"&DATE(2026,6,1),D6:D65,"Closed Won")+SUMIFS(J6:J65,F6:F65,$B$181,G6:G65,"<"&DATE(2026,6,1),D6:D65,"Contract Negotiation")+SUMIFS(J6:J65,F6:F65,$B$181,G6:G65,"<"&DATE(2026,6,1),D6:D65,"Shortlisted") -> 2500 | M181: =SUMIFS(J6:J65,F6:F65,$B$181,G6:G65,"<"&DATE(2026,7,1),D6:D65,"Closed Won")+SUMIFS(J6:J65,F6:F65,$B$181,G6:G65,"<"&DATE(2026,7,1),D6:D65,"Contract Negotiation")+SUMIFS(J6:J65,F6:F65,$B$181,G6:G65,"<"&DATE(2026,7,1),D6:D65,"Shortlisted") -> 2500 | N181: =SUMIFS(J6:J65,F6:F65,$B$181,G6:G65,"<"&DATE(2026,8,1),D6:D65,"Closed Won")+SUMIFS(J6:J65,F6:F65,$B$181,G6:G65,"<"&DATE(2026,8,1),D6:D65,"Contract Negotiation")+SUMIFS(J6:J65,F6:F65,$B$181,G6:G65,"<"&DATE(2026,8,1),D6:D65,"Shortlisted") -> 2500 | O181: =SUMIFS(J6:J65,F6:F65,$B$181,G6:G65,"<"&DATE(2026,9,1),D6:D65,"Closed Won")+SUMIFS(J6:J65,F6:F65,$B$181,G6:G65,"<"&DATE(2026,9,1),D6:D65,"Contract Negotiation")+SUMIFS(J6:J65,F6:F65,$B$181,G6:G65,"<"&DATE(2026,9,1),D6:D65,"Shortlisted") -> 2500 | P181: =SUMIFS(J6:J65,F6:F65,$B$181,G6:G65,"<"&DATE(2026,10,1),D6:D65,"Closed Won")+SUMIFS(J6:J65,F6:F65,$B$181,G6:G65,"<"&DATE(2026,10,1),D6:D65,"Contract Negotiation")+SUMIFS(J6:J65,F6:F65,$B$181,G6:G65,"<"&DATE(2026,10,1),D6:D65,"Shortlisted") -> 2500 | Q181: =SUMIFS(J6:J65,F6:F65,$B$181,G6:G65,"<"&DATE(2026,11,1),D6:D65,"Closed Won")+SUMIFS(J6:J65,F6:F65,$B$181,G6:G65,"<"&DATE(2026,11,1),D6:D65,"Contract Negotiation")+SUMIFS(J6:J65,F6:F65,$B$181,G6:G65,"<"&DATE(2026,11,1),D6:D65,"Shortlisted") -> 2500 | R181: =SUMIFS(J6:J65,F6:F65,$B$181,G6:G65,"<"&DATE(2026,12,1),D6:D65,"Closed Won")+SUMIFS(J6:J65,F6:F65,$B$181,G6:G65,"<"&DATE(2026,12,1),D6:D65,"Contract Negotiation")+SUMIFS(J6:J65,F6:F65,$B$181,G6:G65,"<"&DATE(2026,12,1),D6:D65,"Shortlisted") -> 2500 | S181: =SUMIFS(J6:J65,F6:F65,$B$181,G6:G65,"<"&DATE(2027,1,1),D6:D65,"Closed Won")+SUMIFS(J6:J65,F6:F65,$B$181,G6:G65,"<"&DATE(2027,1,1),D6:D65,"Contract Negotiation")+SUMIFS(J6:J65,F6:F65,$B$181,G6:G65,"<"&DATE(2027,1,1),D6:D65,"Shortlisted") -> 2500 | T181: =IFERROR(AVERAGE(L181:S181),0) -> 2500 | U181: =SUMIFS(J6:J65,F6:F65,$B$181,G6:G65,"<"&DATE(2027,2,1),D6:D65,"Closed Won") -> 2500 | V181: =SUMIFS(J6:J65,F6:F65,$B$181,G6:G65,"<"&DATE(2027,3,1),D6:D65,"Closed Won") -> 2500 | W181: =SUMIFS(J6:J65,F6:F65,$B$181,G6:G65,"<"&DATE(2027,4,1),D6:D65,"Closed Won") -> 2500 | X181: =SUMIFS(J6:J65,F6:F65,$B$181,G6:G65,"<"&DATE(2027,5,1),D6:D65,"Closed Won") -> 2500 | Y181: =SUMIFS(J6:J65,F6:F65,$B$181,G6:G65,"<"&DATE(2027,6,1),D6:D65,"Closed Won") -> 2500 | Z181: =SUMIFS(J6:J65,F6:F65,$B$181,G6:G65,"<"&DATE(2027,7,1),D6:D65,"Closed Won") -> 2500 | AA181: =SUMIFS(J6:J65,F6:F65,$B$181,G6:G65,"<"&DATE(2027,8,1),D6:D65,"Closed Won") -> 2500 | AB181: =SUMIFS(J6:J65,F6:F65,$B$181,G6:G65,"<"&DATE(2027,9,1),D6:D65,"Closed Won") -> 2500 | AC181: =SUMIFS(J6:J65,F6:F65,$B$181,G6:G65,"<"&DATE(2027,10,1),D6:D65,"Closed Won") -> 2500 | AD181: =SUMIFS(J6:J65,F6:F65,$B$181,G6:G65,"<"&DATE(2027,11,1),D6:D65,"Closed Won") -> 2500 | AE181: =SUMIFS(J6:J65,F6:F65,$B$181,G6:G65,"<"&DATE(2027,12,1),D6:D65,"Closed Won") -> 2500 | AF181: =SUMIFS(J6:J65,F6:F65,$B$181,G6:G65,"<"&DATE(2028,1,1),D6:D65,"Closed Won") -> 2500 | AG181: =IFERROR(AVERAGE(U181:AF181),0) -> 2500 | AH181: =IFERROR(AVERAGE(L181:S181,U181:AF181),0) -> 2500
A182: 10 | B182: Contract Logistics | C182: =C170 -> 0 | D182: =D170 -> 0 | E182: =E170 -> 0 | F182: =F170 -> 0 | G182: =G170 -> 0 | H182: =H170 -> 0 | I182: =I170 -> 0 | J182: =J170 -> 0 | L182: =SUMIFS(J6:J65,F6:F65,$B$182,G6:G65,"<"&DATE(2026,6,1),D6:D65,"Closed Won")+SUMIFS(J6:J65,F6:F65,$B$182,G6:G65,"<"&DATE(2026,6,1),D6:D65,"Contract Negotiation")+SUMIFS(J6:J65,F6:F65,$B$182,G6:G65,"<"&DATE(2026,6,1),D6:D65,"Shortlisted") -> 0 | M182: =SUMIFS(J6:J65,F6:F65,$B$182,G6:G65,"<"&DATE(2026,7,1),D6:D65,"Closed Won")+SUMIFS(J6:J65,F6:F65,$B$182,G6:G65,"<"&DATE(2026,7,1),D6:D65,"Contract Negotiation")+SUMIFS(J6:J65,F6:F65,$B$182,G6:G65,"<"&DATE(2026,7,1),D6:D65,"Shortlisted") -> 0 | N182: =SUMIFS(J6:J65,F6:F65,$B$182,G6:G65,"<"&DATE(2026,8,1),D6:D65,"Closed Won")+SUMIFS(J6:J65,F6:F65,$B$182,G6:G65,"<"&DATE(2026,8,1),D6:D65,"Contract Negotiation")+SUMIFS(J6:J65,F6:F65,$B$182,G6:G65,"<"&DATE(2026,8,1),D6:D65,"Shortlisted") -> 0 | O182: =SUMIFS(J6:J65,F6:F65,$B$182,G6:G65,"<"&DATE(2026,9,1),D6:D65,"Closed Won")+SUMIFS(J6:J65,F6:F65,$B$182,G6:G65,"<"&DATE(2026,9,1),D6:D65,"Contract Negotiation")+SUMIFS(J6:J65,F6:F65,$B$182,G6:G65,"<"&DATE(2026,9,1),D6:D65,"Shortlisted") -> 0 | P182: =SUMIFS(J6:J65,F6:F65,$B$182,G6:G65,"<"&DATE(2026,10,1),D6:D65,"Closed Won")+SUMIFS(J6:J65,F6:F65,$B$182,G6:G65,"<"&DATE(2026,10,1),D6:D65,"Contract Negotiation")+SUMIFS(J6:J65,F6:F65,$B$182,G6:G65,"<"&DATE(2026,10,1),D6:D65,"Shortlisted") -> 0 | Q182: =SUMIFS(J6:J65,F6:F65,$B$182,G6:G65,"<"&DATE(2026,11,1),D6:D65,"Closed Won")+SUMIFS(J6:J65,F6:F65,$B$182,G6:G65,"<"&DATE(2026,11,1),D6:D65,"Contract Negotiation")+SUMIFS(J6:J65,F6:F65,$B$182,G6:G65,"<"&DATE(2026,11,1),D6:D65,"Shortlisted") -> 0 | R182: =SUMIFS(J6:J65,F6:F65,$B$182,G6:G65,"<"&DATE(2026,12,1),D6:D65,"Closed Won")+SUMIFS(J6:J65,F6:F65,$B$182,G6:G65,"<"&DATE(2026,12,1),D6:D65,"Contract Negotiation")+SUMIFS(J6:J65,F6:F65,$B$182,G6:G65,"<"&DATE(2026,12,1),D6:D65,"Shortlisted") -> 0 | S182: =SUMIFS(J6:J65,F6:F65,$B$182,G6:G65,"<"&DATE(2027,1,1),D6:D65,"Closed Won")+SUMIFS(J6:J65,F6:F65,$B$182,G6:G65,"<"&DATE(2027,1,1),D6:D65,"Contract Negotiation")+SUMIFS(J6:J65,F6:F65,$B$182,G6:G65,"<"&DATE(2027,1,1),D6:D65,"Shortlisted") -> 0 | T182: =IFERROR(AVERAGE(L182:S182),0) -> 0 | U182: =SUMIFS(J6:J65,F6:F65,$B$182,G6:G65,"<"&DATE(2027,2,1),D6:D65,"Closed Won") -> 0 | V182: =SUMIFS(J6:J65,F6:F65,$B$182,G6:G65,"<"&DATE(2027,3,1),D6:D65,"Closed Won") -> 0 | W182: =SUMIFS(J6:J65,F6:F65,$B$182,G6:G65,"<"&DATE(2027,4,1),D6:D65,"Closed Won") -> 0 | X182: =SUMIFS(J6:J65,F6:F65,$B$182,G6:G65,"<"&DATE(2027,5,1),D6:D65,"Closed Won") -> 0 | Y182: =SUMIFS(J6:J65,F6:F65,$B$182,G6:G65,"<"&DATE(2027,6,1),D6:D65,"Closed Won") -> 0 | Z182: =SUMIFS(J6:J65,F6:F65,$B$182,G6:G65,"<"&DATE(2027,7,1),D6:D65,"Closed Won") -> 0 | AA182: =SUMIFS(J6:J65,F6:F65,$B$182,G6:G65,"<"&DATE(2027,8,1),D6:D65,"Closed Won") -> 0 | AB182: =SUMIFS(J6:J65,F6:F65,$B$182,G6:G65,"<"&DATE(2027,9,1),D6:D65,"Closed Won") -> 0 | AC182: =SUMIFS(J6:J65,F6:F65,$B$182,G6:G65,"<"&DATE(2027,10,1),D6:D65,"Closed Won") -> 0 | AD182: =SUMIFS(J6:J65,F6:F65,$B$182,G6:G65,"<"&DATE(2027,11,1),D6:D65,"Closed Won") -> 0 | AE182: =SUMIFS(J6:J65,F6:F65,$B$182,G6:G65,"<"&DATE(2027,12,1),D6:D65,"Closed Won") -> 0 | AF182: =SUMIFS(J6:J65,F6:F65,$B$182,G6:G65,"<"&DATE(2028,1,1),D6:D65,"Closed Won") -> 0 | AG182: =IFERROR(AVERAGE(U182:AF182),0) -> 0 | AH182: =IFERROR(AVERAGE(L182:S182,U182:AF182),0) -> 0
B183: Total Committed Pallet Positions | C183: =SUM(C173:C182)-IF((C175+C176)<>0,C177,0) -> 132560 | D183: =SUM(D173:D182)-IF((D175+D176)<>0,D177,0) -> 180370 | E183: =SUM(E173:E182)-IF((E175+E176)<>0,E177,0) -> 99000 | F183: =IFERROR(E183/D183,0) -> 0.54887176 | G183: =SUM(G173:G182)-IF((G175+G176)<>0,G177,0) -> 88870 | H183: =SUM(H173:H182)-IF((H175+H176)<>0,H177,0) -> 39774 | I183: =SUM(I173:I182)-IF((I175+I176)<>0,I177,0) -> 16537 | J183: =SUM(J173:J182)-IF((J175+J176)<>0,J177,0) -> 278 | L183: =SUM(L173,L174,L175,L176,L178,L179,L180,L181,L182) -> 16590 | M183: =SUM(M173,M174,M175,M176,M178,M179,M180,M181,M182) -> 24220 | N183: =SUM(N173,N174,N175,N176,N178,N179,N180,N181,N182) -> 24220 | O183: =SUM(O173,O174,O175,O176,O178,O179,O180,O181,O182) -> 24220 | P183: =SUM(P173,P174,P175,P176,P178,P179,P180,P181,P182) -> 24220 | Q183: =SUM(Q173,Q174,Q175,Q176,Q178,Q179,Q180,Q181,Q182) -> 24220 | R183: =SUM(R173,R174,R175,R176,R178,R179,R180,R181,R182) -> 24220 | S183: =SUM(S173,S174,S175,S176,S178,S179,S180,S181,S182) -> 24220 | T183: =IFERROR(AVERAGE(L183:S183),0) -> 23266.25 | U183: =SUM(U173,U174,U175,U176,U178,U179,U180,U181,U182) -> 11090 | V183: =SUM(V173,V174,V175,V176,V178,V179,V180,V181,V182) -> 11090 | W183: =SUM(W173,W174,W175,W176,W178,W179,W180,W181,W182) -> 11090 | X183: =SUM(X173,X174,X175,X176,X178,X179,X180,X181,X182) -> 11090 | Y183: =SUM(Y173,Y174,Y175,Y176,Y178,Y179,Y180,Y181,Y182) -> 11090 | Z183: =SUM(Z173,Z174,Z175,Z176,Z178,Z179,Z180,Z181,Z182) -> 11090 | AA183: =SUM(AA173,AA174,AA175,AA176,AA178,AA179,AA180,AA181,AA182) -> 11090 | AB183: =SUM(AB173,AB174,AB175,AB176,AB178,AB179,AB180,AB181,AB182) -> 11090 | ... AF183: =SUM(AF173,AF174,AF175,AF176,AF178,AF179,AF180,AF181,AF182) -> 11090 | AG183: =IFERROR(AVERAGE(U183:AF183),0) -> 11090 | AH183: =IFERROR(AVERAGE(L183:S183,U183:AF183),0) -> 15960.5
B184: Free Space Baseline (Sellable Capacity) | L184: =$G$171 -> 88870 | M184: =$G$171 -> 88870 | N184: =$G$171 -> 88870 | O184: =$G$171 -> 88870 | P184: =$G$171 -> 88870 | Q184: =$G$171 -> 88870 | R184: =$G$171 -> 88870 | S184: =$G$171 -> 88870 | T184: =IFERROR(AVERAGE(L184:S184),0) -> 88870 | U184: =-$H$171+$J$171 -> -39496 | V184: =-$H$171+$J$171 -> -39496 | W184: =-$H$171+$J$171 -> -39496 | X184: =-$H$171+$J$171 -> -39496 | Y184: =-$H$171+$J$171 -> -39496 | Z184: =-$H$171+$J$171 -> -39496 | AA184: =-$H$171+$J$171 -> -39496 | AB184: =-$H$171+$J$171 -> -39496 | ... AF184: =-$H$171+$J$171 -> -39496 | AG184: =IFERROR(AVERAGE(U184:AF184),0) -> -39496 | AH184: =IFERROR(AVERAGE(L184:S184,U184:AF184),0) -> 11850.4
B185: Utilization % (Committed / Baseline) | L185: =IFERROR(L183/L184,0) -> 0.18667717 | M185: =IFERROR(M183/M184,0) -> 0.27253291 | N185: =IFERROR(N183/N184,0) -> 0.27253291 | O185: =IFERROR(O183/O184,0) -> 0.27253291 | P185: =IFERROR(P183/P184,0) -> 0.27253291 | Q185: =IFERROR(Q183/Q184,0) -> 0.27253291 | R185: =IFERROR(R183/R184,0) -> 0.27253291 | S185: =IFERROR(S183/S184,0) -> 0.27253291 | ... AH185: =IFERROR(AH183/AH184,0) -> 1.3468322
A187: 5. PROBABLE POTENTIAL INCOME (PPI) — Probability-weighted income from Shortlisted, Contract Negotiation & Closed Won deals (30-day payment delay applied)
A188: # | B188: Stage | L188: May-26 | M188: Jun-26 | N188: Jul-26 | O188: Aug-26 | P188: Sep-26 | Q188: Oct-26 | R188: Nov-26 | S188: Dec-26 | T188: 2026 Total | U188: Jan-27 | V188: Feb-27 | W188: Mar-27 | X188: Apr-27 | Y188: May-27 | Z188: Jun-27 | AA188: Jul-27 | AB188: Aug-27 | AC188: Sep-27 | AD188: Oct-27 | AE188: Nov-27 | AF188: Dec-27 | AG188: 2027 Total | AH188: Grand Total | AJ188: Notes
A189: 1 | B189: PPI — Shortlisted | L189: =0 -> 0 | M189: =SUMIFS(L$6:L$65,$D$6:$D$65,"Shortlisted")*VLOOKUP("Shortlisted",$B$211:$C$217,2,FALSE()) -> 45375 | N189: =SUMIFS(M$6:M$65,$D$6:$D$65,"Shortlisted")*VLOOKUP("Shortlisted",$B$211:$C$217,2,FALSE()) -> 167475 | O189: =SUMIFS(N$6:N$65,$D$6:$D$65,"Shortlisted")*VLOOKUP("Shortlisted",$B$211:$C$217,2,FALSE()) -> 220600 | P189: =SUMIFS(O$6:O$65,$D$6:$D$65,"Shortlisted")*VLOOKUP("Shortlisted",$B$211:$C$217,2,FALSE()) -> 220600 | Q189: =SUMIFS(P$6:P$65,$D$6:$D$65,"Shortlisted")*VLOOKUP("Shortlisted",$B$211:$C$217,2,FALSE()) -> 220600 | R189: =SUMIFS(Q$6:Q$65,$D$6:$D$65,"Shortlisted")*VLOOKUP("Shortlisted",$B$211:$C$217,2,FALSE()) -> 220600 | S189: =SUMIFS(R$6:R$65,$D$6:$D$65,"Shortlisted")*VLOOKUP("Shortlisted",$B$211:$C$217,2,FALSE()) -> 220600 | T189: =SUM(L189:S189) -> 1315850 | U189: =SUMIFS(S$6:S$65,$D$6:$D$65,"Shortlisted")*VLOOKUP("Shortlisted",$B$211:$C$217,2,FALSE()) -> 220600 | V189: =SUMIFS(U$6:U$65,$D$6:$D$65,"Shortlisted")*VLOOKUP("Shortlisted",$B$211:$C$217,2,FALSE()) -> 220600 | W189: =SUMIFS(V$6:V$65,$D$6:$D$65,"Shortlisted")*VLOOKUP("Shortlisted",$B$211:$C$217,2,FALSE()) -> 220600 | X189: =SUMIFS(W$6:W$65,$D$6:$D$65,"Shortlisted")*VLOOKUP("Shortlisted",$B$211:$C$217,2,FALSE()) -> 220600 | Y189: =SUMIFS(X$6:X$65,$D$6:$D$65,"Shortlisted")*VLOOKUP("Shortlisted",$B$211:$C$217,2,FALSE()) -> 220600 | Z189: =SUMIFS(Y$6:Y$65,$D$6:$D$65,"Shortlisted")*VLOOKUP("Shortlisted",$B$211:$C$217,2,FALSE()) -> 220600 | AA189: =SUMIFS(Z$6:Z$65,$D$6:$D$65,"Shortlisted")*VLOOKUP("Shortlisted",$B$211:$C$217,2,FALSE()) -> 220600 | AB189: =SUMIFS(AA$6:AA$65,$D$6:$D$65,"Shortlisted")*VLOOKUP("Shortlisted",$B$211:$C$217,2,FALSE()) -> 220600 | AC189: =SUMIFS(AB$6:AB$65,$D$6:$D$65,"Shortlisted")*VLOOKUP("Shortlisted",$B$211:$C$217,2,FALSE()) -> 220600 | ... AF189: =SUMIFS(AE$6:AE$65,$D$6:$D$65,"Shortlisted")*VLOOKUP("Shortlisted",$B$211:$C$217,2,FALSE()) -> 220600 | AG189: =SUM(U189:AF189) -> 2647200 | AH189: =T189+AG189 -> 3963050
A190: 2 | B190: PPI — Contract Negotiation | L190: =0 -> 0 | M190: =SUMIFS(L$6:L$65,$D$6:$D$65,"Contract Negotiation")*VLOOKUP("Contract Negotiation",$B$211:$C$217,2,FALSE()) -> 148500 | N190: =SUMIFS(M$6:M$65,$D$6:$D$65,"Contract Negotiation")*VLOOKUP("Contract Negotiation",$B$211:$C$217,2,FALSE()) -> 328500 | O190: =SUMIFS(N$6:N$65,$D$6:$D$65,"Contract Negotiation")*VLOOKUP("Contract Negotiation",$B$211:$C$217,2,FALSE()) -> 328500 | P190: =SUMIFS(O$6:O$65,$D$6:$D$65,"Contract Negotiation")*VLOOKUP("Contract Negotiation",$B$211:$C$217,2,FALSE()) -> 328500 | Q190: =SUMIFS(P$6:P$65,$D$6:$D$65,"Contract Negotiation")*VLOOKUP("Contract Negotiation",$B$211:$C$217,2,FALSE()) -> 328500 | R190: =SUMIFS(Q$6:Q$65,$D$6:$D$65,"Contract Negotiation")*VLOOKUP("Contract Negotiation",$B$211:$C$217,2,FALSE()) -> 328500 | S190: =SUMIFS(R$6:R$65,$D$6:$D$65,"Contract Negotiation")*VLOOKUP("Contract Negotiation",$B$211:$C$217,2,FALSE()) -> 328500 | T190: =SUM(L190:S190) -> 2119500 | U190: =SUMIFS(S$6:S$65,$D$6:$D$65,"Contract Negotiation")*VLOOKUP("Contract Negotiation",$B$211:$C$217,2,FALSE()) -> 328500 | V190: =SUMIFS(U$6:U$65,$D$6:$D$65,"Contract Negotiation")*VLOOKUP("Contract Negotiation",$B$211:$C$217,2,FALSE()) -> 328500 | W190: =SUMIFS(V$6:V$65,$D$6:$D$65,"Contract Negotiation")*VLOOKUP("Contract Negotiation",$B$211:$C$217,2,FALSE()) -> 328500 | X190: =SUMIFS(W$6:W$65,$D$6:$D$65,"Contract Negotiation")*VLOOKUP("Contract Negotiation",$B$211:$C$217,2,FALSE()) -> 328500 | Y190: =SUMIFS(X$6:X$65,$D$6:$D$65,"Contract Negotiation")*VLOOKUP("Contract Negotiation",$B$211:$C$217,2,FALSE()) -> 328500 | Z190: =SUMIFS(Y$6:Y$65,$D$6:$D$65,"Contract Negotiation")*VLOOKUP("Contract Negotiation",$B$211:$C$217,2,FALSE()) -> 328500 | AA190: =SUMIFS(Z$6:Z$65,$D$6:$D$65,"Contract Negotiation")*VLOOKUP("Contract Negotiation",$B$211:$C$217,2,FALSE()) -> 328500 | AB190: =SUMIFS(AA$6:AA$65,$D$6:$D$65,"Contract Negotiation")*VLOOKUP("Contract Negotiation",$B$211:$C$217,2,FALSE()) -> 328500 | AC190: =SUMIFS(AB$6:AB$65,$D$6:$D$65,"Contract Negotiation")*VLOOKUP("Contract Negotiation",$B$211:$C$217,2,FALSE()) -> 328500 | ... AF190: =SUMIFS(AE$6:AE$65,$D$6:$D$65,"Contract Negotiation")*VLOOKUP("Contract Negotiation",$B$211:$C$217,2,FALSE()) -> 328500 | AG190: =SUM(U190:AF190) -> 3942000 | AH190: =T190+AG190 -> 6061500
A191: 3 | B191: PPI — Closed Won | L191: =0 -> 0 | M191: =SUMIFS(L$6:L$65,$D$6:$D$65,"Closed Won")*VLOOKUP("Closed Won",$B$211:$C$217,2,FALSE()) -> 482216.67 | N191: =SUMIFS(M$6:M$65,$D$6:$D$65,"Closed Won")*VLOOKUP("Closed Won",$B$211:$C$217,2,FALSE()) -> 482216.67 | O191: =SUMIFS(N$6:N$65,$D$6:$D$65,"Closed Won")*VLOOKUP("Closed Won",$B$211:$C$217,2,FALSE()) -> 482216.67 | P191: =SUMIFS(O$6:O$65,$D$6:$D$65,"Closed Won")*VLOOKUP("Closed Won",$B$211:$C$217,2,FALSE()) -> 482216.67 | Q191: =SUMIFS(P$6:P$65,$D$6:$D$65,"Closed Won")*VLOOKUP("Closed Won",$B$211:$C$217,2,FALSE()) -> 482216.67 | R191: =SUMIFS(Q$6:Q$65,$D$6:$D$65,"Closed Won")*VLOOKUP("Closed Won",$B$211:$C$217,2,FALSE()) -> 482216.67 | S191: =SUMIFS(R$6:R$65,$D$6:$D$65,"Closed Won")*VLOOKUP("Closed Won",$B$211:$C$217,2,FALSE()) -> 482216.67 | T191: =SUM(L191:S191) -> 3375516.7 | U191: =SUMIFS(S$6:S$65,$D$6:$D$65,"Closed Won")*VLOOKUP("Closed Won",$B$211:$C$217,2,FALSE()) -> 482216.67 | V191: =SUMIFS(U$6:U$65,$D$6:$D$65,"Closed Won")*VLOOKUP("Closed Won",$B$211:$C$217,2,FALSE()) -> 482216.67 | W191: =SUMIFS(V$6:V$65,$D$6:$D$65,"Closed Won")*VLOOKUP("Closed Won",$B$211:$C$217,2,FALSE()) -> 482216.67 | X191: =SUMIFS(W$6:W$65,$D$6:$D$65,"Closed Won")*VLOOKUP("Closed Won",$B$211:$C$217,2,FALSE()) -> 482216.67 | Y191: =SUMIFS(X$6:X$65,$D$6:$D$65,"Closed Won")*VLOOKUP("Closed Won",$B$211:$C$217,2,FALSE()) -> 482216.67 | Z191: =SUMIFS(Y$6:Y$65,$D$6:$D$65,"Closed Won")*VLOOKUP("Closed Won",$B$211:$C$217,2,FALSE()) -> 482216.67 | AA191: =SUMIFS(Z$6:Z$65,$D$6:$D$65,"Closed Won")*VLOOKUP("Closed Won",$B$211:$C$217,2,FALSE()) -> 482216.67 | AB191: =SUMIFS(AA$6:AA$65,$D$6:$D$65,"Closed Won")*VLOOKUP("Closed Won",$B$211:$C$217,2,FALSE()) -> 482216.67 | AC191: =SUMIFS(AB$6:AB$65,$D$6:$D$65,"Closed Won")*VLOOKUP("Closed Won",$B$211:$C$217,2,FALSE()) -> 482216.67 | ... AF191: =SUMIFS(AE$6:AE$65,$D$6:$D$65,"Closed Won")*VLOOKUP("Closed Won",$B$211:$C$217,2,FALSE()) -> 482216.67 | AG191: =SUM(U191:AF191) -> 5786600 | AH191: =T191+AG191 -> 9162116.7
B192: TOTAL PPI | L192: =SUM(L189:L191) -> 0 | M192: =SUM(M189:M191) -> 676091.67 | N192: =SUM(N189:N191) -> 978191.67 | O192: =SUM(O189:O191) -> 1031316.7 | P192: =SUM(P189:P191) -> 1031316.7 | Q192: =SUM(Q189:Q191) -> 1031316.7 | R192: =SUM(R189:R191) -> 1031316.7 | S192: =SUM(S189:S191) -> 1031316.7 | T192: =SUM(L192:S192) -> 6810866.7 | U192: =SUM(U189:U191) -> 1031316.7 | V192: =SUM(V189:V191) -> 1031316.7 | W192: =SUM(W189:W191) -> 1031316.7 | X192: =SUM(X189:X191) -> 1031316.7 | Y192: =SUM(Y189:Y191) -> 1031316.7 | Z192: =SUM(Z189:Z191) -> 1031316.7 | AA192: =SUM(AA189:AA191) -> 1031316.7 | AB192: =SUM(AB189:AB191) -> 1031316.7 | ... AF192: =SUM(AF189:AF191) -> 1031316.7 | AG192: =SUM(U192:AF192) -> 12375800 | AH192: =T192+AG192 -> 19186667
A195: LEGEND
A196: Blue text | B196: → Inputs (you fill these in)
A197: Black text | B197: → Formulas (auto-calculated)
A198: Green text | B198: → Mirrored from another section (e.g., Cost rows mirror Pipeline customers)
A199: Yellow fill | B199: → Key assumption / required input
A200: Grey fill | B200: → Field not applicable in this section
A201: Light blue fill | B201: → Year subtotal column (2026 Total / 2027 Total)
A202: Orange flag | B202: → Source Expected CY ≠ ACV/12 distribution (review)
A203: Note: | B203: Monthly amounts = ACV÷12 from Go-Live month onwards, continuing through Dec-27 (assumes contracts continue/renew past 12 months)
...

Sheet Pipeline Data Input
A1: PIPELINE DATA — paste your latest CRM export into rows 2-41 (account names, ACVs, stages, etc.). The main report will refresh automatically.
A2: # | B2: Warehouse (raw) | C2: Opportunity Name | D2: Account / Customer | E2: Owner | F2: Pallets | G2: SQM | H2: Source Exp CY | I2: ACV (Annual) | J2: Stage | K2: Go-Live Date | L2: Region | M2: Notes
A3: 1 | B3: DMM 2nd Ind | C3: ChampionX/DMM/WH/4000PP | D3: SLB | E3: Yazan Darwish | F3: 4000 | G3: 0 | H3: 1200000 | I3: 2400000 | J3: Prospecting | K3: 46204 | L3: East | M3: Opp: ChampionX/DMM/WH/4000PP | Region: East
A4: 2 | B4: DMM 2nd Ind | C4: NALCO/WH/DMM/4000PP | D4: NALCO Ecolab | E4: Yazan Darwish | F4: 4000 | G4: 0 | H4: 1400000 | I4: 2400000 | J4: Contract Negotiation | K4: 46174 | L4: East | M4: Opp: NALCO/WH/DMM/4000PP | Region: East
A5: 3 | B5: DMM 2nd Ind | C5: Synthomer/WH/DMM/1500PP | D5: Synthomer ME | E5: Yazan Darwish | F5: 1500 | G5: 0 | H5: 600000 | I5: 900000 | J5: Contract Negotiation | K5: 46157 | L5: East | M5: Opp: Synthomer/WH/DMM/1500PP | Region: East
A6: 4 | B6: DMM 2nd Ind | C6: Transworld/DMM/WH/500PP | D6: Transworld Saudi Logistics | E6: Yazan Darwish | F6: 500 | G6: 0 | H6: 280000 | I6: 420000 | J6: Proposal Sent | K6: 46143 | L6: East | M6: Opp: Transworld/DMM/WH/500PP | Region: East
A7: 5 | B7: DMM 2nd Ind | C7: Schmidt/WH/DMM2/400PP | D7: Schmidt | E7: Yazan Darwish | F7: 400 | G7: 0 | H7: 164000 | I7: 264000 | J7: Proposal Sent | K7: 46143 | L7: East | M7: Opp: Schmidt/WH/DMM2/400PP | Region: East
A8: 6 | B8: DMM 2nd Ind | C8: Zaghami/WH/DMM/250PP | D8: Zaghami | E8: Yazan Darwish | F8: 250 | G8: 0 | H8: 87500 | I8: 210000 | J8: Proposal Sent | K8: 46235 | L8: East | M8: Opp: Zaghami/WH/DMM/250PP | Region: East
A9: 7 | B9: DMM 2nd Ind | C9: Transworld/DMM/WH/250PP | D9: Transworld Saudi Logistics | E9: Yazan Darwish | F9: 250 | G9: 0 | H9: 113750 | I9: 162500 | J9: Proposal Sent | K9: 46174 | L9: East | M9: ⚠ Source Exp CY (113,750) ≠ ACV/12 implied (94,792) | Opp: Transworld/DMM/WH/250PP | Region: East
A10: 8 | B10: DMM 2nd Ind | C10: iEnergy/WH/DMM2/250PP | D10: i-Energy | E10: Yazan Darwish | F10: 250 | G10: 0 | H10: 100000 | I10: 150000 | J10: Proposal Sent | K10: 46143 | L10: East | M10: Opp: iEnergy/WH/DMM2/250PP | Region: East
A11: 9 | B11: DMM 2nd Ind | C11: FMS/DMM/WH/100PP | D11: FMS Group | E11: Yazan Darwish | F11: 100 | G11: 0 | H11: 35000 | I11: 50000 | J11: Proposal Sent | K11: 46174 | L11: East | M11: ⚠ Source Exp CY (35,000) ≠ ACV/12 implied (29,167) | Opp: FMS/DMM/WH/100PP | Region: East
A12: 10 | B12: DMM 2nd Ind | C12: El Ajou Group/WH/DAMM2nd/100PP | D12: El Ajou Group | E12: Yazan Darwish | F12: 100 | G12: 0 | H12: 39000 | I12: 78000 | J12: Proposal Sent | K12: 46204 | L12: East | M12: Opp: El Ajou Group/WH/DAMM2nd/100PP | Region: East
A13: 11 | B13: Jubail 1 | C13: JAS/WH/JUB/1400PP | D13: JAS | E13: Yazan Darwish | F13: 1400 | G13: 0 | H13: 539000 | I13: 924000 | J13: Shortlisted | K13: 46174 | L13: East | M13: Opp: JAS/WH/JUB/1400PP | Region: East
A14: 12 | B14: Jubail 1 | C14: LXPantos/WH/JUB1/1000PP | D14: LX Pantos Logistics | E14: Yazan Darwish | F14: 1000 | G14: 0 | H14: 484000 | I14: 726000 | J14: Shortlisted | K14: 46143 | L14: East | M14: Opp: LXPantos/WH/JUB1/1000PP | Region: East
... A37: 35 | B37: Contract Logistics | C37: SNB / Asset Verification | D37: Saudi National Bank | E37: Hano Oberholzer | F37: 0 | G37: 0 | H37: 2257584 | I37: 1975386 | J37: Proposal Sent | K37: 46157 | L37: West | M37: ⚠ Source Exp CY (2,257,584) ≠ ACV/12 implied (1,316,924) | Opp: SNB / Asset Verification | Region: West
A38: 36 | B38: =IF('Closed-won data Input'!B3="","",'Closed-won data Input'!B3) -> DMM Port | C38: =IF('Closed-won data Input'!C3="","",'Closed-won data Input'!C3&" (Closed Won)") -> SAUDI CARBONATE COMPANY (Closed Won) | D38: =IF('Closed-won data Input'!C3="","",'Closed-won data Input'!C3) -> SAUDI CARBONATE COMPANY | E38: =IF('Closed-won data Input'!D3="","",'Closed-won data Input'!D3) -> Yazan Darwish | F38: =IF('Closed-won data Input'!E3="",0,'Closed-won data Input'!E3) -> 300 | G38: =IF('Closed-won data Input'!F3="",0,'Closed-won data Input'!F3) -> 0 | H38: =IF('Closed-won data Input'!G3="",0,'Closed-won data Input'!G3) -> 91200 | I38: =IF(OR('Closed-won data Input'!H3="",ISBLANK('Closed-won data Input'!H3)),0,'Closed-won data Input'!H3) -> 0 | J38: =IF('Closed-won data Input'!J3="","",'Closed-won data Input'!J3) -> Closed Won | K38: =IF('Closed-won data Input'!I3="","",'Closed-won data Input'!I3) -> 46143 | L38: East | M38: Closed Won — auto-pulled from Closed-won data Input row 3
A39: 37 | B39: =IF('Closed-won data Input'!B4="","",'Closed-won data Input'!B4) -> DMM 2nd Ind | C39: =IF('Closed-won data Input'!C4="","",'Closed-won data Input'!C4&" (Closed Won)") -> MEBCo (Clarios) (Closed Won) | D39: =IF('Closed-won data Input'!C4="","",'Closed-won data Input'!C4) -> MEBCo (Clarios) | E39: =IF('Closed-won data Input'!D4="","",'Closed-won data Input'!D4) -> Yazan Darwish | F39: =IF('Closed-won data Input'!E4="",0,'Closed-won data Input'!E4) -> 900 | G39: =IF('Closed-won data Input'!F4="",0,'Closed-won data Input'!F4) -> 0 | H39: =IF('Closed-won data Input'!G4="",0,'Closed-won data Input'!G4) -> 540000 | I39: =IF(OR('Closed-won data Input'!H4="",ISBLANK('Closed-won data Input'!H4)),0,'Closed-won data Input'!H4) -> 648000 | J39: =IF('Closed-won data Input'!J4="","",'Closed-won data Input'!J4) -> Closed Won | K39: =IF('Closed-won data Input'!I4="","",'Closed-won data Input'!I4) -> 46082 | L39: East | M39: Closed Won — auto-pulled from Closed-won data Input row 4
A40: 38 | B40: =IF('Closed-won data Input'!B5="","",'Closed-won data Input'!B5) -> DMM 2nd Ind | C40: =IF('Closed-won data Input'!C5="","",'Closed-won data Input'!C5&" (Closed Won)") -> Rawabi Electric (Closed Won) | D40: =IF('Closed-won data Input'!C5="","",'Closed-won data Input'!C5) -> Rawabi Electric | E40: =IF('Closed-won data Input'!D5="","",'Closed-won data Input'!D5) -> Yazan Darwish | F40: =IF('Closed-won data Input'!E5="",0,'Closed-won data Input'!E5) -> 440 | G40: =IF('Closed-won data Input'!F5="",0,'Closed-won data Input'!F5) -> 0 | H40: =IF('Closed-won data Input'!G5="",0,'Closed-won data Input'!G5) -> 211200 | I40: =IF(OR('Closed-won data Input'!H5="",ISBLANK('Closed-won data Input'!H5)),0,'Closed-won data Input'!H5) -> 105600 | J40: =IF('Closed-won data Input'!J5="","",'Closed-won data Input'!J5) -> Closed Won | K40: =IF('Closed-won data Input'!I5="","",'Closed-won data Input'!I5) -> 46049 | L40: East | M40: Closed Won — auto-pulled from Closed-won data Input row 5
A41: 39 | B41: =IF('Closed-won data Input'!B6="","",'Closed-won data Input'!B6) -> DMM 2nd Ind | C41: =IF('Closed-won data Input'!C6="","",'Closed-won data Input'!C6&" (Closed Won)") -> Dorfketal (Closed Won) | D41: =IF('Closed-won data Input'!C6="","",'Closed-won data Input'!C6) -> Dorfketal | E41: =IF('Closed-won data Input'!D6="","",'Closed-won data Input'!D6) -> Yazan Darwish | F41: =IF('Closed-won data Input'!E6="",0,'Closed-won data Input'!E6) -> 200 | G41: =IF('Closed-won data Input'!F6="",0,'Closed-won data Input'!F6) -> 0 | H41: =IF('Closed-won data Input'!G6="",0,'Closed-won data Input'!G6) -> 86400 | I41: =IF(OR('Closed-won data Input'!H6="",ISBLANK('Closed-won data Input'!H6)),0,'Closed-won data Input'!H6) -> 78000 | J41: =IF('Closed-won data Input'!J6="","",'Closed-won data Input'!J6) -> Closed Won | K41: =IF('Closed-won data Input'!I6="","",'Closed-won data Input'!I6) -> 46143 | L41: East | M41: Closed Won — auto-pulled from Closed-won data Input row 6
A42: 40 | B42: =IF('Closed-won data Input'!B7="","",'Closed-won data Input'!B7) -> DMM 2nd Ind | C42: =IF('Closed-won data Input'!C7="","",'Closed-won data Input'!C7&" (Closed Won)") -> Rising Future (Closed Won) | D42: =IF('Closed-won data Input'!C7="","",'Closed-won data Input'!C7) -> Rising Future | E42: =IF('Closed-won data Input'!D7="","",'Closed-won data Input'!D7) -> Yazan Darwish | F42: =IF('Closed-won data Input'!E7="",0,'Closed-won data Input'!E7) -> 50 | G42: =IF('Closed-won data Input'!F7="",0,'Closed-won data Input'!F7) -> 0 | H42: =IF('Closed-won data Input'!G7="",0,'Closed-won data Input'!G7) -> 25000 | I42: =IF(OR('Closed-won data Input'!H7="",ISBLANK('Closed-won data Input'!H7)),0,'Closed-won data Input'!H7) -> 30000 | J42: =IF('Closed-won data Input'!J7="","",'Closed-won data Input'!J7) -> Closed Won | K42: =IF('Closed-won data Input'!I7="","",'Closed-won data Input'!I7) -> 46082 | L42: East | M42: Closed Won — auto-pulled from Closed-won data Input row 7
A43: 41 | B43: =IF('Closed-won data Input'!B8="","",'Closed-won data Input'!B8) -> Jubail 1 | C43: =IF('Closed-won data Input'!C8="","",'Closed-won data Input'!C8&" (Closed Won)") -> Maaden (Closed Won) | D43: =IF('Closed-won data Input'!C8="","",'Closed-won data Input'!C8) -> Maaden | E43: =IF('Closed-won data Input'!D8="","",'Closed-won data Input'!D8) -> Yazan Darwish | F43: =IF('Closed-won data Input'!E8="",0,'Closed-won data Input'!E8) -> 1200 | G43: =IF('Closed-won data Input'!F8="",0,'Closed-won data Input'!F8) -> 0 | H43: =IF('Closed-won data Input'!G8="",0,'Closed-won data Input'!G8) -> 880000 | I43: =IF(OR('Closed-won data Input'!H8="",ISBLANK('Closed-won data Input'!H8)),0,'Closed-won data Input'!H8) -> 960000 | J43: =IF('Closed-won data Input'!J8="","",'Closed-won data Input'!J8) -> Closed Won | K43: =IF('Closed-won data Input'!I8="","",'Closed-won data Input'!I8) -> 46054 | L43: East | M43: Closed Won — auto-pulled from Closed-won data Input row 8
A44: 42 | B44: =IF('Closed-won data Input'!B9="","",'Closed-won data Input'!B9) -> JED Modon 3B | C44: =IF('Closed-won data Input'!C9="","",'Closed-won data Input'!C9&" (Closed Won)") -> Al Nahdi (Closed Won) | D44: =IF('Closed-won data Input'!C9="","",'Closed-won data Input'!C9) -> Al Nahdi | E44: =IF('Closed-won data Input'!D9="","",'Closed-won data Input'!D9) -> Simon Reah | F44: =IF('Closed-won data Input'!E9="",0,'Closed-won data Input'!E9) -> 4000 | G44: =IF('Closed-won data Input'!F9="",0,'Closed-won data Input'!F9) -> 0 | H44: =IF('Closed-won data Input'!G9="",0,'Closed-won data Input'!G9) -> 756000 | I44: =IF(OR('Closed-won data Input'!H9="",ISBLANK('Closed-won data Input'!H9)),0,'Closed-won data Input'!H9) -> 756000 | J44: =IF('Closed-won data Input'!J9="","",'Closed-won data Input'!J9) -> Closed Won | K44: =IF('Closed-won data Input'!I9="","",'Closed-won data Input'!I9) -> 46113 | L44: West | M44: Closed Won — auto-pulled from Closed-won data Input row 9
A45: 43 | B45: =IF('Closed-won data Input'!B10="","",'Closed-won data Input'!B10) -> JED Modon 3B | C45: =IF('Closed-won data Input'!C10="","",'Closed-won data Input'!C10&" (Closed Won)") -> Sharbatly Fruit Company (Closed Won) | D45: =IF('Closed-won data Input'!C10="","",'Closed-won data Input'!C10) -> Sharbatly Fruit Company | E45: =IF('Closed-won data Input'!D10="","",'Closed-won data Input'!D10) -> Simon Reah | F45: =IF('Closed-won data Input'!E10="",0,'Closed-won data Input'!E10) -> 1500 | G45: =IF('Closed-won data Input'!F10="",0,'Closed-won data Input'!F10) -> 0 | H45: =IF('Closed-won data Input'!G10="",0,'Closed-won data Input'!G10) -> 513000 | I45: =IF(OR('Closed-won data Input'!H10="",ISBLANK('Closed-won data Input'!H10)),0,'Closed-won data Input'!H10) -> 684000 | J45: =IF('Closed-won data Input'!J10="","",'Closed-won data Input'!J10) -> Closed Won | K45: =IF('Closed-won data Input'!I10="","",'Closed-won data Input'!I10) -> 46127 | L45: West | M45: Closed Won — auto-pulled from Closed-won data Input row 10
A46: 44 | B46: =IF('Closed-won data Input'!B11="","",'Closed-won data Input'!B11) -> Subcontractor | C46: =IF('Closed-won data Input'!C11="","",'Closed-won data Input'!C11&" (Closed Won)") -> PSA-BDP (Closed Won) | D46: =IF('Closed-won data Input'!C11="","",'Closed-won data Input'!C11) -> PSA-BDP | E46: =IF('Closed-won data Input'!D11="","",'Closed-won data Input'!D11) -> Amin AlHalabi | F46: =IF('Closed-won data Input'!E11="",0,'Closed-won data Input'!E11) -> 2500 | G46: =IF('Closed-won data Input'!F11="",0,'Closed-won data Input'!F11) -> 0 | H46: =IF('Closed-won data Input'!G11="",0,'Closed-won data Input'!G11) -> 1650000 | I46: =IF(OR('Closed-won data Input'!H11="",ISBLANK('Closed-won data Input'!H11)),0,'Closed-won data Input'!H11) -> 1800000 | J46: =IF('Closed-won data Input'!J11="","",'Closed-won data Input'!J11) -> Closed Won | K46: =IF('Closed-won data Input'!I11="","",'Closed-won data Input'!I11) -> 46067 | L46: Central | M46: Closed Won — auto-pulled from Closed-won data Input row 11
A47: 45 | B47: =IF('Closed-won data Input'!B12="","",'Closed-won data Input'!B12) -> Contract Logistics | C47: =IF('Closed-won data Input'!C12="","",'Closed-won data Input'!C12&" (Closed Won)") -> Tasnee (Closed Won) | D47: =IF('Closed-won data Input'!C12="","",'Closed-won data Input'!C12) -> Tasnee | E47: =IF('Closed-won data Input'!D12="","",'Closed-won data Input'!D12) -> Yazan Darwish | F47: =IF('Closed-won data Input'!E12="",0,'Closed-won data Input'!E12) -> 0 | G47: =IF('Closed-won data Input'!F12="",0,'Closed-won data Input'!F12) -> 0 | H47: =IF('Closed-won data Input'!G12="",0,'Closed-won data Input'!G12) -> 1450000 | I47: =IF(OR('Closed-won data Input'!H12="",ISBLANK('Closed-won data Input'!H12)),0,'Closed-won data Input'!H12) -> 725000 | J47: =IF('Closed-won data Input'!J12="","",'Closed-won data Input'!J12) -> Closed Won | K47: =IF('Closed-won data Input'!I12="","",'Closed-won data Input'!I12) -> 46143 | L47: East | M47: Closed Won — auto-pulled from Closed-won data Input row 12
A48: 46
A49: 47
A50: 48
A51: 49
A52: 50
A53: 51
A54: 52
A55: 53
A56: 54
A57: 55
A58: 56
A59: 57
... A62: 60
A64: WAREHOUSE NAME MAPPING — raw CRM names (col A) → report labels (col B). Add rows here if new warehouse names appear in your CRM.
A65: Raw Name (CRM) | B65: Mapped Name (Report)
A66: DMM 2nd Ind | B66: Dammam 2nd Ind -Tad WH
A67: Jubail 1 | B67: Jubail 1
A68: Jubail 2 | B68: Jubail 2
A69: JED Modon 3A | B69: Jeddah Modon 3A
A70: JED Modon 3B | B70: Jeddah Modon 3B
A71: RUH Tayba | B71: RUH Tayba
A72: Subcontractor | B72: Subcontractor
A73: Contract Logistics | B73: Contract Logistics
A74: DMM Port | B74: Dammam Port

Sheet Warehouse Pallet data input
A1: WAREHOUSE SNAPSHOT — paste the latest capacity dashboard here. Column A must use REPORT labels (e.g., 'Dammam Port', 'Jubail Total') so Section 4 finds them via VLOOKUP. Empty rows (Subcontractor, etc.) return 0 and are fine. Jubail tip: as soon as you fill Jubail 1 and Jubail 2 individually, Section 4 auto-switches to split mode and ignores the Jubail Total row.
A2: Warehouse (Report Label) | B2: Region | C2: Total Locations | D2: Total Capacity | E2: Occupied Capacity | F2: Utilization % | G2: Sellable Capacity | H2: Committed Capacity | I2: Blocked Locations | J2: Virtual Locations | K2: Shortfall Capacity
A3: Definition | C3: Physical Rac locations | D3: Bin + Manual | E3: Physical + Floor + Manual | G3: Free to sell Now | H3: Min Commited per customer | K3: Unfilled commitment gap
A4: Dammam Port | B4: Dammam | C4: 28694 | D4: 34755 | E4: 29782 | F4: =IFERROR(E4/D4,0) -> 0.85691267 | G4: 4973 | H4: 23400 | K4: 6156
A5: Dammam 2nd Ind -Tad WH | B5: Dammam | C5: 16153 | D5: 18654 | E5: 8607 | F5: =IFERROR(E5/D5,0) -> 0.46140238 | G5: 10047 | I5: 3619 | K5: 0
A6: Jubail 1 | B6: Jubail | C6: =B25 -> 31172 | D6: =C25 -> 35542 | E6: =D25 -> 11836 | F6: =IFERROR(E6/D6,0) -> 0.33301446 | G6: =F25 -> 23706 | H6: =G25 -> 13157 | I6: 146 | J6: 144 | K6: =H25 -> 10498
A7: Jubail 2 | B7: Jubail | C7: =B29 -> 8152 | D7: =C29 -> 29258 | E7: =D29 -> 10011 | F7: =IFERROR(E7/D7,0) -> 0.34216283 | G7: =F29 -> 19247 | H7: =G29 -> 0 | K7: =H29 -> 0
A8: Jubail Total | B8: Jubail | C8: =C6+C7 -> 39324 | D8: =D6+D7 -> 64800 | E8: =E6+E7 -> 21847 | F8: =IFERROR(E8/D8,0) -> 0.33714506 | G8: =G6+G7 -> 42953 | H8: =H6+H7 -> 13157 | I8: =I6+I7 -> 146 | J8: =J6+J7 -> 144 | K8: =K6+K7 -> 10498
A9: Jeddah Modon 3A | B9: Jeddah | C9: 36212 | D9: 36840 | E9: 17127 | F9: =IFERROR(E9/D9,0) -> 0.46490228 | G9: 19713 | H9: 300 | I9: 9038 | J9: 134 | K9: 70
A10: Jeddah Modon 3B | B10: Jeddah | C10: 12177 | D10: 14189 | E10: 13503 | F10: =IFERROR(E10/D10,0) -> 0.95165269 | G10: 686 | H10: 2600 | I10: 3734 | K10: 752
A11: RUH Tayba | B11: Riyadh | D11: 11132 | E11: 8134 | F11: =IFERROR(E11/D11,0) -> 0.73068631 | G11: 2998 | H11: 317 | K11: 77
A12: Subcontractor | B12: Jeddah (UWC/BDP-Hempel) | F12: =IFERROR(E12/D12,0) -> 0 | G12: =D20 -> 7500
A13: Contract Logistics | F13: =IFERROR(E13/D13,0) -> 0
A14: All | C14: =SUM(C4:C13)-IF((C6+C7)<>0,C8,0) -> 132560 | D14: =SUM(D4:D13)-IF((D6+D7)<>0,D8,0) -> 180370 | E14: =SUM(E4:E13)-IF((E6+E7)<>0,E8,0) -> 99000 | F14: =IFERROR(E14/D14,0) -> 0.54887176 | G14: =SUM(G4:G13)-IF((G6+G7)<>0,G8,0) -> 88870 | H14: =SUM(H4:H13)-IF((H6+H7)<>0,H8,0) -> 39774 | I14: =SUM(I4:I13)-IF((I6+I7)<>0,I8,0) -> 16537 | J14: =SUM(J4:J13)-IF((J6+J7)<>0,J8,0) -> 278 | K14: =SUM(K4:K13)-IF((K6+K7)<>0,K8,0) -> 17553
A17: Subcontractor | B17: Baxter/WH/RUH/2500PP | C17: Baxter | D17: 2500
A18: Subcontractor | B18: AL Nahdi/WH/RUH/2000PP | C18: Al Nahdi | D18: 2500
A19: Subcontractor | B19: PSA-BDP (Closed Won) | C19: PSA-BDP | D19: 2500
D20: =SUM(D17:D19) -> 7500
A23: 🏗️ JUBAIL BREAKDOWN — by Chamber
A24: Facility | B24: Total Locations | C24: Total Capacity | D24: Occupied | E24: Util % | F24: Sellable | G24: Committed | H24: Shortfall
A25: Jubail 1 | B25: =SUM(B26:B28) -> 31172 | C25: =SUM(C26:C28) -> 35542 | D25: =SUM(D26:D28) -> 11836 | E25: =IFERROR(D25/C25,0) -> 0.33301446 | F25: =SUM(F26:F28) -> 23706 | G25: 13157 | H25: 10498
A26: ↳ CHM-01 | B26: 9261 | C26: 10533 | D26: 1331 | E26: =IFERROR(D26/C26,0) -> 0.12636476 | F26: 9202
A27: ↳ CHM-02 | B27: 21811 | C27: 24884 | D27: 10450 | E27: =IFERROR(D27/C27,0) -> 0.41994856 | F27: 14434
A28: ↳ FLO-02 | B28: 100 | C28: 125 | D28: 55 | E28: =IFERROR(D28/C28,0) -> 0.44 | F28: 70
A29: Jubail 2 (CHM-03) | B29: 8152 | C29: 29258 | D29: 10011 | E29: =IFERROR(D29/C29,0) -> 0.34216283 | F29: 19247 | G29: 0 | H29: 0
A30: Jubail Total (Jub 1 + Jub 2) | B30: =B25+B29 -> 39324 | C30: =C25+C29 -> 64800 | D30: =D25+D29 -> 21847 | E30: =IFERROR(D30/C30,0) -> 0.33714506 | F30: =F25+F29 -> 42953 | G30: =G25+G29 -> 13157 | H30: =H25+H29 -> 10498
A32: Methodology: chamber-summed math is now the source of truth. Total Locations & Capacity tie cleanly to the system rollup (39,324 / 64,800). Occupied & Sellable use chamber sums (21,847 / 42,953) — the system's Total view counts ~10,854 more pallets as Occupied that the chamber view classifies as Sellable. Committed (13,157) and Shortfall (10,498) are warehouse-level metrics — parked on Jubail 1's row so Row 30 sums correctly. Blocked (146) & Virtual (144) likewise live on Jubail 1's row in the main snapshot table.

Sheet Revenue Data Input
C1: P03 | D1: Hala Supply Chain Services Co. Ltd
D2: Manament Accounts YTD P03 2026
D3: Profit and Loss | F3: YTD P03 2026 Actual | T3: 2026 Budget | AH3: Prior Year 2025
A4: Codes | B4: Legacy | D4: Description | F4: P1 Act | G4: P2 Act | H4: P3 Act | I4: P4 Act | J4: P5 Act | K4: P6 Act | L4: P7 Act | M4: P8 Act | N4: P9 Act | O4: P10 Act | P4: P11 Act | Q4: P12 Act | R4: Total | T4: P1 Bud | U4: P2 Bud | V4: P3 Bud | W4: P4 Bud | X4: P5 Bud | Y4: P6 Bud | Z4: P7 Bud | AA4: P8 Bud | AB4: P9 Bud | AC4: P10 Bud | AD4: P11 Bud | AE4: P12 Bud | AF4: Total | AH4: P1 Act | AI4: P2 Act | AJ4: P3 Act | AK4: P4 Act | AL4: P5 Act | AM4: P6 Act | AN4: P7 Act | AO4: P8 Act | AP4: P9 Act | AQ4: P10 Act | AR4: P11 Act | AS4: P12 Act | AT4: Total FINAL
